Workbook

Sheet READ ME
A1: New Excel Bidding Spreadsheet: How It Works
A2: Rebuilt from 'Template-Empty - WORK IN PROGRESS.xlsm'. Full transparent cost first, margin added on top.
B4: FLOW
B5: 1. INPUTS | C5: Project info, durations, PST, consumables, contingency, target margin per division, levels, your typical COGS %.
B6: 2. LABOUR RATES | C6: Crew mix per trade (same layout as the original PRJ INFO rates block), shown beside Knowify actual rates and mix.
B7: 3. PLUMBING EST / HVAC EST | C7: One row per item: Qty x Material $/unit and Qty x Hrs/unit. Same columns on both sheets so HVAC ties back exactly like Plumbing.
B8: 4. SUBS & GC | C8: Subtrade quotes and general conditions. Allocate by % to each division, or leave % blank to auto-split by direct cost.
B9: 5. BID SUMMARY | C9: Cost by type and division, then margin. COGS mix vs your Knowify job and vs your typical %. Holds every tie-out check.
B10: 6. BUDGET | C10: Cost budget per division and phase. Phases match Knowify, so the field budget and the actuals line up.
B11: 7. SCHEDULE OF VALUES | C11: Contract split into Knowify-style lines (e.g. 'P - BLDG A - L1 Plumbing Rough-in (Labour)'), with the Knowify cost budget for each line.
B12: 8. KNOWIFY PHASES / TIME | C12: Paste the 'Actual vs Budget - Phases' and 'Time' sheets from a Knowify Job Summary export, cell A1, exactly as exported.
B13: 9. KNOWIFY REVIEW | C13: Reads the two paste tabs: margin after overhead, cost mix, actual crew rates and mix, and how each phase ran vs its budget.
B14: 10. AUDIT NOTES | C14: Formula problems found in the original template, decisions made, and open questions.
B16: COLOUR LEGEND
B17: Blue text, light yellow fill | C17: Input. Type here.
B18: Bright yellow fill | C18: Key assumption. Review on every bid.
B19: Black text | C19: Formula. Do not type over.
B20: Green text | C20: Link from another tab.
B22: MARGIN vs MARKUP
C23: This workbook prices with MARGIN: Contract = Total Cost / (1 - Margin %).
C24: Example: cost $100,000 at 15% margin = $117,647 contract, $17,647 gross profit (17.6% markup).
C25: The original template used 15% MARKUP: $100,000 x 1.15 = $115,000, which is only a 13.0% margin.
B27: PHASES (match Knowify)
C28: Tag each estimate row with the phase the WORK happens in. Rough-in and finishing rows carry both labour and material.
C29: Labour on 03 Rough-in and 04 Finishing is split by level on the SOV; their material rolls into 05 Material Supply automatically,
C30: the same way Knowify jobs are set up (level lines are labour only, material supply is its own line).
B32: UPDATING KNOWIFY DATA
C33: 1. In Knowify, open the job > Summary > Project Summary report and download the Excel file.
C34: 2. In that file, select the used cells of 'Actual vs Budget - Phases' (A1 to column V, last row). Copy.
C35: 3. Paste into cell A1 of KNOWIFY PHASES (clear old data first). Do the same for the 'Time' sheet into KNOWIFY TIME.
C36: 4. On KNOWIFY REVIEW, type the job name, contract (Total Amount) and committed cost from the export's Summary sheet.
C37: 5. If a role or phase shows 'Unmapped', add it to the mapping tables on the right of KNOWIFY REVIEW.

Sheet INPUTS
A1: INPUTS
A2: Blue cells are inputs. Bright yellow = key assumption to review on every bid.
B3: PROJECT INFORMATION
B4: Project Name
B5: Quote Number
B6: Project Type | C6: Multi-Family
B7: Owner
B8: General Contractor
B9: Architect
B10: Mech. Engineer
B11: Site Address | C11: 2650 East 41st Ave
B12: City | C12: Vancouver
B13: Proposal Date
B14: Proposal Rev
B15: Prepared By | C15: Paris Mechanical Ltd
B16: Drawings | C16: Issued For Tender
B17: Gross Floor Area (sq ft)
B18: Number of Units | C18: =D64 -> 123
B20: KEY ASSUMPTIONS
B21: P&H project duration (months) | C21: 24 | G21: From original PRJ INFO H34.
B22: HVAC project duration (months) | C22: 24 | G22: From original PRJ INFO H43.
B23: PST on materials | C23: 0.07 | G23: BC PST 7%. From original PRJ INFO H52. Applied to material rows marked Y.
B24: GST (shown on proposal only, not a cost) | C24: 0.05 | G24: From original PRJ INFO H51. GST is recoverable, so it is not in cost.
B25: Consumables (% of material) | C25: 0.02 | G25: Original used 2% of material (P&H SUMMARY H46, HVAC SUMMARY D30).
B26: Contingency (% of direct cost) | C26: 0 | G26: Optional risk allowance. Kept as its own line so it stays visible.
B27: Warranty reserve (% of fixture & equipment supply) | C27: 0.02 | G27: Original: 2 years x 1% of equipment+fixtures (PRJ SUMMARY rows 75-78).
B28: Contract rounding (round up to nearest $) | C28: 100 | G28: Original rounded each division up to the nearest $100.
B29: Holdback (BC Builders Lien Act) | C29: 0.1 | G29: Used on the SOV for progress billing.
B31: TARGET MARGIN BY DIVISION
B32: Division | C32: Code | D32: Target Margin % | E32: Equivalent Markup % | F32: Crew
B33: Plumbing | C33: P | D33: 0.15 | E33: =IFERROR(D33/(1-D33),0) -> 0.17647059 | F33: P&H | G33: Margin = profit / contract. 15% is a placeholder: set your real target.
B34: Hydronic | C34: H | D34: 0.15 | E34: =IFERROR(D34/(1-D34),0) -> 0.17647059 | F34: P&H | G34: Division names feed the SOV line names (Knowify uses 'HVAC'
B35: Ventilation | C35: V | D35: 0.15 | E35: =IFERROR(D35/(1-D35),0) -> 0.17647059 | F35: HVAC | G35: for ventilation; rename here if you prefer that).
B36: Air Conditioning | C36: AC | D36: 0.15 | E36: =IFERROR(D36/(1-D36),0) -> 0.17647059 | F36: HVAC
B38: LEVELS (SOV splits rough-in and finishing labour by level)
B39: Tag (e.g. BLDG A - L1) | C39: Floor | D39: Units | E39: SOV Weight %
B40: U/G | C40: Ground Work | E40: =IFERROR(D40/$D$64,0) -> 0 | G40: Units per level from original PRJ INFO C6:C10.
B41: P-02 | C41: Parking 2 | E41: =IFERROR(D41/$D$64,0) -> 0 | G41: Weight defaults to units share. Type over it to give parking,
B42: PRKG | C42: Parking 1 | E42: =IFERROR(D42/$D$64,0) -> 0 | G42: U/G or roof a share. Weights must total 100%.
B43: L-01 | C43: Level 1 | D43: 24 | E43: =IFERROR(D43/$D$64,0) -> 0.19512195 | G43: Multi-building jobs: use tags like 'BLDG A - L1' to match Knowify.
B44: L-02 | C44: Level 2 | D44: 25 | E44: =IFERROR(D44/$D$64,0) -> 0.20325203
B45: L-03 | C45: Level 3 | D45: 25 | E45: =IFERROR(D45/$D$64,0) -> 0.20325203
B46: L-04 | C46: Level 4 | D46: 25 | E46: =IFERROR(D46/$D$64,0) -> 0.20325203
B47: L-05 | C47: Level 5 | D47: 24 | E47: =IFERROR(D47/$D$64,0) -> 0.19512195
B48: L-06 | C48: Level 6 | E48: =IFERROR(D48/$D$64,0) -> 0
B49: L-07 | C49: Level 7 | E49: =IFERROR(D49/$D$64,0) -> 0
B50: L-08 | C50: Level 8 | E50: =IFERROR(D50/$D$64,0) -> 0
B51: L-09 | C51: Level 9 | E51: =IFERROR(D51/$D$64,0) -> 0
B52: L-10 | C52: Level 10 | E52: =IFERROR(D52/$D$64,0) -> 0
B53: ROOF | C53: Roof | E53: =IFERROR(D53/$D$64,0) -> 0
E54: =IFERROR(D54/$D$64,0) -> 0
E55: =IFERROR(D55/$D$64,0) -> 0
E56: =IFERROR(D56/$D$64,0) -> 0
E57: =IFERROR(D57/$D$64,0) -> 0
E58: =IFERROR(D58/$D$64,0) -> 0
E59: =IFERROR(D59/$D$64,0) -> 0
E60: =IFERROR(D60/$D$64,0) -> 0
E61: =IFERROR(D61/$D$64,0) -> 0
E62: =IFERROR(D62/$D$64,0) -> 0
E63: =IFERROR(D63/$D$64,0) -> 0
B64: TOTAL | D64: =SUM(D40:D63) -> 123 | E64: =SUM(E40:E63) -> 1 | F64: =IF(ABS(E64-1)<0.0001,"OK","CHECK") -> OK
B66: PHASES (drop-down list used on every tab; matches Knowify setup)
B67: 01 Shop Drawings, Permits & Mobilization | G67: Rename freely but keep 9 rows and keep the order:
B68: 02 Foundation & Underground | G68: 03/04 are split by level; 05 collects 03/04 material.
B69: 03 Rough-in (Labour)
B70: 04 Finishing (Labour)
B71: 05 Material Supply
B72: 06 Fixtures & Equipment Supply
B73: 07 Testing, TAB & Commissioning
B74: 08 Completion & Final Documents
B75: 09 Office, Supervision & General
B77: YOUR TYPICAL COST OF GOODS (% of total cost)
B78: Cost Type | C78: Typical % of Total Cost
B79: Labour (wage + burden) | G79: Leave blank if unknown; BID SUMMARY compares only filled rows.
B80: Overhead
B81: Material: pipe, fittings, valves (incl. PST + consumables) | C81: 0.26 | G81: 26% of total COGS: from estimator (Oct 2026). On 405 Marie Place, material
B82: Fixtures & Equipment Supply | G82: excluding fixtures & equipment supply was 25.9% of cost.
B83: Subtrades
B84: General Conditions
B85: Contingency
B86: TOTAL | C86: =SUM(C79:C85) -> 0.26 | D86: =IF(COUNT(C79:C85)<7,"",IF(ABS(C86-1)<0.0001,"OK","CHECK"))

Sheet LABOUR RATES
A1: LABOUR RATES (crew mix)
A2: Same layout as the original PRJ INFO rates block. Both trades tie back the same way. | B2: UPDATED 2026-06-29
B4: PLUMBING & HYDRONIC CREW
B5: Classification | C5: Burdened Rate $/hr | D5: Crew Mix % | E5: Weighted $/hr | F5: Hours | G5: Cost by Wage Breakdown | H5: Knowify Actual $/hr | I5: Knowify Actual Mix
B6: Apprentice Lvl 1-2 | C6: 53 | D6: 0.4 | E6: =C6*D6 -> 21.2 | F6: =$C$15*D6 -> 590.4 | G6: =F6*C6 -> 31291.2 | H6: =IFERROR(INDEX('KNOWIFY REVIEW'!$E$66:$E$70,MATCH(B6,'KNOWIFY REVIEW'!$B$66:$B$70,0)),"") -> 40.248892 | I6: =IFERROR(INDEX('KNOWIFY REVIEW'!$F$66:$F$70,MATCH(B6,'KNOWIFY REVIEW'!$B$66:$B$70,0)),"") -> 0.36472509 | K6: Rates are fully burdened (confirmed): from original PRJ INFO D36:D40.
B7: Apprentice Lvl 3-6 | C7: 62.5 | D7: 0.3 | E7: =C7*D7 -> 18.75 | F7: =$C$15*D7 -> 442.8 | G7: =F7*C7 -> 27675 | H7: =IFERROR(INDEX('KNOWIFY REVIEW'!$E$66:$E$70,MATCH(B7,'KNOWIFY REVIEW'!$B$66:$B$70,0)),"") -> 47.102138 | I7: =IFERROR(INDEX('KNOWIFY REVIEW'!$F$66:$F$70,MATCH(B7,'KNOWIFY REVIEW'!$B$66:$B$70,0)),"") -> 0.24982948 | K7: Crew mix from original PRJ INFO E36:E40.
B8: Apprentice Lvl 7-8 | C8: 66.5 | D8: 0.05 | E8: =C8*D8 -> 3.325 | F8: =$C$15*D8 -> 73.8 | G8: =F8*C8 -> 4907.7 | H8: =IFERROR(INDEX('KNOWIFY REVIEW'!$E$66:$E$70,MATCH(B8,'KNOWIFY REVIEW'!$B$66:$B$70,0)),"") -> 51.21304 | I8: =IFERROR(INDEX('KNOWIFY REVIEW'!$F$66:$F$70,MATCH(B8,'KNOWIFY REVIEW'!$B$66:$B$70,0)),"") -> 0.085780851 | K8: Overhead $22/hr from original PRJ INFO H35/H44 (salaried staff, company wide).
B9: Journeyman Lvl 1-2 | C9: 73 | D9: 0.11 | E9: =C9*D9 -> 8.03 | F9: =$C$15*D9 -> 162.36 | G9: =F9*C9 -> 11852.28 | H9: =IFERROR(INDEX('KNOWIFY REVIEW'!$E$66:$E$70,MATCH(B9,'KNOWIFY REVIEW'!$B$66:$B$70,0)),"") -> 61.546529 | I9: =IFERROR(INDEX('KNOWIFY REVIEW'!$F$66:$F$70,MATCH(B9,'KNOWIFY REVIEW'!$B$66:$B$70,0)),"") -> 0.12010443 | K9: Knowify columns: company-wide actuals from KNOWIFY TIME (all trades together).
B10: Foreman & PM | C10: 96 | D10: 0.14 | E10: =C10*D10 -> 13.44 | F10: =$C$15*D10 -> 206.64 | G10: =F10*C10 -> 19837.44 | H10: =IFERROR(INDEX('KNOWIFY REVIEW'!$E$66:$E$70,MATCH(B10,'KNOWIFY REVIEW'!$B$66:$B$70,0)),"") -> 68.335403 | I10: =IFERROR(INDEX('KNOWIFY REVIEW'!$F$66:$F$70,MATCH(B10,'KNOWIFY REVIEW'!$B$66:$B$70,0)),"") -> 0.17956015 | K10: Knowify mix excludes 'Unmapped' roles, so it can total under 100%.
B11: Weighted average burdened wage | D11: =SUM(D6:D10) -> 1 | E11: =SUM(E6:E10) -> 64.745 | F11: =SUM(F6:F10) -> 1476 | G11: =SUM(G6:G10) -> 95563.62 | H11: ='KNOWIFY REVIEW'!$E$72 -> 50.502707 | I11: =SUM(I6:I10) -> 1
B12: Overhead $/hr (salaried staff, shop, office, insurance) | C12: 22
B13: FULLY LOADED RATE $/hr | C13: =E11+C12 -> 86.745
B14: Crew mix = 100% and hours x rate ties to breakdown | C14: =IF(AND(ABS(D11-1)<0.0001,ABS(G11-F11*E11)<1),"OK","CHECK") -> OK
B15: Estimated hours (from estimate tabs) | C15: =SUMIFS('PLUMBING EST'!$M$7:$M$156,'PLUMBING EST'!$B$7:$B$156,"P")+SUMIFS('HVAC EST'!$M$7:$M$156,'HVAC EST'!$B$7:$B$156,"P")+SUMIFS('PLUMBING EST'!$M$7:$M$156,'PLUMBING EST'!$B$7:$B$156,"H")+SUMIFS('HVAC EST'!$M$7:$M$156,'HVAC EST'!$B$7:$B$156,"H") -> 1476
B19: HVAC CREW (ventilation & A/C)
B20: Classification | C20: Burdened Rate $/hr | D20: Crew Mix % | E20: Weighted $/hr | F20: Hours | G20: Cost by Wage Breakdown | H20: Knowify Actual $/hr | I20: Knowify Actual Mix
B21: Apprentice Lvl 1-2 | C21: 53 | D21: 0.4 | E21: =C21*D21 -> 21.2 | F21: =$C$30*D21 -> 0 | G21: =F21*C21 -> 0 | H21: =IFERROR(INDEX('KNOWIFY REVIEW'!$E$66:$E$70,MATCH(B21,'KNOWIFY REVIEW'!$B$66:$B$70,0)),"") -> 40.248892 | I21: =IFERROR(INDEX('KNOWIFY REVIEW'!$F$66:$F$70,MATCH(B21,'KNOWIFY REVIEW'!$B$66:$B$70,0)),"") -> 0.36472509 | K21: Rates are fully burdened (confirmed): from original PRJ INFO D36:D40.
B22: Apprentice Lvl 3-6 | C22: 62.5 | D22: 0.3 | E22: =C22*D22 -> 18.75 | F22: =$C$30*D22 -> 0 | G22: =F22*C22 -> 0 | H22: =IFERROR(INDEX('KNOWIFY REVIEW'!$E$66:$E$70,MATCH(B22,'KNOWIFY REVIEW'!$B$66:$B$70,0)),"") -> 47.102138 | I22: =IFERROR(INDEX('KNOWIFY REVIEW'!$F$66:$F$70,MATCH(B22,'KNOWIFY REVIEW'!$B$66:$B$70,0)),"") -> 0.24982948 | K22: Crew mix from original PRJ INFO E36:E40.
B23: Apprentice Lvl 7-8 | C23: 66.5 | D23: 0.05 | E23: =C23*D23 -> 3.325 | F23: =$C$30*D23 -> 0 | G23: =F23*C23 -> 0 | H23: =IFERROR(INDEX('KNOWIFY REVIEW'!$E$66:$E$70,MATCH(B23,'KNOWIFY REVIEW'!$B$66:$B$70,0)),"") -> 51.21304 | I23: =IFERROR(INDEX('KNOWIFY REVIEW'!$F$66:$F$70,MATCH(B23,'KNOWIFY REVIEW'!$B$66:$B$70,0)),"") -> 0.085780851 | K23: Overhead $22/hr from original PRJ INFO H35/H44 (salaried staff, company wide).
B24: Journeyman Lvl 1-2 | C24: 73 | D24: 0.11 | E24: =C24*D24 -> 8.03 | F24: =$C$30*D24 -> 0 | G24: =F24*C24 -> 0 | H24: =IFERROR(INDEX('KNOWIFY REVIEW'!$E$66:$E$70,MATCH(B24,'KNOWIFY REVIEW'!$B$66:$B$70,0)),"") -> 61.546529 | I24: =IFERROR(INDEX('KNOWIFY REVIEW'!$F$66:$F$70,MATCH(B24,'KNOWIFY REVIEW'!$B$66:$B$70,0)),"") -> 0.12010443 | K24: Knowify columns: company-wide actuals from KNOWIFY TIME (all trades together).
B25: Foreman & PM | C25: 96 | D25: 0.14 | E25: =C25*D25 -> 13.44 | F25: =$C$30*D25 -> 0 | G25: =F25*C25 -> 0 | H25: =IFERROR(INDEX('KNOWIFY REVIEW'!$E$66:$E$70,MATCH(B25,'KNOWIFY REVIEW'!$B$66:$B$70,0)),"") -> 68.335403 | I25: =IFERROR(INDEX('KNOWIFY REVIEW'!$F$66:$F$70,MATCH(B25,'KNOWIFY REVIEW'!$B$66:$B$70,0)),"") -> 0.17956015 | K25: Knowify mix excludes 'Unmapped' roles, so it can total under 100%.
B26: Weighted average burdened wage | D26: =SUM(D21:D25) -> 1 | E26: =SUM(E21:E25) -> 64.745 | F26: =SUM(F21:F25) -> 0 | G26: =SUM(G21:G25) -> 0 | H26: ='KNOWIFY REVIEW'!$E$72 -> 50.502707 | I26: =SUM(I21:I25) -> 1
B27: Overhead $/hr (salaried staff, shop, office, insurance) | C27: 22
B28: FULLY LOADED RATE $/hr | C28: =E26+C27 -> 86.745
B29: Crew mix = 100% and hours x rate ties to breakdown | C29: =IF(AND(ABS(D26-1)<0.0001,ABS(G26-F26*E26)<1),"OK","CHECK") -> OK
B30: Estimated hours (from estimate tabs) | C30: =SUMIFS('PLUMBING EST'!$M$7:$M$156,'PLUMBING EST'!$B$7:$B$156,"V")+SUMIFS('HVAC EST'!$M$7:$M$156,'HVAC EST'!$B$7:$B$156,"V")+SUMIFS('PLUMBING EST'!$M$7:$M$156,'PLUMBING EST'!$B$7:$B$156,"AC")+SUMIFS('HVAC EST'!$M$7:$M$156,'HVAC EST'!$B$7:$B$156,"AC") -> 0
B33: RATE COMPARISON (per hour)
B34: Rate Basis | C34: $/hr | F34: P&H Est. Hours | G34: Labour (+OH) Cost
B35: Original template line items (Apprentice 1-2 only) | C35: =C6 -> 53 | F35: =$C$15 -> 1476 | G35: =C35*F35 -> 78228 | K35: If Knowify's cost per hour is well below the template rate, either Knowify
B36: Original template 'Budget with' (simple average) | C36: =AVERAGE(C6:C10) -> 70.2 | F36: =$C$15 -> 1476 | G36: =C36*F36 -> 103615.2 | K36: is missing burden, or the template rates are high. Settle which is true
B37: Crew-mix weighted burdened wage (this template) | C37: =E11 -> 64.745 | F37: =$C$15 -> 1476 | G37: =C37*F37 -> 95563.62 | K37: before trusting either for bids.
B38: Fully loaded: weighted wage + overhead | C38: =C13 -> 86.745 | F38: =$C$15 -> 1476 | G38: =C38*F38 -> 128035.62
B39: Knowify actual average cost per hour (job pasted) | C39: ='KNOWIFY REVIEW'!$E$72 -> 50.502707 | F39: =$C$15 -> 1476 | G39: =C39*F39 -> 74541.996
B40: Knowify actual + overhead | C40: ='KNOWIFY REVIEW'!$E$72+C12 -> 72.502707 | F40: =$C$15 -> 1476 | G40: =C40*F40 -> 107014

Sheet PLUMBING EST
A1: PLUMBING EST
A2: Plumbing (P) and Hydronic (H). Seed unit costs and hours from the original EQUIPMENT sheet.
A3: TOTALS | L3: =SUM(L7:L156) -> 105288 | M3: =SUM(M7:M156) -> 1476 | N3: =SUM(N7:N156) -> 95563.62 | O3: =SUM(O7:O156) -> 32472 | P3: =SUM(P7:P156) -> 233323.62
A4: Labour $ = Hours x crew-mix weighted burdened wage. Overhead $ = Hours x overhead $/hr. P/H rows use the P&H crew, V/AC rows use the HVAC crew. Q:R show how the same Div + Phase ran vs budget on the Knowify job pasted (1.30x = 30% over).
A6: Item Code | B6: Div | C6: Phase | D6: Description | E6: Qty | F6: Unit | G6: Material $/Unit | H6: Hrs/Unit | I6: Add Material $ | J6: Add Hrs | K6: PST? (Y/N) | L6: Material $ (incl PST) | M6: Hours | N6: Labour $ (wage+burden) | O6: Overhead $ | P6: TOTAL COST $ | Q6: Knowify Labour Actual/Budget | R6: Knowify Material Actual/Budget | S6: History Flag
A7: P-UG-SUMP | B7: P | C7: 02 Foundation & Underground | D7: Sumps & Interceptors | F7: ea | K7: Y | L7: =($E7*$G7+$I7)*(1+IF($K7="N",0,INPUTS!$C$23)) -> 0 | M7: =$E7*$H7+$J7 -> 0 | N7: =$M7*IF(OR($B7="V",$B7="AC"),'LABOUR RATES'!$E$26,'LABOUR RATES'!$E$11) -> 0 | O7: =$M7*IF(OR($B7="V",$B7="AC"),'LABOUR RATES'!$C$27,'LABOUR RATES'!$C$12) -> 0 | P7: =$L7+$N7+$O7 -> 0 | Q7: =IF(OR($B7="",$C7=""),"",IFERROR(SUMIFS('KNOWIFY REVIEW'!$AF$4:$AF$400,'KNOWIFY REVIEW'!$AB$4:$AB$400,$B7,'KNOWIFY REVIEW'!$AC$4:$AC$400,$C7,'KNOWIFY REVIEW'!$AD$4:$AD$400,1)/SUMIFS('KNOWIFY REVIEW'!$AE$4:$AE$400,'KNOWIFY REVIEW'!$AB$4:$AB$400,$B7,'KNOWIFY REVIEW'!$AC$4:$AC$400,$C7,'KNOWIFY REVIEW'!$AD$4:$AD$400,1),"")) -> 1.7292751 | R7: =IF(OR($B7="",$C7=""),"",IFERROR(SUMIFS('KNOWIFY REVIEW'!$AH$4:$AH$400,'KNOWIFY REVIEW'!$AB$4:$AB$400,$B7,'KNOWIFY REVIEW'!$AC$4:$AC$400,IF(OR($C7=INPUTS!$B$69,$C7=INPUTS!$B$70),INPUTS!$B$71,$C7),'KNOWIFY REVIEW'!$AD$4:$AD$400,1)/SUMIFS('KNOWIFY REVIEW'!$AG$4:$AG$400,'KNOWIFY REVIEW'!$AB$4:$AB$400,$B7,'KNOWIFY REVIEW'!$AC$4:$AC$400,IF(OR($C7=INPUTS!$B$69,$C7=INPUTS!$B$70),INPUTS!$B$71,$C7),'KNOWIFY REVIEW'!$AD$4:$AD$400,1),"")) -> 1.022045 | S7: =IF(MAX(N($Q7),N($R7))>1.1,"Past job ran over budget","") -> Past job ran over budget
A8: P-UG-STRM | B8: P | C8: 02 Foundation & Underground | D8: Storm Water & Drain Tile | F8: lf | K8: Y | L8: =($E8*$G8+$I8)*(1+IF($K8="N",0,INPUTS!$C$23)) -> 0 | M8: =$E8*$H8+$J8 -> 0 | N8: =$M8*IF(OR($B8="V",$B8="AC"),'LABOUR RATES'!$E$26,'LABOUR RATES'!$E$11) -> 0 | O8: =$M8*IF(OR($B8="V",$B8="AC"),'LABOUR RATES'!$C$27,'LABOUR RATES'!$C$12) -> 0 | P8: =$L8+$N8+$O8 -> 0 | Q8: =IF(OR($B8="",$C8=""),"",IFERROR(SUMIFS('KNOWIFY REVIEW'!$AF$4:$AF$400,'KNOWIFY REVIEW'!$AB$4:$AB$400,$B8,'KNOWIFY REVIEW'!$AC$4:$AC$400,$C8,'KNOWIFY REVIEW'!$AD$4:$AD$400,1)/SUMIFS('KNOWIFY REVIEW'!$AE$4:$AE$400,'KNOWIFY REVIEW'!$AB$4:$AB$400,$B8,'KNOWIFY REVIEW'!$AC$4:$AC$400,$C8,'KNOWIFY REVIEW'!$AD$4:$AD$400,1),"")) -> 1.7292751 | R8: =IF(OR($B8="",$C8=""),"",IFERROR(SUMIFS('KNOWIFY REVIEW'!$AH$4:$AH$400,'KNOWIFY REVIEW'!$AB$4:$AB$400,$B8,'KNOWIFY REVIEW'!$AC$4:$AC$400,IF(OR($C8=INPUTS!$B$69,$C8=INPUTS!$B$70),INPUTS!$B$71,$C8),'KNOWIFY REVIEW'!$AD$4:$AD$400,1)/SUMIFS('KNOWIFY REVIEW'!$AG$4:$AG$400,'KNOWIFY REVIEW'!$AB$4:$AB$400,$B8,'KNOWIFY REVIEW'!$AC$4:$AC$400,IF(OR($C8=INPUTS!$B$69,$C8=INPUTS!$B$70),INPUTS!$B$71,$C8),'KNOWIFY REVIEW'!$AD$4:$AD$400,1),"")) -> 1.022045 | S8: =IF(MAX(N($Q8),N($R8))>1.1,"Past job ran over budget","") -> Past job ran over budget
A9: P-UG-SAN | B9: P | C9: 02 Foundation & Underground | D9: Sanitary (underground) | F9: lf | K9: Y | L9: =($E9*$G9+$I9)*(1+IF($K9="N",0,INPUTS!$C$23)) -> 0 | M9: =$E9*$H9+$J9 -> 0 | N9: =$M9*IF(OR($B9="V",$B9="AC"),'LABOUR RATES'!$E$26,'LABOUR RATES'!$E$11) -> 0 | O9: =$M9*IF(OR($B9="V",$B9="AC"),'LABOUR RATES'!$C$27,'LABOUR RATES'!$C$12) -> 0 | P9: =$L9+$N9+$O9 -> 0 | Q9: =IF(OR($B9="",$C9=""),"",IFERROR(SUMIFS('KNOWIFY REVIEW'!$AF$4:$AF$400,'KNOWIFY REVIEW'!$AB$4:$AB$400,$B9,'KNOWIFY REVIEW'!$AC$4:$AC$400,$C9,'KNOWIFY REVIEW'!$AD$4:$AD$400,1)/SUMIFS('KNOWIFY REVIEW'!$AE$4:$AE$400,'KNOWIFY REVIEW'!$AB$4:$AB$400,$B9,'KNOWIFY REVIEW'!$AC$4:$AC$400,$C9,'KNOWIFY REVIEW'!$AD$4:$AD$400,1),"")) -> 1.7292751 | R9: =IF(OR($B9="",$C9=""),"",IFERROR(SUMIFS('KNOWIFY REVIEW'!$AH$4:$AH$400,'KNOWIFY REVIEW'!$AB$4:$AB$400,$B9,'KNOWIFY REVIEW'!$AC$4:$AC$400,IF(OR($C9=INPUTS!$B$69,$C9=INPUTS!$B$70),INPUTS!$B$71,$C9),'KNOWIFY REVIEW'!$AD$4:$AD$400,1)/SUMIFS('KNOWIFY REVIEW'!$AG$4:$AG$400,'KNOWIFY REVIEW'!$AB$4:$AB$400,$B9,'KNOWIFY REVIEW'!$AC$4:$AC$400,IF(OR($C9=INPUTS!$B$69,$C9=INPUTS!$B$70),INPUTS!$B$71,$C9),'KNOWIFY REVIEW'!$AD$4:$AD$400,1),"")) -> 1.022045 | S9: =IF(MAX(N($Q9),N($R9))>1.1,"Past job ran over budget","") -> Past job ran over budget
A10: P-UG-DW | B10: P | C10: 02 Foundation & Underground | D10: Domestic Water (underground) | F10: lf | K10: Y | L10: =($E10*$G10+$I10)*(1+IF($K10="N",0,INPUTS!$C$23)) -> 0 | M10: =$E10*$H10+$J10 -> 0 | N10: =$M10*IF(OR($B10="V",$B10="AC"),'LABOUR RATES'!$E$26,'LABOUR RATES'!$E$11) -> 0 | O10: =$M10*IF(OR($B10="V",$B10="AC"),'LABOUR RATES'!$C$27,'LABOUR RATES'!$C$12) -> 0 | P10: =$L10+$N10+$O10 -> 0 | Q10: =IF(OR($B10="",$C10=""),"",IFERROR(SUMIFS('KNOWIFY REVIEW'!$AF$4:$AF$400,'KNOWIFY REVIEW'!$AB$4:$AB$400,$B10,'KNOWIFY REVIEW'!$AC$4:$AC$400,$C10,'KNOWIFY REVIEW'!$AD$4:$AD$400,1)/SUMIFS('KNOWIFY REVIEW'!$AE$4:$AE$400,'KNOWIFY REVIEW'!$AB$4:$AB$400,$B10,'KNOWIFY REVIEW'!$AC$4:$AC$400,$C10,'KNOWIFY REVIEW'!$AD$4:$AD$400,1),"")) -> 1.7292751 | R10: =IF(OR($B10="",$C10=""),"",IFERROR(SUMIFS('KNOWIFY REVIEW'!$AH$4:$AH$400,'KNOWIFY REVIEW'!$AB$4:$AB$400,$B10,'KNOWIFY REVIEW'!$AC$4:$AC$400,IF(OR($C10=INPUTS!$B$69,$C10=INPUTS!$B$70),INPUTS!$B$71,$C10),'KNOWIFY REVIEW'!$AD$4:$AD$400,1)/SUMIFS('KNOWIFY REVIEW'!$AG$4:$AG$400,'KNOWIFY REVIEW'!$AB$4:$AB$400,$B10,'KNOWIFY REVIEW'!$AC$4:$AC$400,IF(OR($C10=INPUTS!$B$69,$C10=INPUTS!$B$70),INPUTS!$B$71,$C10),'KNOWIFY REVIEW'!$AD$4:$AD$400,1),"")) -> 1.022045 | S10: =IF(MAX(N($Q10),N($R10))>1.1,"Past job ran over budget","") -> Past job ran over budget
A11: P-RI-STRM | B11: P | C11: 03 Rough-in (Labour) | D11: DWV Storm Water | F11: lf | K11: Y | L11: =($E11*$G11+$I11)*(1+IF($K11="N",0,INPUTS!$C$23)) -> 0 | M11: =$E11*$H11+$J11 -> 0 | N11: =$M11*IF(OR($B11="V",$B11="AC"),'LABOUR RATES'!$E$26,'LABOUR RATES'!$E$11) -> 0 | O11: =$M11*IF(OR($B11="V",$B11="AC"),'LABOUR RATES'!$C$27,'LABOUR RATES'!$C$12) -> 0 | P11: =$L11+$N11+$O11 -> 0 | Q11: =IF(OR($B11="",$C11=""),"",IFERROR(SUMIFS('KNOWIFY REVIEW'!$AF$4:$AF$400,'KNOWIFY REVIEW'!$AB$4:$AB$400,$B11,'KNOWIFY REVIEW'!$AC$4:$AC$400,$C11,'KNOWIFY REVIEW'!$AD$4:$AD$400,1)/SUMIFS('KNOWIFY REVIEW'!$AE$4:$AE$400,'KNOWIFY REVIEW'!$AB$4:$AB$400,$B11,'KNOWIFY REVIEW'!$AC$4:$AC$400,$C11,'KNOWIFY REVIEW'!$AD$4:$AD$400,1),"")) -> 1.3492499 | R11: =IF(OR($B11="",$C11=""),"",IFERROR(SUMIFS('KNOWIFY REVIEW'!$AH$4:$AH$400,'KNOWIFY REVIEW'!$AB$4:$AB$400,$B11,'KNOWIFY REVIEW'!$AC$4:$AC$400,IF(OR($C11=INPUTS!$B$69,$C11=INPUTS!$B$70),INPUTS!$B$71,$C11),'KNOWIFY REVIEW'!$AD$4:$AD$400,1)/SUMIFS('KNOWIFY REVIEW'!$AG$4:$AG$400,'KNOWIFY REVIEW'!$AB$4:$AB$400,$B11,'KNOWIFY REVIEW'!$AC$4:$AC$400,IF(OR($C11=INPUTS!$B$69,$C11=INPUTS!$B$70),INPUTS!$B$71,$C11),'KNOWIFY REVIEW'!$AD$4:$AD$400,1),"")) -> 1.2924123 | S11: =IF(MAX(N($Q11),N($R11))>1.1,"Past job ran over budget","") -> Past job ran over budget
A12: P-RI-SAN | B12: P | C12: 03 Rough-in (Labour) | D12: DWV Sanitary (Drainage/Vents) | F12: lf | K12: Y | L12: =($E12*$G12+$I12)*(1+IF($K12="N",0,INPUTS!$C$23)) -> 0 | M12: =$E12*$H12+$J12 -> 0 | N12: =$M12*IF(OR($B12="V",$B12="AC"),'LABOUR RATES'!$E$26,'LABOUR RATES'!$E$11) -> 0 | O12: =$M12*IF(OR($B12="V",$B12="AC"),'LABOUR RATES'!$C$27,'LABOUR RATES'!$C$12) -> 0 | P12: =$L12+$N12+$O12 -> 0 | Q12: =IF(OR($B12="",$C12=""),"",IFERROR(SUMIFS('KNOWIFY REVIEW'!$AF$4:$AF$400,'KNOWIFY REVIEW'!$AB$4:$AB$400,$B12,'KNOWIFY REVIEW'!$AC$4:$AC$400,$C12,'KNOWIFY REVIEW'!$AD$4:$AD$400,1)/SUMIFS('KNOWIFY REVIEW'!$AE$4:$AE$400,'KNOWIFY REVIEW'!$AB$4:$AB$400,$B12,'KNOWIFY REVIEW'!$AC$4:$AC$400,$C12,'KNOWIFY REVIEW'!$AD$4:$AD$400,1),"")) -> 1.3492499 | R12: =IF(OR($B12="",$C12=""),"",IFERROR(SUMIFS('KNOWIFY REVIEW'!$AH$4:$AH$400,'KNOWIFY REVIEW'!$AB$4:$AB$400,$B12,'KNOWIFY REVIEW'!$AC$4:$AC$400,IF(OR($C12=INPUTS!$B$69,$C12=INPUTS!$B$70),INPUTS!$B$71,$C12),'KNOWIFY REVIEW'!$AD$4:$AD$400,1)/SUMIFS('KNOWIFY REVIEW'!$AG$4:$AG$400,'KNOWIFY REVIEW'!$AB$4:$AB$400,$B12,'KNOWIFY REVIEW'!$AC$4:$AC$400,IF(OR($C12=INPUTS!$B$69,$C12=INPUTS!$B$70),INPUTS!$B$71,$C12),'KNOWIFY REVIEW'!$AD$4:$AD$400,1),"")) -> 1.2924123 | S12: =IF(MAX(N($Q12),N($R12))>1.1,"Past job ran over budget","") -> Past job ran over budget
A13: P-RI-WR2 | B13: P | C13: 03 Rough-in (Labour) | D13: 2-Piece Bathroom (WC, LAV) | F13: ea | G13: 550 | H13: 3 | K13: Y | L13: =($E13*$G13+$I13)*(1+IF($K13="N",0,INPUTS!$C$23)) -> 0 | M13: =$E13*$H13+$J13 -> 0 | N13: =$M13*IF(OR($B13="V",$B13="AC"),'LABOUR RATES'!$E$26,'LABOUR RATES'!$E$11) -> 0 | O13: =$M13*IF(OR($B13="V",$B13="AC"),'LABOUR RATES'!$C$27,'LABOUR RATES'!$C$12) -> 0 | P13: =$L13+$N13+$O13 -> 0 | Q13: =IF(OR($B13="",$C13=""),"",IFERROR(SUMIFS('KNOWIFY REVIEW'!$AF$4:$AF$400,'KNOWIFY REVIEW'!$AB$4:$AB$400,$B13,'KNOWIFY REVIEW'!$AC$4:$AC$400,$C13,'KNOWIFY REVIEW'!$AD$4:$AD$400,1)/SUMIFS('KNOWIFY REVIEW'!$AE$4:$AE$400,'KNOWIFY REVIEW'!$AB$4:$AB$400,$B13,'KNOWIFY REVIEW'!$AC$4:$AC$400,$C13,'KNOWIFY REVIEW'!$AD$4:$AD$400,1),"")) -> 1.3492499 | R13: =IF(OR($B13="",$C13=""),"",IFERROR(SUMIFS('KNOWIFY REVIEW'!$AH$4:$AH$400,'KNOWIFY REVIEW'!$AB$4:$AB$400,$B13,'KNOWIFY REVIEW'!$AC$4:$AC$400,IF(OR($C13=INPUTS!$B$69,$C13=INPUTS!$B$70),INPUTS!$B$71,$C13),'KNOWIFY REVIEW'!$AD$4:$AD$400,1)/SUMIFS('KNOWIFY REVIEW'!$AG$4:$AG$400,'KNOWIFY REVIEW'!$AB$4:$AB$400,$B13,'KNOWIFY REVIEW'!$AC$4:$AC$400,IF(OR($C13=INPUTS!$B$69,$C13=INPUTS!$B$70),INPUTS!$B$71,$C13),'KNOWIFY REVIEW'!$AD$4:$AD$400,1),"")) -> 1.2924123 | S13: =IF(MAX(N($Q13),N($R13))>1.1,"Past job ran over budget","") -> Past job ran over budget
A14: P-RI-WR3T | B14: P | C14: 03 Rough-in (Labour) | D14: 3-Piece Bathroom (WC, LAV, TUB) | F14: ea | G14: 860 | H14: 5 | K14: Y | L14: =($E14*$G14+$I14)*(1+IF($K14="N",0,INPUTS!$C$23)) -> 0 | M14: =$E14*$H14+$J14 -> 0 | N14: =$M14*IF(OR($B14="V",$B14="AC"),'LABOUR RATES'!$E$26,'LABOUR RATES'!$E$11) -> 0 | O14: =$M14*IF(OR($B14="V",$B14="AC"),'LABOUR RATES'!$C$27,'LABOUR RATES'!$C$12) -> 0 | P14: =$L14+$N14+$O14 -> 0 | Q14: =IF(OR($B14="",$C14=""),"",IFERROR(SUMIFS('KNOWIFY REVIEW'!$AF$4:$AF$400,'KNOWIFY REVIEW'!$AB$4:$AB$400,$B14,'KNOWIFY REVIEW'!$AC$4:$AC$400,$C14,'KNOWIFY REVIEW'!$AD$4:$AD$400,1)/SUMIFS('KNOWIFY REVIEW'!$AE$4:$AE$400,'KNOWIFY REVIEW'!$AB$4:$AB$400,$B14,'KNOWIFY REVIEW'!$AC$4:$AC$400,$C14,'KNOWIFY REVIEW'!$AD$4:$AD$400,1),"")) -> 1.3492499 | R14: =IF(OR($B14="",$C14=""),"",IFERROR(SUMIFS('KNOWIFY REVIEW'!$AH$4:$AH$400,'KNOWIFY REVIEW'!$AB$4:$AB$400,$B14,'KNOWIFY REVIEW'!$AC$4:$AC$400,IF(OR($C14=INPUTS!$B$69,$C14=INPUTS!$B$70),INPUTS!$B$71,$C14),'KNOWIFY REVIEW'!$AD$4:$AD$400,1)/SUMIFS('KNOWIFY REVIEW'!$AG$4:$AG$400,'KNOWIFY REVIEW'!$AB$4:$AB$400,$B14,'KNOWIFY REVIEW'!$AC$4:$AC$400,IF(OR($C14=INPUTS!$B$69,$C14=INPUTS!$B$70),INPUTS!$B$71,$C14),'KNOWIFY REVIEW'!$AD$4:$AD$400,1),"")) -> 1.2924123 | S14: =IF(MAX(N($Q14),N($R14))>1.1,"Past job ran over budget","") -> Past job ran over budget
A15: P-RI-WR3S | B15: P | C15: 03 Rough-in (Labour) | D15: 3-Piece Bathroom (WC, LAV, SH) | F15: ea | G15: 860 | H15: 5 | K15: Y | L15: =($E15*$G15+$I15)*(1+IF($K15="N",0,INPUTS!$C$23)) -> 0 | M15: =$E15*$H15+$J15 -> 0 | N15: =$M15*IF(OR($B15="V",$B15="AC"),'LABOUR RATES'!$E$26,'LABOUR RATES'!$E$11) -> 0 | O15: =$M15*IF(OR($B15="V",$B15="AC"),'LABOUR RATES'!$C$27,'LABOUR RATES'!$C$12) -> 0 | P15: =$L15+$N15+$O15 -> 0 | Q15: =IF(OR($B15="",$C15=""),"",IFERROR(SUMIFS('KNOWIFY REVIEW'!$AF$4:$AF$400,'KNOWIFY REVIEW'!$AB$4:$AB$400,$B15,'KNOWIFY REVIEW'!$AC$4:$AC$400,$C15,'KNOWIFY REVIEW'!$AD$4:$AD$400,1)/SUMIFS('KNOWIFY REVIEW'!$AE$4:$AE$400,'KNOWIFY REVIEW'!$AB$4:$AB$400,$B15,'KNOWIFY REVIEW'!$AC$4:$AC$400,$C15,'KNOWIFY REVIEW'!$AD$4:$AD$400,1),"")) -> 1.3492499 | R15: =IF(OR($B15="",$C15=""),"",IFERROR(SUMIFS('KNOWIFY REVIEW'!$AH$4:$AH$400,'KNOWIFY REVIEW'!$AB$4:$AB$400,$B15,'KNOWIFY REVIEW'!$AC$4:$AC$400,IF(OR($C15=INPUTS!$B$69,$C15=INPUTS!$B$70),INPUTS!$B$71,$C15),'KNOWIFY REVIEW'!$AD$4:$AD$400,1)/SUMIFS('KNOWIFY REVIEW'!$AG$4:$AG$400,'KNOWIFY REVIEW'!$AB$4:$AB$400,$B15,'KNOWIFY REVIEW'!$AC$4:$AC$400,IF(OR($C15=INPUTS!$B$69,$C15=INPUTS!$B$70),INPUTS!$B$71,$C15),'KNOWIFY REVIEW'!$AD$4:$AD$400,1),"")) -> 1.2924123 | S15: =IF(MAX(N($Q15),N($R15))>1.1,"Past job ran over budget","") -> Past job ran over budget
A16: P-RI-WR4T | B16: P | C16: 03 Rough-in (Labour) | D16: 4-Piece Bathroom (WC, 2LAV, TUB) | F16: ea | G16: 990 | H16: 6 | K16: Y | L16: =($E16*$G16+$I16)*(1+IF($K16="N",0,INPUTS!$C$23)) -> 0 | M16: =$E16*$H16+$J16 -> 0 | N16: =$M16*IF(OR($B16="V",$B16="AC"),'LABOUR RATES'!$E$26,'LABOUR RATES'!$E$11) -> 0 | O16: =$M16*IF(OR($B16="V",$B16="AC"),'LABOUR RATES'!$C$27,'LABOUR RATES'!$C$12) -> 0 | P16: =$L16+$N16+$O16 -> 0 | Q16: =IF(OR($B16="",$C16=""),"",IFERROR(SUMIFS('KNOWIFY REVIEW'!$AF$4:$AF$400,'KNOWIFY REVIEW'!$AB$4:$AB$400,$B16,'KNOWIFY REVIEW'!$AC$4:$AC$400,$C16,'KNOWIFY REVIEW'!$AD$4:$AD$400,1)/SUMIFS('KNOWIFY REVIEW'!$AE$4:$AE$400,'KNOWIFY REVIEW'!$AB$4:$AB$400,$B16,'KNOWIFY REVIEW'!$AC$4:$AC$400,$C16,'KNOWIFY REVIEW'!$AD$4:$AD$400,1),"")) -> 1.3492499 | R16: =IF(OR($B16="",$C16=""),"",IFERROR(SUMIFS('KNOWIFY REVIEW'!$AH$4:$AH$400,'KNOWIFY REVIEW'!$AB$4:$AB$400,$B16,'KNOWIFY REVIEW'!$AC$4:$AC$400,IF(OR($C16=INPUTS!$B$69,$C16=INPUTS!$B$70),INPUTS!$B$71,$C16),'KNOWIFY REVIEW'!$AD$4:$AD$400,1)/SUMIFS('KNOWIFY REVIEW'!$AG$4:$AG$400,'KNOWIFY REVIEW'!$AB$4:$AB$400,$B16,'KNOWIFY REVIEW'!$AC$4:$AC$400,IF(OR($C16=INPUTS!$B$69,$C16=INPUTS!$B$70),INPUTS!$B$71,$C16),'KNOWIFY REVIEW'!$AD$4:$AD$400,1),"")) -> 1.2924123 | S16: =IF(MAX(N($Q16),N($R16))>1.1,"Past job ran over budget","") -> Past job ran over budget
A17: P-RI-WR4S | B17: P | C17: 03 Rough-in (Labour) | D17: 4-Piece Bathroom (WC, 2LAV, SH) | F17: ea | G17: 990 | H17: 6 | K17: Y | L17: =($E17*$G17+$I17)*(1+IF($K17="N",0,INPUTS!$C$23)) -> 0 | M17: =$E17*$H17+$J17 -> 0 | N17: =$M17*IF(OR($B17="V",$B17="AC"),'LABOUR RATES'!$E$26,'LABOUR RATES'!$E$11) -> 0 | O17: =$M17*IF(OR($B17="V",$B17="AC"),'LABOUR RATES'!$C$27,'LABOUR RATES'!$C$12) -> 0 | P17: =$L17+$N17+$O17 -> 0 | Q17: =IF(OR($B17="",$C17=""),"",IFERROR(SUMIFS('KNOWIFY REVIEW'!$AF$4:$AF$400,'KNOWIFY REVIEW'!$AB$4:$AB$400,$B17,'KNOWIFY REVIEW'!$AC$4:$AC$400,$C17,'KNOWIFY REVIEW'!$AD$4:$AD$400,1)/SUMIFS('KNOWIFY REVIEW'!$AE$4:$AE$400,'KNOWIFY REVIEW'!$AB$4:$AB$400,$B17,'KNOWIFY REVIEW'!$AC$4:$AC$400,$C17,'KNOWIFY REVIEW'!$AD$4:$AD$400,1),"")) -> 1.3492499 | R17: =IF(OR($B17="",$C17=""),"",IFERROR(SUMIFS('KNOWIFY REVIEW'!$AH$4:$AH$400,'KNOWIFY REVIEW'!$AB$4:$AB$400,$B17,'KNOWIFY REVIEW'!$AC$4:$AC$400,IF(OR($C17=INPUTS!$B$69,$C17=INPUTS!$B$70),INPUTS!$B$71,$C17),'KNOWIFY REVIEW'!$AD$4:$AD$400,1)/SUMIFS('KNOWIFY REVIEW'!$AG$4:$AG$400,'KNOWIFY REVIEW'!$AB$4:$AB$400,$B17,'KNOWIFY REVIEW'!$AC$4:$AC$400,IF(OR($C17=INPUTS!$B$69,$C17=INPUTS!$B$70),INPUTS!$B$71,$C17),'KNOWIFY REVIEW'!$AD$4:$AD$400,1),"")) -> 1.2924123 | S17: =IF(MAX(N($Q17),N($R17))>1.1,"Past job ran over budget","") -> Past job ran over budget
A18: P-RI-WR4TS | B18: P | C18: 03 Rough-in (Labour) | D18: 4-Piece Bathroom (WC, LAV, TUB & SH) | F18: ea | G18: 1310 | H18: 6 | K18: Y | L18: =($E18*$G18+$I18)*(1+IF($K18="N",0,INPUTS!$C$23)) -> 0 | M18: =$E18*$H18+$J18 -> 0 | N18: =$M18*IF(OR($B18="V",$B18="AC"),'LABOUR RATES'!$E$26,'LABOUR RATES'!$E$11) -> 0 | O18: =$M18*IF(OR($B18="V",$B18="AC"),'LABOUR RATES'!$C$27,'LABOUR RATES'!$C$12) -> 0 | P18: =$L18+$N18+$O18 -> 0 | Q18: =IF(OR($B18="",$C18=""),"",IFERROR(SUMIFS('KNOWIFY REVIEW'!$AF$4:$AF$400,'KNOWIFY REVIEW'!$AB$4:$AB$400,$B18,'KNOWIFY REVIEW'!$AC$4:$AC$400,$C18,'KNOWIFY REVIEW'!$AD$4:$AD$400,1)/SUMIFS('KNOWIFY REVIEW'!$AE$4:$AE$400,'KNOWIFY REVIEW'!$AB$4:$AB$400,$B18,'KNOWIFY REVIEW'!$AC$4:$AC$400,$C18,'KNOWIFY REVIEW'!$AD$4:$AD$400,1),"")) -> 1.3492499 | R18: =IF(OR($B18="",$C18=""),"",IFERROR(SUMIFS('KNOWIFY REVIEW'!$AH$4:$AH$400,'KNOWIFY REVIEW'!$AB$4:$AB$400,$B18,'KNOWIFY REVIEW'!$AC$4:$AC$400,IF(OR($C18=INPUTS!$B$69,$C18=INPUTS!$B$70),INPUTS!$B$71,$C18),'KNOWIFY REVIEW'!$AD$4:$AD$400,1)/SUMIFS('KNOWIFY REVIEW'!$AG$4:$AG$400,'KNOWIFY REVIEW'!$AB$4:$AB$400,$B18,'KNOWIFY REVIEW'!$AC$4:$AC$400,IF(OR($C18=INPUTS!$B$69,$C18=INPUTS!$B$70),INPUTS!$B$71,$C18),'KNOWIFY REVIEW'!$AD$4:$AD$400,1),"")) -> 1.2924123 | S18: =IF(MAX(N($Q18),N($R18))>1.1,"Past job ran over budget","") -> Past job ran over budget
A19: P-RI-WR5 | B19: P | C19: 03 Rough-in (Labour) | D19: 5-Piece Bathroom (WC, 2LAV, TUB & SH) | F19: ea | G19: 1460 | H19: 6 | K19: Y | L19: =($E19*$G19+$I19)*(1+IF($K19="N",0,INPUTS!$C$23)) -> 0 | M19: =$E19*$H19+$J19 -> 0 | N19: =$M19*IF(OR($B19="V",$B19="AC"),'LABOUR RATES'!$E$26,'LABOUR RATES'!$E$11) -> 0 | O19: =$M19*IF(OR($B19="V",$B19="AC"),'LABOUR RATES'!$C$27,'LABOUR RATES'!$C$12) -> 0 | P19: =$L19+$N19+$O19 -> 0 | Q19: =IF(OR($B19="",$C19=""),"",IFERROR(SUMIFS('KNOWIFY REVIEW'!$AF$4:$AF$400,'KNOWIFY REVIEW'!$AB$4:$AB$400,$B19,'KNOWIFY REVIEW'!$AC$4:$AC$400,$C19,'KNOWIFY REVIEW'!$AD$4:$AD$400,1)/SUMIFS('KNOWIFY REVIEW'!$AE$4:$AE$400,'KNOWIFY REVIEW'!$AB$4:$AB$400,$B19,'KNOWIFY REVIEW'!$AC$4:$AC$400,$C19,'KNOWIFY REVIEW'!$AD$4:$AD$400,1),"")) -> 1.3492499 | R19: =IF(OR($B19="",$C19=""),"",IFERROR(SUMIFS('KNOWIFY REVIEW'!$AH$4:$AH$400,'KNOWIFY REVIEW'!$AB$4:$AB$400,$B19,'KNOWIFY REVIEW'!$AC$4:$AC$400,IF(OR($C19=INPUTS!$B$69,$C19=INPUTS!$B$70),INPUTS!$B$71,$C19),'KNOWIFY REVIEW'!$AD$4:$AD$400,1)/SUMIFS('KNOWIFY REVIEW'!$AG$4:$AG$400,'KNOWIFY REVIEW'!$AB$4:$AB$400,$B19,'KNOWIFY REVIEW'!$AC$4:$AC$400,IF(OR($C19=INPUTS!$B$69,$C19=INPUTS!$B$70),INPUTS!$B$71,$C19),'KNOWIFY REVIEW'!$AD$4:$AD$400,1),"")) -> 1.2924123 | S19: =IF(MAX(N($Q19),N($R19))>1.1,"Past job ran over budget","") -> Past job ran over budget
A20: P-RI-LAUN | B20: P | C20: 03 Rough-in (Labour) | D20: Laundry - 4" Wet Vent | F20: ea | G20: 280 | H20: 2 | K20: Y | L20: =($E20*$G20+$I20)*(1+IF($K20="N",0,INPUTS!$C$23)) -> 0 | M20: =$E20*$H20+$J20 -> 0 | N20: =$M20*IF(OR($B20="V",$B20="AC"),'LABOUR RATES'!$E$26,'LABOUR RATES'!$E$11) -> 0 | O20: =$M20*IF(OR($B20="V",$B20="AC"),'LABOUR RATES'!$C$27,'LABOUR RATES'!$C$12) -> 0 | P20: =$L20+$N20+$O20 -> 0 | Q20: =IF(OR($B20="",$C20=""),"",IFERROR(SUMIFS('KNOWIFY REVIEW'!$AF$4:$AF$400,'KNOWIFY REVIEW'!$AB$4:$AB$400,$B20,'KNOWIFY REVIEW'!$AC$4:$AC$400,$C20,'KNOWIFY REVIEW'!$AD$4:$AD$400,1)/SUMIFS('KNOWIFY REVIEW'!$AE$4:$AE$400,'KNOWIFY REVIEW'!$AB$4:$AB$400,$B20,'KNOWIFY REVIEW'!$AC$4:$AC$400,$C20,'KNOWIFY REVIEW'!$AD$4:$AD$400,1),"")) -> 1.3492499 | R20: =IF(OR($B20="",$C20=""),"",IFERROR(SUMIFS('KNOWIFY REVIEW'!$AH$4:$AH$400,'KNOWIFY REVIEW'!$AB$4:$AB$400,$B20,'KNOWIFY REVIEW'!$AC$4:$AC$400,IF(OR($C20=INPUTS!$B$69,$C20=INPUTS!$B$70),INPUTS!$B$71,$C20),'KNOWIFY REVIEW'!$AD$4:$AD$400,1)/SUMIFS('KNOWIFY REVIEW'!$AG$4:$AG$400,'KNOWIFY REVIEW'!$AB$4:$AB$400,$B20,'KNOWIFY REVIEW'!$AC$4:$AC$400,IF(OR($C20=INPUTS!$B$69,$C20=INPUTS!$B$70),INPUTS!$B$71,$C20),'KNOWIFY REVIEW'!$AD$4:$AD$400,1),"")) -> 1.2924123 | S20: =IF(MAX(N($Q20),N($R20))>1.1,"Past job ran over budget","") -> Past job ran over budget
A21: P-RI-KS3 | B21: P | C21: 03 Rough-in (Labour) | D21: Kitchen Sink - 3" Vent | F21: ea | G21: 240 | H21: 2 | K21: Y | L21: =($E21*$G21+$I21)*(1+IF($K21="N",0,INPUTS!$C$23)) -> 0 | M21: =$E21*$H21+$J21 -> 0 | N21: =$M21*IF(OR($B21="V",$B21="AC"),'LABOUR RATES'!$E$26,'LABOUR RATES'!$E$11) -> 0 | O21: =$M21*IF(OR($B21="V",$B21="AC"),'LABOUR RATES'!$C$27,'LABOUR RATES'!$C$12) -> 0 | P21: =$L21+$N21+$O21 -> 0 | Q21: =IF(OR($B21="",$C21=""),"",IFERROR(SUMIFS('KNOWIFY REVIEW'!$AF$4:$AF$400,'KNOWIFY REVIEW'!$AB$4:$AB$400,$B21,'KNOWIFY REVIEW'!$AC$4:$AC$400,$C21,'KNOWIFY REVIEW'!$AD$4:$AD$400,1)/SUMIFS('KNOWIFY REVIEW'!$AE$4:$AE$400,'KNOWIFY REVIEW'!$AB$4:$AB$400,$B21,'KNOWIFY REVIEW'!$AC$4:$AC$400,$C21,'KNOWIFY REVIEW'!$AD$4:$AD$400,1),"")) -> 1.3492499 | R21: =IF(OR($B21="",$C21=""),"",IFERROR(SUMIFS('KNOWIFY REVIEW'!$AH$4:$AH$400,'KNOWIFY REVIEW'!$AB$4:$AB$400,$B21,'KNOWIFY REVIEW'!$AC$4:$AC$400,IF(OR($C21=INPUTS!$B$69,$C21=INPUTS!$B$70),INPUTS!$B$71,$C21),'KNOWIFY REVIEW'!$AD$4:$AD$400,1)/SUMIFS('KNOWIFY REVIEW'!$AG$4:$AG$400,'KNOWIFY REVIEW'!$AB$4:$AB$400,$B21,'KNOWIFY REVIEW'!$AC$4:$AC$400,IF(OR($C21=INPUTS!$B$69,$C21=INPUTS!$B$70),INPUTS!$B$71,$C21),'KNOWIFY REVIEW'!$AD$4:$AD$400,1),"")) -> 1.2924123 | S21: =IF(MAX(N($Q21),N($R21))>1.1,"Past job ran over budget","") -> Past job ran over budget
A22: P-RI-KS4 | B22: P | C22: 03 Rough-in (Labour) | D22: Kitchen Sink - 4" Vent | F22: ea | G22: 250 | H22: 2 | K22: Y | L22: =($E22*$G22+$I22)*(1+IF($K22="N",0,INPUTS!$C$23)) -> 0 | M22: =$E22*$H22+$J22 -> 0 | N22: =$M22*IF(OR($B22="V",$B22="AC"),'LABOUR RATES'!$E$26,'LABOUR RATES'!$E$11) -> 0 | O22: =$M22*IF(OR($B22="V",$B22="AC"),'LABOUR RATES'!$C$27,'LABOUR RATES'!$C$12) -> 0 | P22: =$L22+$N22+$O22 -> 0 | Q22: =IF(OR($B22="",$C22=""),"",IFERROR(SUMIFS('KNOWIFY REVIEW'!$AF$4:$AF$400,'KNOWIFY REVIEW'!$AB$4:$AB$400,$B22,'KNOWIFY REVIEW'!$AC$4:$AC$400,$C22,'KNOWIFY REVIEW'!$AD$4:$AD$400,1)/SUMIFS('KNOWIFY REVIEW'!$AE$4:$AE$400,'KNOWIFY REVIEW'!$AB$4:$AB$400,$B22,'KNOWIFY REVIEW'!$AC$4:$AC$400,$C22,'KNOWIFY REVIEW'!$AD$4:$AD$400,1),"")) -> 1.3492499 | R22: =IF(OR($B22="",$C22=""),"",IFERROR(SUMIFS('KNOWIFY REVIEW'!$AH$4:$AH$400,'KNOWIFY REVIEW'!$AB$4:$AB$400,$B22,'KNOWIFY REVIEW'!$AC$4:$AC$400,IF(OR($C22=INPUTS!$B$69,$C22=INPUTS!$B$70),INPUTS!$B$71,$C22),'KNOWIFY REVIEW'!$AD$4:$AD$400,1)/SUMIFS('KNOWIFY REVIEW'!$AG$4:$AG$400,'KNOWIFY REVIEW'!$AB$4:$AB$400,$B22,'KNOWIFY REVIEW'!$AC$4:$AC$400,IF(OR($C22=INPUTS!$B$69,$C22=INPUTS!$B$70),INPUTS!$B$71,$C22),'KNOWIFY REVIEW'!$AD$4:$AD$400,1),"")) -> 1.2924123 | S22: =IF(MAX(N($Q22),N($R22))>1.1,"Past job ran over budget","") -> Past job ran over budget
A23: P-RI-DWD | B23: P | C23: 03 Rough-in (Labour) | D23: Domestic Water Distribution Piping | F23: lf | K23: Y | L23: =($E23*$G23+$I23)*(1+IF($K23="N",0,INPUTS!$C$23)) -> 0 | M23: =$E23*$H23+$J23 -> 0 | N23: =$M23*IF(OR($B23="V",$B23="AC"),'LABOUR RATES'!$E$26,'LABOUR RATES'!$E$11) -> 0 | O23: =$M23*IF(OR($B23="V",$B23="AC"),'LABOUR RATES'!$C$27,'LABOUR RATES'!$C$12) -> 0 | P23: =$L23+$N23+$O23 -> 0 | Q23: =IF(OR($B23="",$C23=""),"",IFERROR(SUMIFS('KNOWIFY REVIEW'!$AF$4:$AF$400,'KNOWIFY REVIEW'!$AB$4:$AB$400,$B23,'KNOWIFY REVIEW'!$AC$4:$AC$400,$C23,'KNOWIFY REVIEW'!$AD$4:$AD$400,1)/SUMIFS('KNOWIFY REVIEW'!$AE$4:$AE$400,'KNOWIFY REVIEW'!$AB$4:$AB$400,$B23,'KNOWIFY REVIEW'!$AC$4:$AC$400,$C23,'KNOWIFY REVIEW'!$AD$4:$AD$400,1),"")) -> 1.3492499 | R23: =IF(OR($B23="",$C23=""),"",IFERROR(SUMIFS('KNOWIFY REVIEW'!$AH$4:$AH$400,'KNOWIFY REVIEW'!$AB$4:$AB$400,$B23,'KNOWIFY REVIEW'!$AC$4:$AC$400,IF(OR($C23=INPUTS!$B$69,$C23=INPUTS!$B$70),INPUTS!$B$71,$C23),'KNOWIFY REVIEW'!$AD$4:$AD$400,1)/SUMIFS('KNOWIFY REVIEW'!$AG$4:$AG$400,'KNOWIFY REVIEW'!$AB$4:$AB$400,$B23,'KNOWIFY REVIEW'!$AC$4:$AC$400,IF(OR($C23=INPUTS!$B$69,$C23=INPUTS!$B$70),INPUTS!$B$71,$C23),'KNOWIFY REVIEW'!$AD$4:$AD$400,1),"")) -> 1.2924123 | S23: =IF(MAX(N($Q23),N($R23))>1.1,"Past job ran over budget","") -> Past job ran over budget
A24: P-RI-DWS | B24: P | C24: 03 Rough-in (Labour) | D24: Domestic Water Insuite Piping | E24: 123 | F24: suite | G24: 800 | H24: 12 | K24: Y | L24: =($E24*$G24+$I24)*(1+IF($K24="N",0,INPUTS!$C$23)) -> 105288 | M24: =$E24*$H24+$J24 -> 1476 | N24: =$M24*IF(OR($B24="V",$B24="AC"),'LABOUR RATES'!$E$26,'LABOUR RATES'!$E$11) -> 95563.62 | O24: =$M24*IF(OR($B24="V",$B24="AC"),'LABOUR RATES'!$C$27,'LABOUR RATES'!$C$12) -> 32472 | P24: =$L24+$N24+$O24 -> 233323.62 | Q24: =IF(OR($B24="",$C24=""),"",IFERROR(SUMIFS('KNOWIFY REVIEW'!$AF$4:$AF$400,'KNOWIFY REVIEW'!$AB$4:$AB$400,$B24,'KNOWIFY REVIEW'!$AC$4:$AC$400,$C24,'KNOWIFY REVIEW'!$AD$4:$AD$400,1)/SUMIFS('KNOWIFY REVIEW'!$AE$4:$AE$400,'KNOWIFY REVIEW'!$AB$4:$AB$400,$B24,'KNOWIFY REVIEW'!$AC$4:$AC$400,$C24,'KNOWIFY REVIEW'!$AD$4:$AD$400,1),"")) -> 1.3492499 | R24: =IF(OR($B24="",$C24=""),"",IFERROR(SUMIFS('KNOWIFY REVIEW'!$AH$4:$AH$400,'KNOWIFY REVIEW'!$AB$4:$AB$400,$B24,'KNOWIFY REVIEW'!$AC$4:$AC$400,IF(OR($C24=INPUTS!$B$69,$C24=INPUTS!$B$70),INPUTS!$B$71,$C24),'KNOWIFY REVIEW'!$AD$4:$AD$400,1)/SUMIFS('KNOWIFY REVIEW'!$AG$4:$AG$400,'KNOWIFY REVIEW'!$AB$4:$AB$400,$B24,'KNOWIFY REVIEW'!$AC$4:$AC$400,IF(OR($C24=INPUTS!$B$69,$C24=INPUTS!$B$70),INPUTS!$B$71,$C24),'KNOWIFY REVIEW'!$AD$4:$AD$400,1),"")) -> 1.2924123 | S24: =IF(MAX(N($Q24),N($R24))>1.1,"Past job ran over budget","") -> Past job ran over budget
A25: P-RI-IRR | B25: P | C25: 03 Rough-in (Labour) | D25: Irrigation | F25: LS | K25: Y | L25: =($E25*$G25+$I25)*(1+IF($K25="N",0,INPUTS!$C$23)) -> 0 | M25: =$E25*$H25+$J25 -> 0 | N25: =$M25*IF(OR($B25="V",$B25="AC"),'LABOUR RATES'!$E$26,'LABOUR RATES'!$E$11) -> 0 | O25: =$M25*IF(OR($B25="V",$B25="AC"),'LABOUR RATES'!$C$27,'LABOUR RATES'!$C$12) -> 0 | P25: =$L25+$N25+$O25 -> 0 | Q25: =IF(OR($B25="",$C25=""),"",IFERROR(SUMIFS('KNOWIFY REVIEW'!$AF$4:$AF$400,'KNOWIFY REVIEW'!$AB$4:$AB$400,$B25,'KNOWIFY REVIEW'!$AC$4:$AC$400,$C25,'KNOWIFY REVIEW'!$AD$4:$AD$400,1)/SUMIFS('KNOWIFY REVIEW'!$AE$4:$AE$400,'KNOWIFY REVIEW'!$AB$4:$AB$400,$B25,'KNOWIFY REVIEW'!$AC$4:$AC$400,$C25,'KNOWIFY REVIEW'!$AD$4:$AD$400,1),"")) -> 1.3492499 | R25: =IF(OR($B25="",$C25=""),"",IFERROR(SUMIFS('KNOWIFY REVIEW'!$AH$4:$AH$400,'KNOWIFY REVIEW'!$AB$4:$AB$400,$B25,'KNOWIFY REVIEW'!$AC$4:$AC$400,IF(OR($C25=INPUTS!$B$69,$C25=INPUTS!$B$70),INPUTS!$B$71,$C25),'KNOWIFY REVIEW'!$AD$4:$AD$400,1)/SUMIFS('KNOWIFY REVIEW'!$AG$4:$AG$400,'KNOWIFY REVIEW'!$AB$4:$AB$400,$B25,'KNOWIFY REVIEW'!$AC$4:$AC$400,IF(OR($C25=INPUTS!$B$69,$C25=INPUTS!$B$70),INPUTS!$B$71,$C25),'KNOWIFY REVIEW'!$AD$4:$AD$400,1),"")) -> 1.2924123 | S25: =IF(MAX(N($Q25),N($R25))>1.1,"Past job ran over budget","") -> Past job ran over budget
A26: P-RI-COND | B26: P | C26: 03 Rough-in (Labour) | D26: Condensate Drains (if by Plumbing) | F26: LS | K26: Y | L26: =($E26*$G26+$I26)*(1+IF($K26="N",0,INPUTS!$C$23)) -> 0 | M26: =$E26*$H26+$J26 -> 0 | N26: =$M26*IF(OR($B26="V",$B26="AC"),'LABOUR RATES'!$E$26,'LABOUR RATES'!$E$11) -> 0 | O26: =$M26*IF(OR($B26="V",$B26="AC"),'LABOUR RATES'!$C$27,'LABOUR RATES'!$C$12) -> 0 | P26: =$L26+$N26+$O26 -> 0 | Q26: =IF(OR($B26="",$C26=""),"",IFERROR(SUMIFS('KNOWIFY REVIEW'!$AF$4:$AF$400,'KNOWIFY REVIEW'!$AB$4:$AB$400,$B26,'KNOWIFY REVIEW'!$AC$4:$AC$400,$C26,'KNOWIFY REVIEW'!$AD$4:$AD$400,1)/SUMIFS('KNOWIFY REVIEW'!$AE$4:$AE$400,'KNOWIFY REVIEW'!$AB$4:$AB$400,$B26,'KNOWIFY REVIEW'!$AC$4:$AC$400,$C26,'KNOWIFY REVIEW'!$AD$4:$AD$400,1),"")) -> 1.3492499 | R26: =IF(OR($B26="",$C26=""),"",IFERROR(SUMIFS('KNOWIFY REVIEW'!$AH$4:$AH$400,'KNOWIFY REVIEW'!$AB$4:$AB$400,$B26,'KNOWIFY REVIEW'!$AC$4:$AC$400,IF(OR($C26=INPUTS!$B$69,$C26=INPUTS!$B$70),INPUTS!$B$71,$C26),'KNOWIFY REVIEW'!$AD$4:$AD$400,1)/SUMIFS('KNOWIFY REVIEW'!$AG$4:$AG$400,'KNOWIFY REVIEW'!$AB$4:$AB$400,$B26,'KNOWIFY REVIEW'!$AC$4:$AC$400,IF(OR($C26=INPUTS!$B$69,$C26=INPUTS!$B$70),INPUTS!$B$71,$C26),'KNOWIFY REVIEW'!$AD$4:$AD$400,1),"")) -> 1.2924123 | S26: =IF(MAX(N($Q26),N($R26))>1.1,"Past job ran over budget","") -> Past job ran over budget
A27: P-RI-GAS | B27: P | C27: 03 Rough-in (Labour) | D27: Gas & Boiler Vents | F27: LS | K27: Y | L27: =($E27*$G27+$I27)*(1+IF($K27="N",0,INPUTS!$C$23)) -> 0 | M27: =$E27*$H27+$J27 -> 0 | N27: =$M27*IF(OR($B27="V",$B27="AC"),'LABOUR RATES'!$E$26,'LABOUR RATES'!$E$11) -> 0 | O27: =$M27*IF(OR($B27="V",$B27="AC"),'LABOUR RATES'!$C$27,'LABOUR RATES'!$C$12) -> 0 | P27: =$L27+$N27+$O27 -> 0 | Q27: =IF(OR($B27="",$C27=""),"",IFERROR(SUMIFS('KNOWIFY REVIEW'!$AF$4:$AF$400,'KNOWIFY REVIEW'!$AB$4:$AB$400,$B27,'KNOWIFY REVIEW'!$AC$4:$AC$400,$C27,'KNOWIFY REVIEW'!$AD$4:$AD$400,1)/SUMIFS('KNOWIFY REVIEW'!$AE$4:$AE$400,'KNOWIFY REVIEW'!$AB$4:$AB$400,$B27,'KNOWIFY REVIEW'!$AC$4:$AC$400,$C27,'KNOWIFY REVIEW'!$AD$4:$AD$400,1),"")) -> 1.3492499 | R27: =IF(OR($B27="",$C27=""),"",IFERROR(SUMIFS('KNOWIFY REVIEW'!$AH$4:$AH$400,'KNOWIFY REVIEW'!$AB$4:$AB$400,$B27,'KNOWIFY REVIEW'!$AC$4:$AC$400,IF(OR($C27=INPUTS!$B$69,$C27=INPUTS!$B$70),INPUTS!$B$71,$C27),'KNOWIFY REVIEW'!$AD$4:$AD$400,1)/SUMIFS('KNOWIFY REVIEW'!$AG$4:$AG$400,'KNOWIFY REVIEW'!$AB$4:$AB$400,$B27,'KNOWIFY REVIEW'!$AC$4:$AC$400,IF(OR($C27=INPUTS!$B$69,$C27=INPUTS!$B$70),INPUTS!$B$71,$C27),'KNOWIFY REVIEW'!$AD$4:$AD$400,1),"")) -> 1.2924123 | S27: =IF(MAX(N($Q27),N($R27))>1.1,"Past job ran over budget","") -> Past job ran over budget
A28: P-RI-DRN | B28: P | C28: 03 Rough-in (Labour) | D28: Drains & Hose Bibs (rough-in) | F28: ea | K28: Y | L28: =($E28*$G28+$I28)*(1+IF($K28="N",0,INPUTS!$C$23)) -> 0 | M28: =$E28*$H28+$J28 -> 0 | N28: =$M28*IF(OR($B28="V",$B28="AC"),'LABOUR RATES'!$E$26,'LABOUR RATES'!$E$11) -> 0 | O28: =$M28*IF(OR($B28="V",$B28="AC"),'LABOUR RATES'!$C$27,'LABOUR RATES'!$C$12) -> 0 | P28: =$L28+$N28+$O28 -> 0 | Q28: =IF(OR($B28="",$C28=""),"",IFERROR(SUMIFS('KNOWIFY REVIEW'!$AF$4:$AF$400,'KNOWIFY REVIEW'!$AB$4:$AB$400,$B28,'KNOWIFY REVIEW'!$AC$4:$AC$400,$C28,'KNOWIFY REVIEW'!$AD$4:$AD$400,1)/SUMIFS('KNOWIFY REVIEW'!$AE$4:$AE$400,'KNOWIFY REVIEW'!$AB$4:$AB$400,$B28,'KNOWIFY REVIEW'!$AC$4:$AC$400,$C28,'KNOWIFY REVIEW'!$AD$4:$AD$400,1),"")) -> 1.3492499 | R28: =IF(OR($B28="",$C28=""),"",IFERROR(SUMIFS('KNOWIFY REVIEW'!$AH$4:$AH$400,'KNOWIFY REVIEW'!$AB$4:$AB$400,$B28,'KNOWIFY REVIEW'!$AC$4:$AC$400,IF(OR($C28=INPUTS!$B$69,$C28=INPUTS!$B$70),INPUTS!$B$71,$C28),'KNOWIFY REVIEW'!$AD$4:$AD$400,1)/SUMIFS('KNOWIFY REVIEW'!$AG$4:$AG$400,'KNOWIFY REVIEW'!$AB$4:$AB$400,$B28,'KNOWIFY REVIEW'!$AC$4:$AC$400,IF(OR($C28=INPUTS!$B$69,$C28=INPUTS!$B$70),INPUTS!$B$71,$C28),'KNOWIFY REVIEW'!$AD$4:$AD$400,1),"")) -> 1.2924123 | S28: =IF(MAX(N($Q28),N($R28))>1.1,"Past job ran over budget","") -> Past job ran over budget
A29: P-RI-WER | B29: P | C29: 03 Rough-in (Labour) | D29: Water Entry Room | F29: LS | K29: Y | L29: =($E29*$G29+$I29)*(1+IF($K29="N",0,INPUTS!$C$23)) -> 0 | M29: =$E29*$H29+$J29 -> 0 | N29: =$M29*IF(OR($B29="V",$B29="AC"),'LABOUR RATES'!$E$26,'LABOUR RATES'!$E$11) -> 0 | O29: =$M29*IF(OR($B29="V",$B29="AC"),'LABOUR RATES'!$C$27,'LABOUR RATES'!$C$12) -> 0 | P29: =$L29+$N29+$O29 -> 0 | Q29: =IF(OR($B29="",$C29=""),"",IFERROR(SUMIFS('KNOWIFY REVIEW'!$AF$4:$AF$400,'KNOWIFY REVIEW'!$AB$4:$AB$400,$B29,'KNOWIFY REVIEW'!$AC$4:$AC$400,$C29,'KNOWIFY REVIEW'!$AD$4:$AD$400,1)/SUMIFS('KNOWIFY REVIEW'!$AE$4:$AE$400,'KNOWIFY REVIEW'!$AB$4:$AB$400,$B29,'KNOWIFY REVIEW'!$AC$4:$AC$400,$C29,'KNOWIFY REVIEW'!$AD$4:$AD$400,1),"")) -> 1.3492499 | R29: =IF(OR($B29="",$C29=""),"",IFERROR(SUMIFS('KNOWIFY REVIEW'!$AH$4:$AH$400,'KNOWIFY REVIEW'!$AB$4:$AB$400,$B29,'KNOWIFY REVIEW'!$AC$4:$AC$400,IF(OR($C29=INPUTS!$B$69,$C29=INPUTS!$B$70),INPUTS!$B$71,$C29),'KNOWIFY REVIEW'!$AD$4:$AD$400,1)/SUMIFS('KNOWIFY REVIEW'!$AG$4:$AG$400,'KNOWIFY REVIEW'!$AB$4:$AB$400,$B29,'KNOWIFY REVIEW'!$AC$4:$AC$400,IF(OR($C29=INPUTS!$B$69,$C29=INPUTS!$B$70),INPUTS!$B$71,$C29),'KNOWIFY REVIEW'!$AD$4:$AD$400,1),"")) -> 1.2924123 | S29: =IF(MAX(N($Q29),N($R29))>1.1,"Past job ran over budget","") -> Past job ran over budget
A30: P-RI-FLSH | B30: P | C30: 03 Rough-in (Labour) | D30: Roof Flashings | F30: ea | K30: Y | L30: =($E30*$G30+$I30)*(1+IF($K30="N",0,INPUTS!$C$23)) -> 0 | M30: =$E30*$H30+$J30 -> 0 | N30: =$M30*IF(OR($B30="V",$B30="AC"),'LABOUR RATES'!$E$26,'LABOUR RATES'!$E$11) -> 0 | O30: =$M30*IF(OR($B30="V",$B30="AC"),'LABOUR RATES'!$C$27,'LABOUR RATES'!$C$12) -> 0 | P30: =$L30+$N30+$O30 -> 0 | Q30: =IF(OR($B30="",$C30=""),"",IFERROR(SUMIFS('KNOWIFY REVIEW'!$AF$4:$AF$400,'KNOWIFY REVIEW'!$AB$4:$AB$400,$B30,'KNOWIFY REVIEW'!$AC$4:$AC$400,$C30,'KNOWIFY REVIEW'!$AD$4:$AD$400,1)/SUMIFS('KNOWIFY REVIEW'!$AE$4:$AE$400,'KNOWIFY REVIEW'!$AB$4:$AB$400,$B30,'KNOWIFY REVIEW'!$AC$4:$AC$400,$C30,'KNOWIFY REVIEW'!$AD$4:$AD$400,1),"")) -> 1.3492499 | R30: =IF(OR($B30="",$C30=""),"",IFERROR(SUMIFS('KNOWIFY REVIEW'!$AH$4:$AH$400,'KNOWIFY REVIEW'!$AB$4:$AB$400,$B30,'KNOWIFY REVIEW'!$AC$4:$AC$400,IF(OR($C30=INPUTS!$B$69,$C30=INPUTS!$B$70),INPUTS!$B$71,$C30),'KNOWIFY REVIEW'!$AD$4:$AD$400,1)/SUMIFS('KNOWIFY REVIEW'!$AG$4:$AG$400,'KNOWIFY REVIEW'!$AB$4:$AB$400,$B30,'KNOWIFY REVIEW'!$AC$4:$AC$400,IF(OR($C30=INPUTS!$B$69,$C30=INPUTS!$B$70),INPUTS!$B$71,$C30),'KNOWIFY REVIEW'!$AD$4:$AD$400,1),"")) -> 1.2924123 | S30: =IF(MAX(N($Q30),N($R30))>1.1,"Past job ran over budget","") -> Past job ran over budget
A31: P-RI-CAN | B31: P | C31: 03 Rough-in (Labour) | D31: Canning / Cutting / Layout | F31: LS | K31: Y | L31: =($E31*$G31+$I31)*(1+IF($K31="N",0,INPUTS!$C$23)) -> 0 | M31: =$E31*$H31+$J31 -> 0 | N31: =$M31*IF(OR($B31="V",$B31="AC"),'LABOUR RATES'!$E$26,'LABOUR RATES'!$E$11) -> 0 | O31: =$M31*IF(OR($B31="V",$B31="AC"),'LABOUR RATES'!$C$27,'LABOUR RATES'!$C$12) -> 0 | P31: =$L31+$N31+$O31 -> 0 | Q31: =IF(OR($B31="",$C31=""),"",IFERROR(SUMIFS('KNOWIFY REVIEW'!$AF$4:$AF$400,'KNOWIFY REVIEW'!$AB$4:$AB$400,$B31,'KNOWIFY REVIEW'!$AC$4:$AC$400,$C31,'KNOWIFY REVIEW'!$AD$4:$AD$400,1)/SUMIFS('KNOWIFY REVIEW'!$AE$4:$AE$400,'KNOWIFY REVIEW'!$AB$4:$AB$400,$B31,'KNOWIFY REVIEW'!$AC$4:$AC$400,$C31,'KNOWIFY REVIEW'!$AD$4:$AD$400,1),"")) -> 1.3492499 | R31: =IF(OR($B31="",$C31=""),"",IFERROR(SUMIFS('KNOWIFY REVIEW'!$AH$4:$AH$400,'KNOWIFY REVIEW'!$AB$4:$AB$400,$B31,'KNOWIFY REVIEW'!$AC$4:$AC$400,IF(OR($C31=INPUTS!$B$69,$C31=INPUTS!$B$70),INPUTS!$B$71,$C31),'KNOWIFY REVIEW'!$AD$4:$AD$400,1)/SUMIFS('KNOWIFY REVIEW'!$AG$4:$AG$400,'KNOWIFY REVIEW'!$AB$4:$AB$400,$B31,'KNOWIFY REVIEW'!$AC$4:$AC$400,IF(OR($C31=INPUTS!$B$69,$C31=INPUTS!$B$70),INPUTS!$B$71,$C31),'KNOWIFY REVIEW'!$AD$4:$AD$400,1),"")) -> 1.2924123 | S31: =IF(MAX(N($Q31),N($R31))>1.1,"Past job ran over budget","") -> Past job ran over budget
A32: P-RI-CLN | B32: P | C32: 03 Rough-in (Labour) | D32: Clean-up | F32: LS | K32: Y | L32: =($E32*$G32+$I32)*(1+IF($K32="N",0,INPUTS!$C$23)) -> 0 | M32: =$E32*$H32+$J32 -> 0 | N32: =$M32*IF(OR($B32="V",$B32="AC"),'LABOUR RATES'!$E$26,'LABOUR RATES'!$E$11) -> 0 | O32: =$M32*IF(OR($B32="V",$B32="AC"),'LABOUR RATES'!$C$27,'LABOUR RATES'!$C$12) -> 0 | P32: =$L32+$N32+$O32 -> 0 | Q32: =IF(OR($B32="",$C32=""),"",IFERROR(SUMIFS('KNOWIFY REVIEW'!$AF$4:$AF$400,'KNOWIFY REVIEW'!$AB$4:$AB$400,$B32,'KNOWIFY REVIEW'!$AC$4:$AC$400,$C32,'KNOWIFY REVIEW'!$AD$4:$AD$400,1)/SUMIFS('KNOWIFY REVIEW'!$AE$4:$AE$400,'KNOWIFY REVIEW'!$AB$4:$AB$400,$B32,'KNOWIFY REVIEW'!$AC$4:$AC$400,$C32,'KNOWIFY REVIEW'!$AD$4:$AD$400,1),"")) -> 1.3492499 | R32: =IF(OR($B32="",$C32=""),"",IFERROR(SUMIFS('KNOWIFY REVIEW'!$AH$4:$AH$400,'KNOWIFY REVIEW'!$AB$4:$AB$400,$B32,'KNOWIFY REVIEW'!$AC$4:$AC$400,IF(OR($C32=INPUTS!$B$69,$C32=INPUTS!$B$70),INPUTS!$B$71,$C32),'KNOWIFY REVIEW'!$AD$4:$AD$400,1)/SUMIFS('KNOWIFY REVIEW'!$AG$4:$AG$400,'KNOWIFY REVIEW'!$AB$4:$AB$400,$B32,'KNOWIFY REVIEW'!$AC$4:$AC$400,IF(OR($C32=INPUTS!$B$69,$C32=INPUTS!$B$70),INPUTS!$B$71,$C32),'KNOWIFY REVIEW'!$AD$4:$AD$400,1),"")) -> 1.2924123 | S32: =IF(MAX(N($Q32),N($R32))>1.1,"Past job ran over budget","") -> Past job ran over budget
A33: P-FN-FIX | B33: P | C33: 04 Finishing (Labour) | D33: Set Plumbing Fixtures | F33: ea | K33: Y | L33: =($E33*$G33+$I33)*(1+IF($K33="N",0,INPUTS!$C$23)) -> 0 | M33: =$E33*$H33+$J33 -> 0 | N33: =$M33*IF(OR($B33="V",$B33="AC"),'LABOUR RATES'!$E$26,'LABOUR RATES'!$E$11) -> 0 | O33: =$M33*IF(OR($B33="V",$B33="AC"),'LABOUR RATES'!$C$27,'LABOUR RATES'!$C$12) -> 0 | P33: =$L33+$N33+$O33 -> 0 | Q33: =IF(OR($B33="",$C33=""),"",IFERROR(SUMIFS('KNOWIFY REVIEW'!$AF$4:$AF$400,'KNOWIFY REVIEW'!$AB$4:$AB$400,$B33,'KNOWIFY REVIEW'!$AC$4:$AC$400,$C33,'KNOWIFY REVIEW'!$AD$4:$AD$400,1)/SUMIFS('KNOWIFY REVIEW'!$AE$4:$AE$400,'KNOWIFY REVIEW'!$AB$4:$AB$400,$B33,'KNOWIFY REVIEW'!$AC$4:$AC$400,$C33,'KNOWIFY REVIEW'!$AD$4:$AD$400,1),"")) | R33: =IF(OR($B33="",$C33=""),"",IFERROR(SUMIFS('KNOWIFY REVIEW'!$AH$4:$AH$400,'KNOWIFY REVIEW'!$AB$4:$AB$400,$B33,'KNOWIFY REVIEW'!$AC$4:$AC$400,IF(OR($C33=INPUTS!$B$69,$C33=INPUTS!$B$70),INPUTS!$B$71,$C33),'KNOWIFY REVIEW'!$AD$4:$AD$400,1)/SUMIFS('KNOWIFY REVIEW'!$AG$4:$AG$400,'KNOWIFY REVIEW'!$AB$4:$AB$400,$B33,'KNOWIFY REVIEW'!$AC$4:$AC$400,IF(OR($C33=INPUTS!$B$69,$C33=INPUTS!$B$70),INPUTS!$B$71,$C33),'KNOWIFY REVIEW'!$AD$4:$AD$400,1),"")) -> 1.2924123 | S33: =IF(MAX(N($Q33),N($R33))>1.1,"Past job ran over budget","") -> Past job ran over budget
A34: P-FN-AP | B34: P | C34: 04 Finishing (Labour) | D34: Install Access Panels | F34: ea | K34: Y | L34: =($E34*$G34+$I34)*(1+IF($K34="N",0,INPUTS!$C$23)) -> 0 | M34: =$E34*$H34+$J34 -> 0 | N34: =$M34*IF(OR($B34="V",$B34="AC"),'LABOUR RATES'!$E$26,'LABOUR RATES'!$E$11) -> 0 | O34: =$M34*IF(OR($B34="V",$B34="AC"),'LABOUR RATES'!$C$27,'LABOUR RATES'!$C$12) -> 0 | P34: =$L34+$N34+$O34 -> 0 | Q34: =IF(OR($B34="",$C34=""),"",IFERROR(SUMIFS('KNOWIFY REVIEW'!$AF$4:$AF$400,'KNOWIFY REVIEW'!$AB$4:$AB$400,$B34,'KNOWIFY REVIEW'!$AC$4:$AC$400,$C34,'KNOWIFY REVIEW'!$AD$4:$AD$400,1)/SUMIFS('KNOWIFY REVIEW'!$AE$4:$AE$400,'KNOWIFY REVIEW'!$AB$4:$AB$400,$B34,'KNOWIFY REVIEW'!$AC$4:$AC$400,$C34,'KNOWIFY REVIEW'!$AD$4:$AD$400,1),"")) | R34: =IF(OR($B34="",$C34=""),"",IFERROR(SUMIFS('KNOWIFY REVIEW'!$AH$4:$AH$400,'KNOWIFY REVIEW'!$AB$4:$AB$400,$B34,'KNOWIFY REVIEW'!$AC$4:$AC$400,IF(OR($C34=INPUTS!$B$69,$C34=INPUTS!$B$70),INPUTS!$B$71,$C34),'KNOWIFY REVIEW'!$AD$4:$AD$400,1)/SUMIFS('KNOWIFY REVIEW'!$AG$4:$AG$400,'KNOWIFY REVIEW'!$AB$4:$AB$400,$B34,'KNOWIFY REVIEW'!$AC$4:$AC$400,IF(OR($C34=INPUTS!$B$69,$C34=INPUTS!$B$70),INPUTS!$B$71,$C34),'KNOWIFY REVIEW'!$AD$4:$AD$400,1),"")) -> 1.2924123 | S34: =IF(MAX(N($Q34),N($R34))>1.1,"Past job ran over budget","") -> Past job ran over budget
A35: P-FN-LBL | B35: P | C35: 04 Finishing (Labour) | D35: Pipe Labelling | F35: LS | K35: Y | L35: =($E35*$G35+$I35)*(1+IF($K35="N",0,INPUTS!$C$23)) -> 0 | M35: =$E35*$H35+$J35 -> 0 | N35: =$M35*IF(OR($B35="V",$B35="AC"),'LABOUR RATES'!$E$26,'LABOUR RATES'!$E$11) -> 0 | O35: =$M35*IF(OR($B35="V",$B35="AC"),'LABOUR RATES'!$C$27,'LABOUR RATES'!$C$12) -> 0 | P35: =$L35+$N35+$O35 -> 0 | Q35: =IF(OR($B35="",$C35=""),"",IFERROR(SUMIFS('KNOWIFY REVIEW'!$AF$4:$AF$400,'KNOWIFY REVIEW'!$AB$4:$AB$400,$B35,'KNOWIFY REVIEW'!$AC$4:$AC$400,$C35,'KNOWIFY REVIEW'!$AD$4:$AD$400,1)/SUMIFS('KNOWIFY REVIEW'!$AE$4:$AE$400,'KNOWIFY REVIEW'!$AB$4:$AB$400,$B35,'KNOWIFY REVIEW'!$AC$4:$AC$400,$C35,'KNOWIFY REVIEW'!$AD$4:$AD$400,1),"")) | R35: =IF(OR($B35="",$C35=""),"",IFERROR(SUMIFS('KNOWIFY REVIEW'!$AH$4:$AH$400,'KNOWIFY REVIEW'!$AB$4:$AB$400,$B35,'KNOWIFY REVIEW'!$AC$4:$AC$400,IF(OR($C35=INPUTS!$B$69,$C35=INPUTS!$B$70),INPUTS!$B$71,$C35),'KNOWIFY REVIEW'!$AD$4:$AD$400,1)/SUMIFS('KNOWIFY REVIEW'!$AG$4:$AG$400,'KNOWIFY REVIEW'!$AB$4:$AB$400,$B35,'KNOWIFY REVIEW'!$AC$4:$AC$400,IF(OR($C35=INPUTS!$B$69,$C35=INPUTS!$B$70),INPUTS!$B$71,$C35),'KNOWIFY REVIEW'!$AD$4:$AD$400,1),"")) -> 1.2924123 | S35: =IF(MAX(N($Q35),N($R35))>1.1,"Past job ran over budget","") -> Past job ran over budget
A36: P-EQ-FIX | B36: P | C36: 06 Fixtures & Equipment Supply | D36: Plumbing Fixtures & Access Panels Supply | F36: LS | K36: Y | L36: =($E36*$G36+$I36)*(1+IF($K36="N",0,INPUTS!$C$23)) -> 0 | M36: =$E36*$H36+$J36 -> 0 | N36: =$M36*IF(OR($B36="V",$B36="AC"),'LABOUR RATES'!$E$26,'LABOUR RATES'!$E$11) -> 0 | O36: =$M36*IF(OR($B36="V",$B36="AC"),'LABOUR RATES'!$C$27,'LABOUR RATES'!$C$12) -> 0 | P36: =$L36+$N36+$O36 -> 0 | Q36: =IF(OR($B36="",$C36=""),"",IFERROR(SUMIFS('KNOWIFY REVIEW'!$AF$4:$AF$400,'KNOWIFY REVIEW'!$AB$4:$AB$400,$B36,'KNOWIFY REVIEW'!$AC$4:$AC$400,$C36,'KNOWIFY REVIEW'!$AD$4:$AD$400,1)/SUMIFS('KNOWIFY REVIEW'!$AE$4:$AE$400,'KNOWIFY REVIEW'!$AB$4:$AB$400,$B36,'KNOWIFY REVIEW'!$AC$4:$AC$400,$C36,'KNOWIFY REVIEW'!$AD$4:$AD$400,1),"")) | R36: =IF(OR($B36="",$C36=""),"",IFERROR(SUMIFS('KNOWIFY REVIEW'!$AH$4:$AH$400,'KNOWIFY REVIEW'!$AB$4:$AB$400,$B36,'KNOWIFY REVIEW'!$AC$4:$AC$400,IF(OR($C36=INPUTS!$B$69,$C36=INPUTS!$B$70),INPUTS!$B$71,$C36),'KNOWIFY REVIEW'!$AD$4:$AD$400,1)/SUMIFS('KNOWIFY REVIEW'!$AG$4:$AG$400,'KNOWIFY REVIEW'!$AB$4:$AB$400,$B36,'KNOWIFY REVIEW'!$AC$4:$AC$400,IF(OR($C36=INPUTS!$B$69,$C36=INPUTS!$B$70),INPUTS!$B$71,$C36),'KNOWIFY REVIEW'!$AD$4:$AD$400,1),"")) | S36: =IF(MAX(N($Q36),N($R36))>1.1,"Past job ran over budget","")
... A43: H-RI-MAN | B43: H | C43: 03 Rough-in (Labour) | D43: Manifolds | F43: ea | K43: Y | L43: =($E43*$G43+$I43)*(1+IF($K43="N",0,INPUTS!$C$23)) -> 0 | M43: =$E43*$H43+$J43 -> 0 | N43: =$M43*IF(OR($B43="V",$B43="AC"),'LABOUR RATES'!$E$26,'LABOUR RATES'!$E$11) -> 0 | O43: =$M43*IF(OR($B43="V",$B43="AC"),'LABOUR RATES'!$C$27,'LABOUR RATES'!$C$12) -> 0 | P43: =$L43+$N43+$O43 -> 0 | Q43: =IF(OR($B43="",$C43=""),"",IFERROR(SUMIFS('KNOWIFY REVIEW'!$AF$4:$AF$400,'KNOWIFY REVIEW'!$AB$4:$AB$400,$B43,'KNOWIFY REVIEW'!$AC$4:$AC$400,$C43,'KNOWIFY REVIEW'!$AD$4:$AD$400,1)/SUMIFS('KNOWIFY REVIEW'!$AE$4:$AE$400,'KNOWIFY REVIEW'!$AB$4:$AB$400,$B43,'KNOWIFY REVIEW'!$AC$4:$AC$400,$C43,'KNOWIFY REVIEW'!$AD$4:$AD$400,1),"")) | R43: =IF(OR($B43="",$C43=""),"",IFERROR(SUMIFS('KNOWIFY REVIEW'!$AH$4:$AH$400,'KNOWIFY REVIEW'!$AB$4:$AB$400,$B43,'KNOWIFY REVIEW'!$AC$4:$AC$400,IF(OR($C43=INPUTS!$B$69,$C43=INPUTS!$B$70),INPUTS!$B$71,$C43),'KNOWIFY REVIEW'!$AD$4:$AD$400,1)/SUMIFS('KNOWIFY REVIEW'!$AG$4:$AG$400,'KNOWIFY REVIEW'!$AB$4:$AB$400,$B43,'KNOWIFY REVIEW'!$AC$4:$AC$400,IF(OR($C43=INPUTS!$B$69,$C43=INPUTS!$B$70),INPUTS!$B$71,$C43),'KNOWIFY REVIEW'!$AD$4:$AD$400,1),"")) | S43: =IF(MAX(N($Q43),N($R43))>1.1,"Past job ran over budget","")
A44: H-RI-SUITE | B44: H | C44: 03 Rough-in (Labour) | D44: Hydronic Insuite Piping | F44: suite | H44: 8 | K44: Y | L44: =($E44*$G44+$I44)*(1+IF($K44="N",0,INPUTS!$C$23)) -> 0 | M44: =$E44*$H44+$J44 -> 0 | N44: =$M44*IF(OR($B44="V",$B44="AC"),'LABOUR RATES'!$E$26,'LABOUR RATES'!$E$11) -> 0 | O44: =$M44*IF(OR($B44="V",$B44="AC"),'LABOUR RATES'!$C$27,'LABOUR RATES'!$C$12) -> 0 | P44: =$L44+$N44+$O44 -> 0 | Q44: =IF(OR($B44="",$C44=""),"",IFERROR(SUMIFS('KNOWIFY REVIEW'!$AF$4:$AF$400,'KNOWIFY REVIEW'!$AB$4:$AB$400,$B44,'KNOWIFY REVIEW'!$AC$4:$AC$400,$C44,'KNOWIFY REVIEW'!$AD$4:$AD$400,1)/SUMIFS('KNOWIFY REVIEW'!$AE$4:$AE$400,'KNOWIFY REVIEW'!$AB$4:$AB$400,$B44,'KNOWIFY REVIEW'!$AC$4:$AC$400,$C44,'KNOWIFY REVIEW'!$AD$4:$AD$400,1),"")) | R44: =IF(OR($B44="",$C44=""),"",IFERROR(SUMIFS('KNOWIFY REVIEW'!$AH$4:$AH$400,'KNOWIFY REVIEW'!$AB$4:$AB$400,$B44,'KNOWIFY REVIEW'!$AC$4:$AC$400,IF(OR($C44=INPUTS!$B$69,$C44=INPUTS!$B$70),INPUTS!$B$71,$C44),'KNOWIFY REVIEW'!$AD$4:$AD$400,1)/SUMIFS('KNOWIFY REVIEW'!$AG$4:$AG$400,'KNOWIFY REVIEW'!$AB$4:$AB$400,$B44,'KNOWIFY REVIEW'!$AC$4:$AC$400,IF(OR($C44=INPUTS!$B$69,$C44=INPUTS!$B$70),INPUTS!$B$71,$C44),'KNOWIFY REVIEW'!$AD$4:$AD$400,1),"")) | S44: =IF(MAX(N($Q44),N($R44))>1.1,"Past job ran over budget","")
A45: H-RI-GLY | B45: H | C45: 03 Rough-in (Labour) | D45: Glycol Loop | F45: LS | K45: Y | L45: =($E45*$G45+$I45)*(1+IF($K45="N",0,INPUTS!$C$23)) -> 0 | M45: =$E45*$H45+$J45 -> 0 | N45: =$M45*IF(OR($B45="V",$B45="AC"),'LABOUR RATES'!$E$26,'LABOUR RATES'!$E$11) -> 0 | O45: =$M45*IF(OR($B45="V",$B45="AC"),'LABOUR RATES'!$C$27,'LABOUR RATES'!$C$12) -> 0 | P45: =$L45+$N45+$O45 -> 0 | Q45: =IF(OR($B45="",$C45=""),"",IFERROR(SUMIFS('KNOWIFY REVIEW'!$AF$4:$AF$400,'KNOWIFY REVIEW'!$AB$4:$AB$400,$B45,'KNOWIFY REVIEW'!$AC$4:$AC$400,$C45,'KNOWIFY REVIEW'!$AD$4:$AD$400,1)/SUMIFS('KNOWIFY REVIEW'!$AE$4:$AE$400,'KNOWIFY REVIEW'!$AB$4:$AB$400,$B45,'KNOWIFY REVIEW'!$AC$4:$AC$400,$C45,'KNOWIFY REVIEW'!$AD$4:$AD$400,1),"")) | R45: =IF(OR($B45="",$C45=""),"",IFERROR(SUMIFS('KNOWIFY REVIEW'!$AH$4:$AH$400,'KNOWIFY REVIEW'!$AB$4:$AB$400,$B45,'KNOWIFY REVIEW'!$AC$4:$AC$400,IF(OR($C45=INPUTS!$B$69,$C45=INPUTS!$B$70),INPUTS!$B$71,$C45),'KNOWIFY REVIEW'!$AD$4:$AD$400,1)/SUMIFS('KNOWIFY REVIEW'!$AG$4:$AG$400,'KNOWIFY REVIEW'!$AB$4:$AB$400,$B45,'KNOWIFY REVIEW'!$AC$4:$AC$400,IF(OR($C45=INPUTS!$B$69,$C45=INPUTS!$B$70),INPUTS!$B$71,$C45),'KNOWIFY REVIEW'!$AD$4:$AD$400,1),"")) | S45: =IF(MAX(N($Q45),N($R45))>1.1,"Past job ran over budget","")
A46: H-RI-CAN | B46: H | C46: 03 Rough-in (Labour) | D46: Canning / Cutting / Layout | F46: LS | K46: Y | L46: =($E46*$G46+$I46)*(1+IF($K46="N",0,INPUTS!$C$23)) -> 0 | M46: =$E46*$H46+$J46 -> 0 | N46: =$M46*IF(OR($B46="V",$B46="AC"),'LABOUR RATES'!$E$26,'LABOUR RATES'!$E$11) -> 0 | O46: =$M46*IF(OR($B46="V",$B46="AC"),'LABOUR RATES'!$C$27,'LABOUR RATES'!$C$12) -> 0 | P46: =$L46+$N46+$O46 -> 0 | Q46: =IF(OR($B46="",$C46=""),"",IFERROR(SUMIFS('KNOWIFY REVIEW'!$AF$4:$AF$400,'KNOWIFY REVIEW'!$AB$4:$AB$400,$B46,'KNOWIFY REVIEW'!$AC$4:$AC$400,$C46,'KNOWIFY REVIEW'!$AD$4:$AD$400,1)/SUMIFS('KNOWIFY REVIEW'!$AE$4:$AE$400,'KNOWIFY REVIEW'!$AB$4:$AB$400,$B46,'KNOWIFY REVIEW'!$AC$4:$AC$400,$C46,'KNOWIFY REVIEW'!$AD$4:$AD$400,1),"")) | R46: =IF(OR($B46="",$C46=""),"",IFERROR(SUMIFS('KNOWIFY REVIEW'!$AH$4:$AH$400,'KNOWIFY REVIEW'!$AB$4:$AB$400,$B46,'KNOWIFY REVIEW'!$AC$4:$AC$400,IF(OR($C46=INPUTS!$B$69,$C46=INPUTS!$B$70),INPUTS!$B$71,$C46),'KNOWIFY REVIEW'!$AD$4:$AD$400,1)/SUMIFS('KNOWIFY REVIEW'!$AG$4:$AG$400,'KNOWIFY REVIEW'!$AB$4:$AB$400,$B46,'KNOWIFY REVIEW'!$AC$4:$AC$400,IF(OR($C46=INPUTS!$B$69,$C46=INPUTS!$B$70),INPUTS!$B$71,$C46),'KNOWIFY REVIEW'!$AD$4:$AD$400,1),"")) | S46: =IF(MAX(N($Q46),N($R46))>1.1,"Past job ran over budget","")
A47: H-RI-CLN | B47: H | C47: 03 Rough-in (Labour) | D47: Clean-up | F47: LS | K47: Y | L47: =($E47*$G47+$I47)*(1+IF($K47="N",0,INPUTS!$C$23)) -> 0 | M47: =$E47*$H47+$J47 -> 0 | N47: =$M47*IF(OR($B47="V",$B47="AC"),'LABOUR RATES'!$E$26,'LABOUR RATES'!$E$11) -> 0 | O47: =$M47*IF(OR($B47="V",$B47="AC"),'LABOUR RATES'!$C$27,'LABOUR RATES'!$C$12) -> 0 | P47: =$L47+$N47+$O47 -> 0 | Q47: =IF(OR($B47="",$C47=""),"",IFERROR(SUMIFS('KNOWIFY REVIEW'!$AF$4:$AF$400,'KNOWIFY REVIEW'!$AB$4:$AB$400,$B47,'KNOWIFY REVIEW'!$AC$4:$AC$400,$C47,'KNOWIFY REVIEW'!$AD$4:$AD$400,1)/SUMIFS('KNOWIFY REVIEW'!$AE$4:$AE$400,'KNOWIFY REVIEW'!$AB$4:$AB$400,$B47,'KNOWIFY REVIEW'!$AC$4:$AC$400,$C47,'KNOWIFY REVIEW'!$AD$4:$AD$400,1),"")) | R47: =IF(OR($B47="",$C47=""),"",IFERROR(SUMIFS('KNOWIFY REVIEW'!$AH$4:$AH$400,'KNOWIFY REVIEW'!$AB$4:$AB$400,$B47,'KNOWIFY REVIEW'!$AC$4:$AC$400,IF(OR($C47=INPUTS!$B$69,$C47=INPUTS!$B$70),INPUTS!$B$71,$C47),'KNOWIFY REVIEW'!$AD$4:$AD$400,1)/SUMIFS('KNOWIFY REVIEW'!$AG$4:$AG$400,'KNOWIFY REVIEW'!$AB$4:$AB$400,$B47,'KNOWIFY REVIEW'!$AC$4:$AC$400,IF(OR($C47=INPUTS!$B$69,$C47=INPUTS!$B$70),INPUTS!$B$71,$C47),'KNOWIFY REVIEW'!$AD$4:$AD$400,1),"")) | S47: =IF(MAX(N($Q47),N($R47))>1.1,"Past job ran over budget","")
A48: H-FN-AP | B48: H | C48: 04 Finishing (Labour) | D48: Install Access Panels | F48: ea | K48: Y | L48: =($E48*$G48+$I48)*(1+IF($K48="N",0,INPUTS!$C$23)) -> 0 | M48: =$E48*$H48+$J48 -> 0 | N48: =$M48*IF(OR($B48="V",$B48="AC"),'LABOUR RATES'!$E$26,'LABOUR RATES'!$E$11) -> 0 | O48: =$M48*IF(OR($B48="V",$B48="AC"),'LABOUR RATES'!$C$27,'LABOUR RATES'!$C$12) -> 0 | P48: =$L48+$N48+$O48 -> 0 | Q48: =IF(OR($B48="",$C48=""),"",IFERROR(SUMIFS('KNOWIFY REVIEW'!$AF$4:$AF$400,'KNOWIFY REVIEW'!$AB$4:$AB$400,$B48,'KNOWIFY REVIEW'!$AC$4:$AC$400,$C48,'KNOWIFY REVIEW'!$AD$4:$AD$400,1)/SUMIFS('KNOWIFY REVIEW'!$AE$4:$AE$400,'KNOWIFY REVIEW'!$AB$4:$AB$400,$B48,'KNOWIFY REVIEW'!$AC$4:$AC$400,$C48,'KNOWIFY REVIEW'!$AD$4:$AD$400,1),"")) | R48: =IF(OR($B48="",$C48=""),"",IFERROR(SUMIFS('KNOWIFY REVIEW'!$AH$4:$AH$400,'KNOWIFY REVIEW'!$AB$4:$AB$400,$B48,'KNOWIFY REVIEW'!$AC$4:$AC$400,IF(OR($C48=INPUTS!$B$69,$C48=INPUTS!$B$70),INPUTS!$B$71,$C48),'KNOWIFY REVIEW'!$AD$4:$AD$400,1)/SUMIFS('KNOWIFY REVIEW'!$AG$4:$AG$400,'KNOWIFY REVIEW'!$AB$4:$AB$400,$B48,'KNOWIFY REVIEW'!$AC$4:$AC$400,IF(OR($C48=INPUTS!$B$69,$C48=INPUTS!$B$70),INPUTS!$B$71,$C48),'KNOWIFY REVIEW'!$AD$4:$AD$400,1),"")) | S48: =IF(MAX(N($Q48),N($R48))>1.1,"Past job ran over budget","")
A49: H-FN-LBL | B49: H | C49: 04 Finishing (Labour) | D49: Pipe Labelling | F49: LS | K49: Y | L49: =($E49*$G49+$I49)*(1+IF($K49="N",0,INPUTS!$C$23)) -> 0 | M49: =$E49*$H49+$J49 -> 0 | N49: =$M49*IF(OR($B49="V",$B49="AC"),'LABOUR RATES'!$E$26,'LABOUR RATES'!$E$11) -> 0 | O49: =$M49*IF(OR($B49="V",$B49="AC"),'LABOUR RATES'!$C$27,'LABOUR RATES'!$C$12) -> 0 | P49: =$L49+$N49+$O49 -> 0 | Q49: =IF(OR($B49="",$C49=""),"",IFERROR(SUMIFS('KNOWIFY REVIEW'!$AF$4:$AF$400,'KNOWIFY REVIEW'!$AB$4:$AB$400,$B49,'KNOWIFY REVIEW'!$AC$4:$AC$400,$C49,'KNOWIFY REVIEW'!$AD$4:$AD$400,1)/SUMIFS('KNOWIFY REVIEW'!$AE$4:$AE$400,'KNOWIFY REVIEW'!$AB$4:$AB$400,$B49,'KNOWIFY REVIEW'!$AC$4:$AC$400,$C49,'KNOWIFY REVIEW'!$AD$4:$AD$400,1),"")) | R49: =IF(OR($B49="",$C49=""),"",IFERROR(SUMIFS('KNOWIFY REVIEW'!$AH$4:$AH$400,'KNOWIFY REVIEW'!$AB$4:$AB$400,$B49,'KNOWIFY REVIEW'!$AC$4:$AC$400,IF(OR($C49=INPUTS!$B$69,$C49=INPUTS!$B$70),INPUTS!$B$71,$C49),'KNOWIFY REVIEW'!$AD$4:$AD$400,1)/SUMIFS('KNOWIFY REVIEW'!$AG$4:$AG$400,'KNOWIFY REVIEW'!$AB$4:$AB$400,$B49,'KNOWIFY REVIEW'!$AC$4:$AC$400,IF(OR($C49=INPUTS!$B$69,$C49=INPUTS!$B$70),INPUTS!$B$71,$C49),'KNOWIFY REVIEW'!$AD$4:$AD$400,1),"")) | S49: =IF(MAX(N($Q49),N($R49))>1.1,"Past job ran over budget","")
A50: H-EQ-MECH | B50: H | C50: 06 Fixtures & Equipment Supply | D50: Mechanical Room | F50: LS | K50: Y | L50: =($E50*$G50+$I50)*(1+IF($K50="N",0,INPUTS!$C$23)) -> 0 | M50: =$E50*$H50+$J50 -> 0 | N50: =$M50*IF(OR($B50="V",$B50="AC"),'LABOUR RATES'!$E$26,'LABOUR RATES'!$E$11) -> 0 | O50: =$M50*IF(OR($B50="V",$B50="AC"),'LABOUR RATES'!$C$27,'LABOUR RATES'!$C$12) -> 0 | P50: =$L50+$N50+$O50 -> 0 | Q50: =IF(OR($B50="",$C50=""),"",IFERROR(SUMIFS('KNOWIFY REVIEW'!$AF$4:$AF$400,'KNOWIFY REVIEW'!$AB$4:$AB$400,$B50,'KNOWIFY REVIEW'!$AC$4:$AC$400,$C50,'KNOWIFY REVIEW'!$AD$4:$AD$400,1)/SUMIFS('KNOWIFY REVIEW'!$AE$4:$AE$400,'KNOWIFY REVIEW'!$AB$4:$AB$400,$B50,'KNOWIFY REVIEW'!$AC$4:$AC$400,$C50,'KNOWIFY REVIEW'!$AD$4:$AD$400,1),"")) | R50: =IF(OR($B50="",$C50=""),"",IFERROR(SUMIFS('KNOWIFY REVIEW'!$AH$4:$AH$400,'KNOWIFY REVIEW'!$AB$4:$AB$400,$B50,'KNOWIFY REVIEW'!$AC$4:$AC$400,IF(OR($C50=INPUTS!$B$69,$C50=INPUTS!$B$70),INPUTS!$B$71,$C50),'KNOWIFY REVIEW'!$AD$4:$AD$400,1)/SUMIFS('KNOWIFY REVIEW'!$AG$4:$AG$400,'KNOWIFY REVIEW'!$AB$4:$AB$400,$B50,'KNOWIFY REVIEW'!$AC$4:$AC$400,IF(OR($C50=INPUTS!$B$69,$C50=INPUTS!$B$70),INPUTS!$B$71,$C50),'KNOWIFY REVIEW'!$AD$4:$AD$400,1),"")) | S50: =IF(MAX(N($Q50),N($R50))>1.1,"Past job ran over budget","")
A51: H-EQ-EQP | B51: H | C51: 06 Fixtures & Equipment Supply | D51: Hydronic Equipment (boilers, pumps, HX) | F51: LS | K51: Y | L51: =($E51*$G51+$I51)*(1+IF($K51="N",0,INPUTS!$C$23)) -> 0 | M51: =$E51*$H51+$J51 -> 0 | N51: =$M51*IF(OR($B51="V",$B51="AC"),'LABOUR RATES'!$E$26,'LABOUR RATES'!$E$11) -> 0 | O51: =$M51*IF(OR($B51="V",$B51="AC"),'LABOUR RATES'!$C$27,'LABOUR RATES'!$C$12) -> 0 | P51: =$L51+$N51+$O51 -> 0 | Q51: =IF(OR($B51="",$C51=""),"",IFERROR(SUMIFS('KNOWIFY REVIEW'!$AF$4:$AF$400,'KNOWIFY REVIEW'!$AB$4:$AB$400,$B51,'KNOWIFY REVIEW'!$AC$4:$AC$400,$C51,'KNOWIFY REVIEW'!$AD$4:$AD$400,1)/SUMIFS('KNOWIFY REVIEW'!$AE$4:$AE$400,'KNOWIFY REVIEW'!$AB$4:$AB$400,$B51,'KNOWIFY REVIEW'!$AC$4:$AC$400,$C51,'KNOWIFY REVIEW'!$AD$4:$AD$400,1),"")) | R51: =IF(OR($B51="",$C51=""),"",IFERROR(SUMIFS('KNOWIFY REVIEW'!$AH$4:$AH$400,'KNOWIFY REVIEW'!$AB$4:$AB$400,$B51,'KNOWIFY REVIEW'!$AC$4:$AC$400,IF(OR($C51=INPUTS!$B$69,$C51=INPUTS!$B$70),INPUTS!$B$71,$C51),'KNOWIFY REVIEW'!$AD$4:$AD$400,1)/SUMIFS('KNOWIFY REVIEW'!$AG$4:$AG$400,'KNOWIFY REVIEW'!$AB$4:$AB$400,$B51,'KNOWIFY REVIEW'!$AC$4:$AC$400,IF(OR($C51=INPUTS!$B$69,$C51=INPUTS!$B$70),INPUTS!$B$71,$C51),'KNOWIFY REVIEW'!$AD$4:$AD$400,1),"")) | S51: =IF(MAX(N($Q51),N($R51))>1.1,"Past job ran over budget","")
A52: H-TS-TEST | B52: H | C52: 07 Testing, TAB & Commissioning | D52: Testing | F52: LS | K52: Y | L52: =($E52*$G52+$I52)*(1+IF($K52="N",0,INPUTS!$C$23)) -> 0 | M52: =$E52*$H52+$J52 -> 0 | N52: =$M52*IF(OR($B52="V",$B52="AC"),'LABOUR RATES'!$E$26,'LABOUR RATES'!$E$11) -> 0 | O52: =$M52*IF(OR($B52="V",$B52="AC"),'LABOUR RATES'!$C$27,'LABOUR RATES'!$C$12) -> 0 | P52: =$L52+$N52+$O52 -> 0 | Q52: =IF(OR($B52="",$C52=""),"",IFERROR(SUMIFS('KNOWIFY REVIEW'!$AF$4:$AF$400,'KNOWIFY REVIEW'!$AB$4:$AB$400,$B52,'KNOWIFY REVIEW'!$AC$4:$AC$400,$C52,'KNOWIFY REVIEW'!$AD$4:$AD$400,1)/SUMIFS('KNOWIFY REVIEW'!$AE$4:$AE$400,'KNOWIFY REVIEW'!$AB$4:$AB$400,$B52,'KNOWIFY REVIEW'!$AC$4:$AC$400,$C52,'KNOWIFY REVIEW'!$AD$4:$AD$400,1),"")) | R52: =IF(OR($B52="",$C52=""),"",IFERROR(SUMIFS('KNOWIFY REVIEW'!$AH$4:$AH$400,'KNOWIFY REVIEW'!$AB$4:$AB$400,$B52,'KNOWIFY REVIEW'!$AC$4:$AC$400,IF(OR($C52=INPUTS!$B$69,$C52=INPUTS!$B$70),INPUTS!$B$71,$C52),'KNOWIFY REVIEW'!$AD$4:$AD$400,1)/SUMIFS('KNOWIFY REVIEW'!$AG$4:$AG$400,'KNOWIFY REVIEW'!$AB$4:$AB$400,$B52,'KNOWIFY REVIEW'!$AC$4:$AC$400,IF(OR($C52=INPUTS!$B$69,$C52=INPUTS!$B$70),INPUTS!$B$71,$C52),'KNOWIFY REVIEW'!$AD$4:$AD$400,1),"")) | S52: =IF(MAX(N($Q52),N($R52))>1.1,"Past job ran over budget","")
K53: Y | L53: =($E53*$G53+$I53)*(1+IF($K53="N",0,INPUTS!$C$23)) -> 0 | M53: =$E53*$H53+$J53 -> 0 | N53: =$M53*IF(OR($B53="V",$B53="AC"),'LABOUR RATES'!$E$26,'LABOUR RATES'!$E$11) -> 0 | O53: =$M53*IF(OR($B53="V",$B53="AC"),'LABOUR RATES'!$C$27,'LABOUR RATES'!$C$12) -> 0 | P53: =$L53+$N53+$O53 -> 0 | Q53: =IF(OR($B53="",$C53=""),"",IFERROR(SUMIFS('KNOWIFY REVIEW'!$AF$4:$AF$400,'KNOWIFY REVIEW'!$AB$4:$AB$400,$B53,'KNOWIFY REVIEW'!$AC$4:$AC$400,$C53,'KNOWIFY REVIEW'!$AD$4:$AD$400,1)/SUMIFS('KNOWIFY REVIEW'!$AE$4:$AE$400,'KNOWIFY REVIEW'!$AB$4:$AB$400,$B53,'KNOWIFY REVIEW'!$AC$4:$AC$400,$C53,'KNOWIFY REVIEW'!$AD$4:$AD$400,1),"")) | R53: =IF(OR($B53="",$C53=""),"",IFERROR(SUMIFS('KNOWIFY REVIEW'!$AH$4:$AH$400,'KNOWIFY REVIEW'!$AB$4:$AB$400,$B53,'KNOWIFY REVIEW'!$AC$4:$AC$400,IF(OR($C53=INPUTS!$B$69,$C53=INPUTS!$B$70),INPUTS!$B$71,$C53),'KNOWIFY REVIEW'!$AD$4:$AD$400,1)/SUMIFS('KNOWIFY REVIEW'!$AG$4:$AG$400,'KNOWIFY REVIEW'!$AB$4:$AB$400,$B53,'KNOWIFY REVIEW'!$AC$4:$AC$400,IF(OR($C53=INPUTS!$B$69,$C53=INPUTS!$B$70),INPUTS!$B$71,$C53),'KNOWIFY REVIEW'!$AD$4:$AD$400,1),"")) | S53: =IF(MAX(N($Q53),N($R53))>1.1,"Past job ran over budget","")
K54: Y | L54: =($E54*$G54+$I54)*(1+IF($K54="N",0,INPUTS!$C$23)) -> 0 | M54: =$E54*$H54+$J54 -> 0 | N54: =$M54*IF(OR($B54="V",$B54="AC"),'LABOUR RATES'!$E$26,'LABOUR RATES'!$E$11) -> 0 | O54: =$M54*IF(OR($B54="V",$B54="AC"),'LABOUR RATES'!$C$27,'LABOUR RATES'!$C$12) -> 0 | P54: =$L54+$N54+$O54 -> 0 | Q54: =IF(OR($B54="",$C54=""),"",IFERROR(SUMIFS('KNOWIFY REVIEW'!$AF$4:$AF$400,'KNOWIFY REVIEW'!$AB$4:$AB$400,$B54,'KNOWIFY REVIEW'!$AC$4:$AC$400,$C54,'KNOWIFY REVIEW'!$AD$4:$AD$400,1)/SUMIFS('KNOWIFY REVIEW'!$AE$4:$AE$400,'KNOWIFY REVIEW'!$AB$4:$AB$400,$B54,'KNOWIFY REVIEW'!$AC$4:$AC$400,$C54,'KNOWIFY REVIEW'!$AD$4:$AD$400,1),"")) | R54: =IF(OR($B54="",$C54=""),"",IFERROR(SUMIFS('KNOWIFY REVIEW'!$AH$4:$AH$400,'KNOWIFY REVIEW'!$AB$4:$AB$400,$B54,'KNOWIFY REVIEW'!$AC$4:$AC$400,IF(OR($C54=INPUTS!$B$69,$C54=INPUTS!$B$70),INPUTS!$B$71,$C54),'KNOWIFY REVIEW'!$AD$4:$AD$400,1)/SUMIFS('KNOWIFY REVIEW'!$AG$4:$AG$400,'KNOWIFY REVIEW'!$AB$4:$AB$400,$B54,'KNOWIFY REVIEW'!$AC$4:$AC$400,IF(OR($C54=INPUTS!$B$69,$C54=INPUTS!$B$70),INPUTS!$B$71,$C54),'KNOWIFY REVIEW'!$AD$4:$AD$400,1),"")) | S54: =IF(MAX(N($Q54),N($R54))>1.1,"Past job ran over budget","")
K55: Y | L55: =($E55*$G55+$I55)*(1+IF($K55="N",0,INPUTS!$C$23)) -> 0 | M55: =$E55*$H55+$J55 -> 0 | N55: =$M55*IF(OR($B55="V",$B55="AC"),'LABOUR RATES'!$E$26,'LABOUR RATES'!$E$11) -> 0 | O55: =$M55*IF(OR($B55="V",$B55="AC"),'LABOUR RATES'!$C$27,'LABOUR RATES'!$C$12) -> 0 | P55: =$L55+$N55+$O55 -> 0 | Q55: =IF(OR($B55="",$C55=""),"",IFERROR(SUMIFS('KNOWIFY REVIEW'!$AF$4:$AF$400,'KNOWIFY REVIEW'!$AB$4:$AB$400,$B55,'KNOWIFY REVIEW'!$AC$4:$AC$400,$C55,'KNOWIFY REVIEW'!$AD$4:$AD$400,1)/SUMIFS('KNOWIFY REVIEW'!$AE$4:$AE$400,'KNOWIFY REVIEW'!$AB$4:$AB$400,$B55,'KNOWIFY REVIEW'!$AC$4:$AC$400,$C55,'KNOWIFY REVIEW'!$AD$4:$AD$400,1),"")) | R55: =IF(OR($B55="",$C55=""),"",IFERROR(SUMIFS('KNOWIFY REVIEW'!$AH$4:$AH$400,'KNOWIFY REVIEW'!$AB$4:$AB$400,$B55,'KNOWIFY REVIEW'!$AC$4:$AC$400,IF(OR($C55=INPUTS!$B$69,$C55=INPUTS!$B$70),INPUTS!$B$71,$C55),'KNOWIFY REVIEW'!$AD$4:$AD$400,1)/SUMIFS('KNOWIFY REVIEW'!$AG$4:$AG$400,'KNOWIFY REVIEW'!$AB$4:$AB$400,$B55,'KNOWIFY REVIEW'!$AC$4:$AC$400,IF(OR($C55=INPUTS!$B$69,$C55=INPUTS!$B$70),INPUTS!$B$71,$C55),'KNOWIFY REVIEW'!$AD$4:$AD$400,1),"")) | S55: =IF(MAX(N($Q55),N($R55))>1.1,"Past job ran over budget","")
K56: Y | L56: =($E56*$G56+$I56)*(1+IF($K56="N",0,INPUTS!$C$23)) -> 0 | M56: =$E56*$H56+$J56 -> 0 | N56: =$M56*IF(OR($B56="V",$B56="AC"),'LABOUR RATES'!$E$26,'LABOUR RATES'!$E$11) -> 0 | O56: =$M56*IF(OR($B56="V",$B56="AC"),'LABOUR RATES'!$C$27,'LABOUR RATES'!$C$12) -> 0 | P56: =$L56+$N56+$O56 -> 0 | Q56: =IF(OR($B56="",$C56=""),"",IFERROR(SUMIFS('KNOWIFY REVIEW'!$AF$4:$AF$400,'KNOWIFY REVIEW'!$AB$4:$AB$400,$B56,'KNOWIFY REVIEW'!$AC$4:$AC$400,$C56,'KNOWIFY REVIEW'!$AD$4:$AD$400,1)/SUMIFS('KNOWIFY REVIEW'!$AE$4:$AE$400,'KNOWIFY REVIEW'!$AB$4:$AB$400,$B56,'KNOWIFY REVIEW'!$AC$4:$AC$400,$C56,'KNOWIFY REVIEW'!$AD$4:$AD$400,1),"")) | R56: =IF(OR($B56="",$C56=""),"",IFERROR(SUMIFS('KNOWIFY REVIEW'!$AH$4:$AH$400,'KNOWIFY REVIEW'!$AB$4:$AB$400,$B56,'KNOWIFY REVIEW'!$AC$4:$AC$400,IF(OR($C56=INPUTS!$B$69,$C56=INPUTS!$B$70),INPUTS!$B$71,$C56),'KNOWIFY REVIEW'!$AD$4:$AD$400,1)/SUMIFS('KNOWIFY REVIEW'!$AG$4:$AG$400,'KNOWIFY REVIEW'!$AB$4:$AB$400,$B56,'KNOWIFY REVIEW'!$AC$4:$AC$400,IF(OR($C56=INPUTS!$B$69,$C56=INPUTS!$B$70),INPUTS!$B$71,$C56),'KNOWIFY REVIEW'!$AD$4:$AD$400,1),"")) | S56: =IF(MAX(N($Q56),N($R56))>1.1,"Past job ran over budget","")
K57: Y | L57: =($E57*$G57+$I57)*(1+IF($K57="N",0,INPUTS!$C$23)) -> 0 | M57: =$E57*$H57+$J57 -> 0 | N57: =$M57*IF(OR($B57="V",$B57="AC"),'LABOUR RATES'!$E$26,'LABOUR RATES'!$E$11) -> 0 | O57: =$M57*IF(OR($B57="V",$B57="AC"),'LABOUR RATES'!$C$27,'LABOUR RATES'!$C$12) -> 0 | P57: =$L57+$N57+$O57 -> 0 | Q57: =IF(OR($B57="",$C57=""),"",IFERROR(SUMIFS('KNOWIFY REVIEW'!$AF$4:$AF$400,'KNOWIFY REVIEW'!$AB$4:$AB$400,$B57,'KNOWIFY REVIEW'!$AC$4:$AC$400,$C57,'KNOWIFY REVIEW'!$AD$4:$AD$400,1)/SUMIFS('KNOWIFY REVIEW'!$AE$4:$AE$400,'KNOWIFY REVIEW'!$AB$4:$AB$400,$B57,'KNOWIFY REVIEW'!$AC$4:$AC$400,$C57,'KNOWIFY REVIEW'!$AD$4:$AD$400,1),"")) | R57: =IF(OR($B57="",$C57=""),"",IFERROR(SUMIFS('KNOWIFY REVIEW'!$AH$4:$AH$400,'KNOWIFY REVIEW'!$AB$4:$AB$400,$B57,'KNOWIFY REVIEW'!$AC$4:$AC$400,IF(OR($C57=INPUTS!$B$69,$C57=INPUTS!$B$70),INPUTS!$B$71,$C57),'KNOWIFY REVIEW'!$AD$4:$AD$400,1)/SUMIFS('KNOWIFY REVIEW'!$AG$4:$AG$400,'KNOWIFY REVIEW'!$AB$4:$AB$400,$B57,'KNOWIFY REVIEW'!$AC$4:$AC$400,IF(OR($C57=INPUTS!$B$69,$C57=INPUTS!$B$70),INPUTS!$B$71,$C57),'KNOWIFY REVIEW'!$AD$4:$AD$400,1),"")) | S57: =IF(MAX(N($Q57),N($R57))>1.1,"Past job ran over budget","")
K58: Y | L58: =($E58*$G58+$I58)*(1+IF($K58="N",0,INPUTS!$C$23)) -> 0 | M58: =$E58*$H58+$J58 -> 0 | N58: =$M58*IF(OR($B58="V",$B58="AC"),'LABOUR RATES'!$E$26,'LABOUR RATES'!$E$11) -> 0 | O58: =$M58*IF(OR($B58="V",$B58="AC"),'LABOUR RATES'!$C$27,'LABOUR RATES'!$C$12) -> 0 | P58: =$L58+$N58+$O58 -> 0 | Q58: =IF(OR($B58="",$C58=""),"",IFERROR(SUMIFS('KNOWIFY REVIEW'!$AF$4:$AF$400,'KNOWIFY REVIEW'!$AB$4:$AB$400,$B58,'KNOWIFY REVIEW'!$AC$4:$AC$400,$C58,'KNOWIFY REVIEW'!$AD$4:$AD$400,1)/SUMIFS('KNOWIFY REVIEW'!$AE$4:$AE$400,'KNOWIFY REVIEW'!$AB$4:$AB$400,$B58,'KNOWIFY REVIEW'!$AC$4:$AC$400,$C58,'KNOWIFY REVIEW'!$AD$4:$AD$400,1),"")) | R58: =IF(OR($B58="",$C58=""),"",IFERROR(SUMIFS('KNOWIFY REVIEW'!$AH$4:$AH$400,'KNOWIFY REVIEW'!$AB$4:$AB$400,$B58,'KNOWIFY REVIEW'!$AC$4:$AC$400,IF(OR($C58=INPUTS!$B$69,$C58=INPUTS!$B$70),INPUTS!$B$71,$C58),'KNOWIFY REVIEW'!$AD$4:$AD$400,1)/SUMIFS('KNOWIFY REVIEW'!$AG$4:$AG$400,'KNOWIFY REVIEW'!$AB$4:$AB$400,$B58,'KNOWIFY REVIEW'!$AC$4:$AC$400,IF(OR($C58=INPUTS!$B$69,$C58=INPUTS!$B$70),INPUTS!$B$71,$C58),'KNOWIFY REVIEW'!$AD$4:$AD$400,1),"")) | S58: =IF(MAX(N($Q58),N($R58))>1.1,"Past job ran over budget","")
K59: Y | L59: =($E59*$G59+$I59)*(1+IF($K59="N",0,INPUTS!$C$23)) -> 0 | M59: =$E59*$H59+$J59 -> 0 | N59: =$M59*IF(OR($B59="V",$B59="AC"),'LABOUR RATES'!$E$26,'LABOUR RATES'!$E$11) -> 0 | O59: =$M59*IF(OR($B59="V",$B59="AC"),'LABOUR RATES'!$C$27,'LABOUR RATES'!$C$12) -> 0 | P59: =$L59+$N59+$O59 -> 0 | Q59: =IF(OR($B59="",$C59=""),"",IFERROR(SUMIFS('KNOWIFY REVIEW'!$AF$4:$AF$400,'KNOWIFY REVIEW'!$AB$4:$AB$400,$B59,'KNOWIFY REVIEW'!$AC$4:$AC$400,$C59,'KNOWIFY REVIEW'!$AD$4:$AD$400,1)/SUMIFS('KNOWIFY REVIEW'!$AE$4:$AE$400,'KNOWIFY REVIEW'!$AB$4:$AB$400,$B59,'KNOWIFY REVIEW'!$AC$4:$AC$400,$C59,'KNOWIFY REVIEW'!$AD$4:$AD$400,1),"")) | R59: =IF(OR($B59="",$C59=""),"",IFERROR(SUMIFS('KNOWIFY REVIEW'!$AH$4:$AH$400,'KNOWIFY REVIEW'!$AB$4:$AB$400,$B59,'KNOWIFY REVIEW'!$AC$4:$AC$400,IF(OR($C59=INPUTS!$B$69,$C59=INPUTS!$B$70),INPUTS!$B$71,$C59),'KNOWIFY REVIEW'!$AD$4:$AD$400,1)/SUMIFS('KNOWIFY REVIEW'!$AG$4:$AG$400,'KNOWIFY REVIEW'!$AB$4:$AB$400,$B59,'KNOWIFY REVIEW'!$AC$4:$AC$400,IF(OR($C59=INPUTS!$B$69,$C59=INPUTS!$B$70),INPUTS!$B$71,$C59),'KNOWIFY REVIEW'!$AD$4:$AD$400,1),"")) | S59: =IF(MAX(N($Q59),N($R59))>1.1,"Past job ran over budget","")
K60: Y | L60: =($E60*$G60+$I60)*(1+IF($K60="N",0,INPUTS!$C$23)) -> 0 | M60: =$E60*$H60+$J60 -> 0 | N60: =$M60*IF(OR($B60="V",$B60="AC"),'LABOUR RATES'!$E$26,'LABOUR RATES'!$E$11) -> 0 | O60: =$M60*IF(OR($B60="V",$B60="AC"),'LABOUR RATES'!$C$27,'LABOUR RATES'!$C$12) -> 0 | P60: =$L60+$N60+$O60 -> 0 | Q60: =IF(OR($B60="",$C60=""),"",IFERROR(SUMIFS('KNOWIFY REVIEW'!$AF$4:$AF$400,'KNOWIFY REVIEW'!$AB$4:$AB$400,$B60,'KNOWIFY REVIEW'!$AC$4:$AC$400,$C60,'KNOWIFY REVIEW'!$AD$4:$AD$400,1)/SUMIFS('KNOWIFY REVIEW'!$AE$4:$AE$400,'KNOWIFY REVIEW'!$AB$4:$AB$400,$B60,'KNOWIFY REVIEW'!$AC$4:$AC$400,$C60,'KNOWIFY REVIEW'!$AD$4:$AD$400,1),"")) | R60: =IF(OR($B60="",$C60=""),"",IFERROR(SUMIFS('KNOWIFY REVIEW'!$AH$4:$AH$400,'KNOWIFY REVIEW'!$AB$4:$AB$400,$B60,'KNOWIFY REVIEW'!$AC$4:$AC$400,IF(OR($C60=INPUTS!$B$69,$C60=INPUTS!$B$70),INPUTS!$B$71,$C60),'KNOWIFY REVIEW'!$AD$4:$AD$400,1)/SUMIFS('KNOWIFY REVIEW'!$AG$4:$AG$400,'KNOWIFY REVIEW'!$AB$4:$AB$400,$B60,'KNOWIFY REVIEW'!$AC$4:$AC$400,IF(OR($C60=INPUTS!$B$69,$C60=INPUTS!$B$70),INPUTS!$B$71,$C60),'KNOWIFY REVIEW'!$AD$4:$AD$400,1),"")) | S60: =IF(MAX(N($Q60),N($R60))>1.1,"Past job ran over budget","")
K61: Y | L61: =($E61*$G61+$I61)*(1+IF($K61="N",0,INPUTS!$C$23)) -> 0 | M61: =$E61*$H61+$J61 -> 0 | N61: =$M61*IF(OR($B61="V",$B61="AC"),'LABOUR RATES'!$E$26,'LABOUR RATES'!$E$11) -> 0 | O61: =$M61*IF(OR($B61="V",$B61="AC"),'LABOUR RATES'!$C$27,'LABOUR RATES'!$C$12) -> 0 | P61: =$L61+$N61+$O61 -> 0 | Q61: =IF(OR($B61="",$C61=""),"",IFERROR(SUMIFS('KNOWIFY REVIEW'!$AF$4:$AF$400,'KNOWIFY REVIEW'!$AB$4:$AB$400,$B61,'KNOWIFY REVIEW'!$AC$4:$AC$400,$C61,'KNOWIFY REVIEW'!$AD$4:$AD$400,1)/SUMIFS('KNOWIFY REVIEW'!$AE$4:$AE$400,'KNOWIFY REVIEW'!$AB$4:$AB$400,$B61,'KNOWIFY REVIEW'!$AC$4:$AC$400,$C61,'KNOWIFY REVIEW'!$AD$4:$AD$400,1),"")) | R61: =IF(OR($B61="",$C61=""),"",IFERROR(SUMIFS('KNOWIFY REVIEW'!$AH$4:$AH$400,'KNOWIFY REVIEW'!$AB$4:$AB$400,$B61,'KNOWIFY REVIEW'!$AC$4:$AC$400,IF(OR($C61=INPUTS!$B$69,$C61=INPUTS!$B$70),INPUTS!$B$71,$C61),'KNOWIFY REVIEW'!$AD$4:$AD$400,1)/SUMIFS('KNOWIFY REVIEW'!$AG$4:$AG$400,'KNOWIFY REVIEW'!$AB$4:$AB$400,$B61,'KNOWIFY REVIEW'!$AC$4:$AC$400,IF(OR($C61=INPUTS!$B$69,$C61=INPUTS!$B$70),INPUTS!$B$71,$C61),'KNOWIFY REVIEW'!$AD$4:$AD$400,1),"")) | S61: =IF(MAX(N($Q61),N($R61))>1.1,"Past job ran over budget","")
K62: Y | L62: =($E62*$G62+$I62)*(1+IF($K62="N",0,INPUTS!$C$23)) -> 0 | M62: =$E62*$H62+$J62 -> 0 | N62: =$M62*IF(OR($B62="V",$B62="AC"),'LABOUR RATES'!$E$26,'LABOUR RATES'!$E$11) -> 0 | O62: =$M62*IF(OR($B62="V",$B62="AC"),'LABOUR RATES'!$C$27,'LABOUR RATES'!$C$12) -> 0 | P62: =$L62+$N62+$O62 -> 0 | Q62: =IF(OR($B62="",$C62=""),"",IFERROR(SUMIFS('KNOWIFY REVIEW'!$AF$4:$AF$400,'KNOWIFY REVIEW'!$AB$4:$AB$400,$B62,'KNOWIFY REVIEW'!$AC$4:$AC$400,$C62,'KNOWIFY REVIEW'!$AD$4:$AD$400,1)/SUMIFS('KNOWIFY REVIEW'!$AE$4:$AE$400,'KNOWIFY REVIEW'!$AB$4:$AB$400,$B62,'KNOWIFY REVIEW'!$AC$4:$AC$400,$C62,'KNOWIFY REVIEW'!$AD$4:$AD$400,1),"")) | R62: =IF(OR($B62="",$C62=""),"",IFERROR(SUMIFS('KNOWIFY REVIEW'!$AH$4:$AH$400,'KNOWIFY REVIEW'!$AB$4:$AB$400,$B62,'KNOWIFY REVIEW'!$AC$4:$AC$400,IF(OR($C62=INPUTS!$B$69,$C62=INPUTS!$B$70),INPUTS!$B$71,$C62),'KNOWIFY REVIEW'!$AD$4:$AD$400,1)/SUMIFS('KNOWIFY REVIEW'!$AG$4:$AG$400,'KNOWIFY REVIEW'!$AB$4:$AB$400,$B62,'KNOWIFY REVIEW'!$AC$4:$AC$400,IF(OR($C62=INPUTS!$B$69,$C62=INPUTS!$B$70),INPUTS!$B$71,$C62),'KNOWIFY REVIEW'!$AD$4:$AD$400,1),"")) | S62: =IF(MAX(N($Q62),N($R62))>1.1,"Past job ran over budget","")
K63: Y | L63: =($E63*$G63+$I63)*(1+IF($K63="N",0,INPUTS!$C$23)) -> 0 | M63: =$E63*$H63+$J63 -> 0 | N63: =$M63*IF(OR($B63="V",$B63="AC"),'LABOUR RATES'!$E$26,'LABOUR RATES'!$E$11) -> 0 | O63: =$M63*IF(OR($B63="V",$B63="AC"),'LABOUR RATES'!$C$27,'LABOUR RATES'!$C$12) -> 0 | P63: =$L63+$N63+$O63 -> 0 | Q63: =IF(OR($B63="",$C63=""),"",IFERROR(SUMIFS('KNOWIFY REVIEW'!$AF$4:$AF$400,'KNOWIFY REVIEW'!$AB$4:$AB$400,$B63,'KNOWIFY REVIEW'!$AC$4:$AC$400,$C63,'KNOWIFY REVIEW'!$AD$4:$AD$400,1)/SUMIFS('KNOWIFY REVIEW'!$AE$4:$AE$400,'KNOWIFY REVIEW'!$AB$4:$AB$400,$B63,'KNOWIFY REVIEW'!$AC$4:$AC$400,$C63,'KNOWIFY REVIEW'!$AD$4:$AD$400,1),"")) | R63: =IF(OR($B63="",$C63=""),"",IFERROR(SUMIFS('KNOWIFY REVIEW'!$AH$4:$AH$400,'KNOWIFY REVIEW'!$AB$4:$AB$400,$B63,'KNOWIFY REVIEW'!$AC$4:$AC$400,IF(OR($C63=INPUTS!$B$69,$C63=INPUTS!$B$70),INPUTS!$B$71,$C63),'KNOWIFY REVIEW'!$AD$4:$AD$400,1)/SUMIFS('KNOWIFY REVIEW'!$AG$4:$AG$400,'KNOWIFY REVIEW'!$AB$4:$AB$400,$B63,'KNOWIFY REVIEW'!$AC$4:$AC$400,IF(OR($C63=INPUTS!$B$69,$C63=INPUTS!$B$70),INPUTS!$B$71,$C63),'KNOWIFY REVIEW'!$AD$4:$AD$400,1),"")) | S63: =IF(MAX(N($Q63),N($R63))>1.1,"Past job ran over budget","")
K64: Y | L64: =($E64*$G64+$I64)*(1+IF($K64="N",0,INPUTS!$C$23)) -> 0 | M64: =$E64*$H64+$J64 -> 0 | N64: =$M64*IF(OR($B64="V",$B64="AC"),'LABOUR RATES'!$E$26,'LABOUR RATES'!$E$11) -> 0 | O64: =$M64*IF(OR($B64="V",$B64="AC"),'LABOUR RATES'!$C$27,'LABOUR RATES'!$C$12) -> 0 | P64: =$L64+$N64+$O64 -> 0 | Q64: =IF(OR($B64="",$C64=""),"",IFERROR(SUMIFS('KNOWIFY REVIEW'!$AF$4:$AF$400,'KNOWIFY REVIEW'!$AB$4:$AB$400,$B64,'KNOWIFY REVIEW'!$AC$4:$AC$400,$C64,'KNOWIFY REVIEW'!$AD$4:$AD$400,1)/SUMIFS('KNOWIFY REVIEW'!$AE$4:$AE$400,'KNOWIFY REVIEW'!$AB$4:$AB$400,$B64,'KNOWIFY REVIEW'!$AC$4:$AC$400,$C64,'KNOWIFY REVIEW'!$AD$4:$AD$400,1),"")) | R64: =IF(OR($B64="",$C64=""),"",IFERROR(SUMIFS('KNOWIFY REVIEW'!$AH$4:$AH$400,'KNOWIFY REVIEW'!$AB$4:$AB$400,$B64,'KNOWIFY REVIEW'!$AC$4:$AC$400,IF(OR($C64=INPUTS!$B$69,$C64=INPUTS!$B$70),INPUTS!$B$71,$C64),'KNOWIFY REVIEW'!$AD$4:$AD$400,1)/SUMIFS('KNOWIFY REVIEW'!$AG$4:$AG$400,'KNOWIFY REVIEW'!$AB$4:$AB$400,$B64,'KNOWIFY REVIEW'!$AC$4:$AC$400,IF(OR($C64=INPUTS!$B$69,$C64=INPUTS!$B$70),INPUTS!$B$71,$C64),'KNOWIFY REVIEW'!$AD$4:$AD$400,1),"")) | S64: =IF(MAX(N($Q64),N($R64))>1.1,"Past job ran over budget","")
... K156: Y | L156: =($E156*$G156+$I156)*(1+IF($K156="N",0,INPUTS!$C$23)) -> 0 | M156: =$E156*$H156+$J156 -> 0 | N156: =$M156*IF(OR($B156="V",$B156="AC"),'LABOUR RATES'!$E$26,'LABOUR RATES'!$E$11) -> 0 | O156: =$M156*IF(OR($B156="V",$B156="AC"),'LABOUR RATES'!$C$27,'LABOUR RATES'!$C$12) -> 0 | P156: =$L156+$N156+$O156 -> 0 | Q156: =IF(OR($B156="",$C156=""),"",IFERROR(SUMIFS('KNOWIFY REVIEW'!$AF$4:$AF$400,'KNOWIFY REVIEW'!$AB$4:$AB$400,$B156,'KNOWIFY REVIEW'!$AC$4:$AC$400,$C156,'KNOWIFY REVIEW'!$AD$4:$AD$400,1)/SUMIFS('KNOWIFY REVIEW'!$AE$4:$AE$400,'KNOWIFY REVIEW'!$AB$4:$AB$400,$B156,'KNOWIFY REVIEW'!$AC$4:$AC$400,$C156,'KNOWIFY REVIEW'!$AD$4:$AD$400,1),"")) | R156: =IF(OR($B156="",$C156=""),"",IFERROR(SUMIFS('KNOWIFY REVIEW'!$AH$4:$AH$400,'KNOWIFY REVIEW'!$AB$4:$AB$400,$B156,'KNOWIFY REVIEW'!$AC$4:$AC$400,IF(OR($C156=INPUTS!$B$69,$C156=INPUTS!$B$70),INPUTS!$B$71,$C156),'KNOWIFY REVIEW'!$AD$4:$AD$400,1)/SUMIFS('KNOWIFY REVIEW'!$AG$4:$AG$400,'KNOWIFY REVIEW'!$AB$4:$AB$400,$B156,'KNOWIFY REVIEW'!$AC$4:$AC$400,IF(OR($C156=INPUTS!$B$69,$C156=INPUTS!$B$70),INPUTS!$B$71,$C156),'KNOWIFY REVIEW'!$AD$4:$AD$400,1),"")) | S156: =IF(MAX(N($Q156),N($R156))>1.1,"Past job ran over budget","")

Sheet HVAC EST
A1: HVAC EST
A2: Ventilation (V) and Air Conditioning (AC). Identical columns and formulas to PLUMBING EST.
A3: TOTALS | L3: =SUM(L7:L156) -> 0 | M3: =SUM(M7:M156) -> 0 | N3: =SUM(N7:N156) -> 0 | O3: =SUM(O7:O156) -> 0 | P3: =SUM(P7:P156) -> 0
A4: Labour $ = Hours x crew-mix weighted burdened wage. Overhead $ = Hours x overhead $/hr. P/H rows use the P&H crew, V/AC rows use the HVAC crew. Q:R show how the same Div + Phase ran vs budget on the Knowify job pasted (1.30x = 30% over).
A6: Item Code | B6: Div | C6: Phase | D6: Description | E6: Qty | F6: Unit | G6: Material $/Unit | H6: Hrs/Unit | I6: Add Material $ | J6: Add Hrs | K6: PST? (Y/N) | L6: Material $ (incl PST) | M6: Hours | N6: Labour $ (wage+burden) | O6: Overhead $ | P6: TOTAL COST $ | Q6: Knowify Labour Actual/Budget | R6: Knowify Material Actual/Budget | S6: History Flag
A7: V-RI-DUCT | B7: V | C7: 03 Rough-in (Labour) | D7: Distribution Ductwork | F7: lb | K7: Y | L7: =($E7*$G7+$I7)*(1+IF($K7="N",0,INPUTS!$C$23)) -> 0 | M7: =$E7*$H7+$J7 -> 0 | N7: =$M7*IF(OR($B7="V",$B7="AC"),'LABOUR RATES'!$E$26,'LABOUR RATES'!$E$11) -> 0 | O7: =$M7*IF(OR($B7="V",$B7="AC"),'LABOUR RATES'!$C$27,'LABOUR RATES'!$C$12) -> 0 | P7: =$L7+$N7+$O7 -> 0 | Q7: =IF(OR($B7="",$C7=""),"",IFERROR(SUMIFS('KNOWIFY REVIEW'!$AF$4:$AF$400,'KNOWIFY REVIEW'!$AB$4:$AB$400,$B7,'KNOWIFY REVIEW'!$AC$4:$AC$400,$C7,'KNOWIFY REVIEW'!$AD$4:$AD$400,1)/SUMIFS('KNOWIFY REVIEW'!$AE$4:$AE$400,'KNOWIFY REVIEW'!$AB$4:$AB$400,$B7,'KNOWIFY REVIEW'!$AC$4:$AC$400,$C7,'KNOWIFY REVIEW'!$AD$4:$AD$400,1),"")) -> 1.7282942 | R7: =IF(OR($B7="",$C7=""),"",IFERROR(SUMIFS('KNOWIFY REVIEW'!$AH$4:$AH$400,'KNOWIFY REVIEW'!$AB$4:$AB$400,$B7,'KNOWIFY REVIEW'!$AC$4:$AC$400,IF(OR($C7=INPUTS!$B$69,$C7=INPUTS!$B$70),INPUTS!$B$71,$C7),'KNOWIFY REVIEW'!$AD$4:$AD$400,1)/SUMIFS('KNOWIFY REVIEW'!$AG$4:$AG$400,'KNOWIFY REVIEW'!$AB$4:$AB$400,$B7,'KNOWIFY REVIEW'!$AC$4:$AC$400,IF(OR($C7=INPUTS!$B$69,$C7=INPUTS!$B$70),INPUTS!$B$71,$C7),'KNOWIFY REVIEW'!$AD$4:$AD$400,1),"")) -> 1.8918975 | S7: =IF(MAX(N($Q7),N($R7))>1.1,"Past job ran over budget","") -> Past job ran over budget
A8: V-RI-SUITE | B8: V | C8: 03 Rough-in (Labour) | D8: Insuite Ductwork | F8: suite | K8: Y | L8: =($E8*$G8+$I8)*(1+IF($K8="N",0,INPUTS!$C$23)) -> 0 | M8: =$E8*$H8+$J8 -> 0 | N8: =$M8*IF(OR($B8="V",$B8="AC"),'LABOUR RATES'!$E$26,'LABOUR RATES'!$E$11) -> 0 | O8: =$M8*IF(OR($B8="V",$B8="AC"),'LABOUR RATES'!$C$27,'LABOUR RATES'!$C$12) -> 0 | P8: =$L8+$N8+$O8 -> 0 | Q8: =IF(OR($B8="",$C8=""),"",IFERROR(SUMIFS('KNOWIFY REVIEW'!$AF$4:$AF$400,'KNOWIFY REVIEW'!$AB$4:$AB$400,$B8,'KNOWIFY REVIEW'!$AC$4:$AC$400,$C8,'KNOWIFY REVIEW'!$AD$4:$AD$400,1)/SUMIFS('KNOWIFY REVIEW'!$AE$4:$AE$400,'KNOWIFY REVIEW'!$AB$4:$AB$400,$B8,'KNOWIFY REVIEW'!$AC$4:$AC$400,$C8,'KNOWIFY REVIEW'!$AD$4:$AD$400,1),"")) -> 1.7282942 | R8: =IF(OR($B8="",$C8=""),"",IFERROR(SUMIFS('KNOWIFY REVIEW'!$AH$4:$AH$400,'KNOWIFY REVIEW'!$AB$4:$AB$400,$B8,'KNOWIFY REVIEW'!$AC$4:$AC$400,IF(OR($C8=INPUTS!$B$69,$C8=INPUTS!$B$70),INPUTS!$B$71,$C8),'KNOWIFY REVIEW'!$AD$4:$AD$400,1)/SUMIFS('KNOWIFY REVIEW'!$AG$4:$AG$400,'KNOWIFY REVIEW'!$AB$4:$AB$400,$B8,'KNOWIFY REVIEW'!$AC$4:$AC$400,IF(OR($C8=INPUTS!$B$69,$C8=INPUTS!$B$70),INPUTS!$B$71,$C8),'KNOWIFY REVIEW'!$AD$4:$AD$400,1),"")) -> 1.8918975 | S8: =IF(MAX(N($Q8),N($R8))>1.1,"Past job ran over budget","") -> Past job ran over budget
A9: V-RI-COND | B9: V | C9: 03 Rough-in (Labour) | D9: Condensate Drains (if by HVAC) | F9: LS | K9: Y | L9: =($E9*$G9+$I9)*(1+IF($K9="N",0,INPUTS!$C$23)) -> 0 | M9: =$E9*$H9+$J9 -> 0 | N9: =$M9*IF(OR($B9="V",$B9="AC"),'LABOUR RATES'!$E$26,'LABOUR RATES'!$E$11) -> 0 | O9: =$M9*IF(OR($B9="V",$B9="AC"),'LABOUR RATES'!$C$27,'LABOUR RATES'!$C$12) -> 0 | P9: =$L9+$N9+$O9 -> 0 | Q9: =IF(OR($B9="",$C9=""),"",IFERROR(SUMIFS('KNOWIFY REVIEW'!$AF$4:$AF$400,'KNOWIFY REVIEW'!$AB$4:$AB$400,$B9,'KNOWIFY REVIEW'!$AC$4:$AC$400,$C9,'KNOWIFY REVIEW'!$AD$4:$AD$400,1)/SUMIFS('KNOWIFY REVIEW'!$AE$4:$AE$400,'KNOWIFY REVIEW'!$AB$4:$AB$400,$B9,'KNOWIFY REVIEW'!$AC$4:$AC$400,$C9,'KNOWIFY REVIEW'!$AD$4:$AD$400,1),"")) -> 1.7282942 | R9: =IF(OR($B9="",$C9=""),"",IFERROR(SUMIFS('KNOWIFY REVIEW'!$AH$4:$AH$400,'KNOWIFY REVIEW'!$AB$4:$AB$400,$B9,'KNOWIFY REVIEW'!$AC$4:$AC$400,IF(OR($C9=INPUTS!$B$69,$C9=INPUTS!$B$70),INPUTS!$B$71,$C9),'KNOWIFY REVIEW'!$AD$4:$AD$400,1)/SUMIFS('KNOWIFY REVIEW'!$AG$4:$AG$400,'KNOWIFY REVIEW'!$AB$4:$AB$400,$B9,'KNOWIFY REVIEW'!$AC$4:$AC$400,IF(OR($C9=INPUTS!$B$69,$C9=INPUTS!$B$70),INPUTS!$B$71,$C9),'KNOWIFY REVIEW'!$AD$4:$AD$400,1),"")) -> 1.8918975 | S9: =IF(MAX(N($Q9),N($R9))>1.1,"Past job ran over budget","") -> Past job ran over budget
A10: V-RI-INS | B10: V | C10: 03 Rough-in (Labour) | D10: Thermal Insulation (in-house) | F10: LS | K10: Y | L10: =($E10*$G10+$I10)*(1+IF($K10="N",0,INPUTS!$C$23)) -> 0 | M10: =$E10*$H10+$J10 -> 0 | N10: =$M10*IF(OR($B10="V",$B10="AC"),'LABOUR RATES'!$E$26,'LABOUR RATES'!$E$11) -> 0 | O10: =$M10*IF(OR($B10="V",$B10="AC"),'LABOUR RATES'!$C$27,'LABOUR RATES'!$C$12) -> 0 | P10: =$L10+$N10+$O10 -> 0 | Q10: =IF(OR($B10="",$C10=""),"",IFERROR(SUMIFS('KNOWIFY REVIEW'!$AF$4:$AF$400,'KNOWIFY REVIEW'!$AB$4:$AB$400,$B10,'KNOWIFY REVIEW'!$AC$4:$AC$400,$C10,'KNOWIFY REVIEW'!$AD$4:$AD$400,1)/SUMIFS('KNOWIFY REVIEW'!$AE$4:$AE$400,'KNOWIFY REVIEW'!$AB$4:$AB$400,$B10,'KNOWIFY REVIEW'!$AC$4:$AC$400,$C10,'KNOWIFY REVIEW'!$AD$4:$AD$400,1),"")) -> 1.7282942 | R10: =IF(OR($B10="",$C10=""),"",IFERROR(SUMIFS('KNOWIFY REVIEW'!$AH$4:$AH$400,'KNOWIFY REVIEW'!$AB$4:$AB$400,$B10,'KNOWIFY REVIEW'!$AC$4:$AC$400,IF(OR($C10=INPUTS!$B$69,$C10=INPUTS!$B$70),INPUTS!$B$71,$C10),'KNOWIFY REVIEW'!$AD$4:$AD$400,1)/SUMIFS('KNOWIFY REVIEW'!$AG$4:$AG$400,'KNOWIFY REVIEW'!$AB$4:$AB$400,$B10,'KNOWIFY REVIEW'!$AC$4:$AC$400,IF(OR($C10=INPUTS!$B$69,$C10=INPUTS!$B$70),INPUTS!$B$71,$C10),'KNOWIFY REVIEW'!$AD$4:$AD$400,1),"")) -> 1.8918975 | S10: =IF(MAX(N($Q10),N($R10))>1.1,"Past job ran over budget","") -> Past job ran over budget
A11: V-RI-CAN | B11: V | C11: 03 Rough-in (Labour) | D11: Canning / Cutting / Layout | F11: LS | K11: Y | L11: =($E11*$G11+$I11)*(1+IF($K11="N",0,INPUTS!$C$23)) -> 0 | M11: =$E11*$H11+$J11 -> 0 | N11: =$M11*IF(OR($B11="V",$B11="AC"),'LABOUR RATES'!$E$26,'LABOUR RATES'!$E$11) -> 0 | O11: =$M11*IF(OR($B11="V",$B11="AC"),'LABOUR RATES'!$C$27,'LABOUR RATES'!$C$12) -> 0 | P11: =$L11+$N11+$O11 -> 0 | Q11: =IF(OR($B11="",$C11=""),"",IFERROR(SUMIFS('KNOWIFY REVIEW'!$AF$4:$AF$400,'KNOWIFY REVIEW'!$AB$4:$AB$400,$B11,'KNOWIFY REVIEW'!$AC$4:$AC$400,$C11,'KNOWIFY REVIEW'!$AD$4:$AD$400,1)/SUMIFS('KNOWIFY REVIEW'!$AE$4:$AE$400,'KNOWIFY REVIEW'!$AB$4:$AB$400,$B11,'KNOWIFY REVIEW'!$AC$4:$AC$400,$C11,'KNOWIFY REVIEW'!$AD$4:$AD$400,1),"")) -> 1.7282942 | R11: =IF(OR($B11="",$C11=""),"",IFERROR(SUMIFS('KNOWIFY REVIEW'!$AH$4:$AH$400,'KNOWIFY REVIEW'!$AB$4:$AB$400,$B11,'KNOWIFY REVIEW'!$AC$4:$AC$400,IF(OR($C11=INPUTS!$B$69,$C11=INPUTS!$B$70),INPUTS!$B$71,$C11),'KNOWIFY REVIEW'!$AD$4:$AD$400,1)/SUMIFS('KNOWIFY REVIEW'!$AG$4:$AG$400,'KNOWIFY REVIEW'!$AB$4:$AB$400,$B11,'KNOWIFY REVIEW'!$AC$4:$AC$400,IF(OR($C11=INPUTS!$B$69,$C11=INPUTS!$B$70),INPUTS!$B$71,$C11),'KNOWIFY REVIEW'!$AD$4:$AD$400,1),"")) -> 1.8918975 | S11: =IF(MAX(N($Q11),N($R11))>1.1,"Past job ran over budget","") -> Past job ran over budget
A12: V-RI-CLN | B12: V | C12: 03 Rough-in (Labour) | D12: Clean-up | F12: LS | K12: Y | L12: =($E12*$G12+$I12)*(1+IF($K12="N",0,INPUTS!$C$23)) -> 0 | M12: =$E12*$H12+$J12 -> 0 | N12: =$M12*IF(OR($B12="V",$B12="AC"),'LABOUR RATES'!$E$26,'LABOUR RATES'!$E$11) -> 0 | O12: =$M12*IF(OR($B12="V",$B12="AC"),'LABOUR RATES'!$C$27,'LABOUR RATES'!$C$12) -> 0 | P12: =$L12+$N12+$O12 -> 0 | Q12: =IF(OR($B12="",$C12=""),"",IFERROR(SUMIFS('KNOWIFY REVIEW'!$AF$4:$AF$400,'KNOWIFY REVIEW'!$AB$4:$AB$400,$B12,'KNOWIFY REVIEW'!$AC$4:$AC$400,$C12,'KNOWIFY REVIEW'!$AD$4:$AD$400,1)/SUMIFS('KNOWIFY REVIEW'!$AE$4:$AE$400,'KNOWIFY REVIEW'!$AB$4:$AB$400,$B12,'KNOWIFY REVIEW'!$AC$4:$AC$400,$C12,'KNOWIFY REVIEW'!$AD$4:$AD$400,1),"")) -> 1.7282942 | R12: =IF(OR($B12="",$C12=""),"",IFERROR(SUMIFS('KNOWIFY REVIEW'!$AH$4:$AH$400,'KNOWIFY REVIEW'!$AB$4:$AB$400,$B12,'KNOWIFY REVIEW'!$AC$4:$AC$400,IF(OR($C12=INPUTS!$B$69,$C12=INPUTS!$B$70),INPUTS!$B$71,$C12),'KNOWIFY REVIEW'!$AD$4:$AD$400,1)/SUMIFS('KNOWIFY REVIEW'!$AG$4:$AG$400,'KNOWIFY REVIEW'!$AB$4:$AB$400,$B12,'KNOWIFY REVIEW'!$AC$4:$AC$400,IF(OR($C12=INPUTS!$B$69,$C12=INPUTS!$B$70),INPUTS!$B$71,$C12),'KNOWIFY REVIEW'!$AD$4:$AD$400,1),"")) -> 1.8918975 | S12: =IF(MAX(N($Q12),N($R12))>1.1,"Past job ran over budget","") -> Past job ran over budget
A13: V-FN-GRL | B13: V | C13: 04 Finishing (Labour) | D13: Grilles & Ventilation Terminations | F13: ea | K13: Y | L13: =($E13*$G13+$I13)*(1+IF($K13="N",0,INPUTS!$C$23)) -> 0 | M13: =$E13*$H13+$J13 -> 0 | N13: =$M13*IF(OR($B13="V",$B13="AC"),'LABOUR RATES'!$E$26,'LABOUR RATES'!$E$11) -> 0 | O13: =$M13*IF(OR($B13="V",$B13="AC"),'LABOUR RATES'!$C$27,'LABOUR RATES'!$C$12) -> 0 | P13: =$L13+$N13+$O13 -> 0 | Q13: =IF(OR($B13="",$C13=""),"",IFERROR(SUMIFS('KNOWIFY REVIEW'!$AF$4:$AF$400,'KNOWIFY REVIEW'!$AB$4:$AB$400,$B13,'KNOWIFY REVIEW'!$AC$4:$AC$400,$C13,'KNOWIFY REVIEW'!$AD$4:$AD$400,1)/SUMIFS('KNOWIFY REVIEW'!$AE$4:$AE$400,'KNOWIFY REVIEW'!$AB$4:$AB$400,$B13,'KNOWIFY REVIEW'!$AC$4:$AC$400,$C13,'KNOWIFY REVIEW'!$AD$4:$AD$400,1),"")) -> 0 | R13: =IF(OR($B13="",$C13=""),"",IFERROR(SUMIFS('KNOWIFY REVIEW'!$AH$4:$AH$400,'KNOWIFY REVIEW'!$AB$4:$AB$400,$B13,'KNOWIFY REVIEW'!$AC$4:$AC$400,IF(OR($C13=INPUTS!$B$69,$C13=INPUTS!$B$70),INPUTS!$B$71,$C13),'KNOWIFY REVIEW'!$AD$4:$AD$400,1)/SUMIFS('KNOWIFY REVIEW'!$AG$4:$AG$400,'KNOWIFY REVIEW'!$AB$4:$AB$400,$B13,'KNOWIFY REVIEW'!$AC$4:$AC$400,IF(OR($C13=INPUTS!$B$69,$C13=INPUTS!$B$70),INPUTS!$B$71,$C13),'KNOWIFY REVIEW'!$AD$4:$AD$400,1),"")) -> 1.8918975 | S13: =IF(MAX(N($Q13),N($R13))>1.1,"Past job ran over budget","") -> Past job ran over budget
A14: V-FN-AP | B14: V | C14: 04 Finishing (Labour) | D14: Install Access Panels | F14: ea | K14: Y | L14: =($E14*$G14+$I14)*(1+IF($K14="N",0,INPUTS!$C$23)) -> 0 | M14: =$E14*$H14+$J14 -> 0 | N14: =$M14*IF(OR($B14="V",$B14="AC"),'LABOUR RATES'!$E$26,'LABOUR RATES'!$E$11) -> 0 | O14: =$M14*IF(OR($B14="V",$B14="AC"),'LABOUR RATES'!$C$27,'LABOUR RATES'!$C$12) -> 0 | P14: =$L14+$N14+$O14 -> 0 | Q14: =IF(OR($B14="",$C14=""),"",IFERROR(SUMIFS('KNOWIFY REVIEW'!$AF$4:$AF$400,'KNOWIFY REVIEW'!$AB$4:$AB$400,$B14,'KNOWIFY REVIEW'!$AC$4:$AC$400,$C14,'KNOWIFY REVIEW'!$AD$4:$AD$400,1)/SUMIFS('KNOWIFY REVIEW'!$AE$4:$AE$400,'KNOWIFY REVIEW'!$AB$4:$AB$400,$B14,'KNOWIFY REVIEW'!$AC$4:$AC$400,$C14,'KNOWIFY REVIEW'!$AD$4:$AD$400,1),"")) -> 0 | R14: =IF(OR($B14="",$C14=""),"",IFERROR(SUMIFS('KNOWIFY REVIEW'!$AH$4:$AH$400,'KNOWIFY REVIEW'!$AB$4:$AB$400,$B14,'KNOWIFY REVIEW'!$AC$4:$AC$400,IF(OR($C14=INPUTS!$B$69,$C14=INPUTS!$B$70),INPUTS!$B$71,$C14),'KNOWIFY REVIEW'!$AD$4:$AD$400,1)/SUMIFS('KNOWIFY REVIEW'!$AG$4:$AG$400,'KNOWIFY REVIEW'!$AB$4:$AB$400,$B14,'KNOWIFY REVIEW'!$AC$4:$AC$400,IF(OR($C14=INPUTS!$B$69,$C14=INPUTS!$B$70),INPUTS!$B$71,$C14),'KNOWIFY REVIEW'!$AD$4:$AD$400,1),"")) -> 1.8918975 | S14: =IF(MAX(N($Q14),N($R14))>1.1,"Past job ran over budget","") -> Past job ran over budget
A15: V-FN-LBL | B15: V | C15: 04 Finishing (Labour) | D15: Duct Labelling | F15: LS | K15: Y | L15: =($E15*$G15+$I15)*(1+IF($K15="N",0,INPUTS!$C$23)) -> 0 | M15: =$E15*$H15+$J15 -> 0 | N15: =$M15*IF(OR($B15="V",$B15="AC"),'LABOUR RATES'!$E$26,'LABOUR RATES'!$E$11) -> 0 | O15: =$M15*IF(OR($B15="V",$B15="AC"),'LABOUR RATES'!$C$27,'LABOUR RATES'!$C$12) -> 0 | P15: =$L15+$N15+$O15 -> 0 | Q15: =IF(OR($B15="",$C15=""),"",IFERROR(SUMIFS('KNOWIFY REVIEW'!$AF$4:$AF$400,'KNOWIFY REVIEW'!$AB$4:$AB$400,$B15,'KNOWIFY REVIEW'!$AC$4:$AC$400,$C15,'KNOWIFY REVIEW'!$AD$4:$AD$400,1)/SUMIFS('KNOWIFY REVIEW'!$AE$4:$AE$400,'KNOWIFY REVIEW'!$AB$4:$AB$400,$B15,'KNOWIFY REVIEW'!$AC$4:$AC$400,$C15,'KNOWIFY REVIEW'!$AD$4:$AD$400,1),"")) -> 0 | R15: =IF(OR($B15="",$C15=""),"",IFERROR(SUMIFS('KNOWIFY REVIEW'!$AH$4:$AH$400,'KNOWIFY REVIEW'!$AB$4:$AB$400,$B15,'KNOWIFY REVIEW'!$AC$4:$AC$400,IF(OR($C15=INPUTS!$B$69,$C15=INPUTS!$B$70),INPUTS!$B$71,$C15),'KNOWIFY REVIEW'!$AD$4:$AD$400,1)/SUMIFS('KNOWIFY REVIEW'!$AG$4:$AG$400,'KNOWIFY REVIEW'!$AB$4:$AB$400,$B15,'KNOWIFY REVIEW'!$AC$4:$AC$400,IF(OR($C15=INPUTS!$B$69,$C15=INPUTS!$B$70),INPUTS!$B$71,$C15),'KNOWIFY REVIEW'!$AD$4:$AD$400,1),"")) -> 1.8918975 | S15: =IF(MAX(N($Q15),N($R15))>1.1,"Past job ran over budget","") -> Past job ran over budget
A16: V-EQ-FAN | B16: V | C16: 06 Fixtures & Equipment Supply | D16: Ventilation Equipment Supply (fans, ERVs) | F16: ea | K16: Y | L16: =($E16*$G16+$I16)*(1+IF($K16="N",0,INPUTS!$C$23)) -> 0 | M16: =$E16*$H16+$J16 -> 0 | N16: =$M16*IF(OR($B16="V",$B16="AC"),'LABOUR RATES'!$E$26,'LABOUR RATES'!$E$11) -> 0 | O16: =$M16*IF(OR($B16="V",$B16="AC"),'LABOUR RATES'!$C$27,'LABOUR RATES'!$C$12) -> 0 | P16: =$L16+$N16+$O16 -> 0 | Q16: =IF(OR($B16="",$C16=""),"",IFERROR(SUMIFS('KNOWIFY REVIEW'!$AF$4:$AF$400,'KNOWIFY REVIEW'!$AB$4:$AB$400,$B16,'KNOWIFY REVIEW'!$AC$4:$AC$400,$C16,'KNOWIFY REVIEW'!$AD$4:$AD$400,1)/SUMIFS('KNOWIFY REVIEW'!$AE$4:$AE$400,'KNOWIFY REVIEW'!$AB$4:$AB$400,$B16,'KNOWIFY REVIEW'!$AC$4:$AC$400,$C16,'KNOWIFY REVIEW'!$AD$4:$AD$400,1),"")) | R16: =IF(OR($B16="",$C16=""),"",IFERROR(SUMIFS('KNOWIFY REVIEW'!$AH$4:$AH$400,'KNOWIFY REVIEW'!$AB$4:$AB$400,$B16,'KNOWIFY REVIEW'!$AC$4:$AC$400,IF(OR($C16=INPUTS!$B$69,$C16=INPUTS!$B$70),INPUTS!$B$71,$C16),'KNOWIFY REVIEW'!$AD$4:$AD$400,1)/SUMIFS('KNOWIFY REVIEW'!$AG$4:$AG$400,'KNOWIFY REVIEW'!$AB$4:$AB$400,$B16,'KNOWIFY REVIEW'!$AC$4:$AC$400,IF(OR($C16=INPUTS!$B$69,$C16=INPUTS!$B$70),INPUTS!$B$71,$C16),'KNOWIFY REVIEW'!$AD$4:$AD$400,1),"")) | S16: =IF(MAX(N($Q16),N($R16))>1.1,"Past job ran over budget","")
A17: V-TS-TEST | B17: V | C17: 07 Testing, TAB & Commissioning | D17: Testing | F17: LS | K17: Y | L17: =($E17*$G17+$I17)*(1+IF($K17="N",0,INPUTS!$C$23)) -> 0 | M17: =$E17*$H17+$J17 -> 0 | N17: =$M17*IF(OR($B17="V",$B17="AC"),'LABOUR RATES'!$E$26,'LABOUR RATES'!$E$11) -> 0 | O17: =$M17*IF(OR($B17="V",$B17="AC"),'LABOUR RATES'!$C$27,'LABOUR RATES'!$C$12) -> 0 | P17: =$L17+$N17+$O17 -> 0 | Q17: =IF(OR($B17="",$C17=""),"",IFERROR(SUMIFS('KNOWIFY REVIEW'!$AF$4:$AF$400,'KNOWIFY REVIEW'!$AB$4:$AB$400,$B17,'KNOWIFY REVIEW'!$AC$4:$AC$400,$C17,'KNOWIFY REVIEW'!$AD$4:$AD$400,1)/SUMIFS('KNOWIFY REVIEW'!$AE$4:$AE$400,'KNOWIFY REVIEW'!$AB$4:$AB$400,$B17,'KNOWIFY REVIEW'!$AC$4:$AC$400,$C17,'KNOWIFY REVIEW'!$AD$4:$AD$400,1),"")) | R17: =IF(OR($B17="",$C17=""),"",IFERROR(SUMIFS('KNOWIFY REVIEW'!$AH$4:$AH$400,'KNOWIFY REVIEW'!$AB$4:$AB$400,$B17,'KNOWIFY REVIEW'!$AC$4:$AC$400,IF(OR($C17=INPUTS!$B$69,$C17=INPUTS!$B$70),INPUTS!$B$71,$C17),'KNOWIFY REVIEW'!$AD$4:$AD$400,1)/SUMIFS('KNOWIFY REVIEW'!$AG$4:$AG$400,'KNOWIFY REVIEW'!$AB$4:$AB$400,$B17,'KNOWIFY REVIEW'!$AC$4:$AC$400,IF(OR($C17=INPUTS!$B$69,$C17=INPUTS!$B$70),INPUTS!$B$71,$C17),'KNOWIFY REVIEW'!$AD$4:$AD$400,1),"")) | S17: =IF(MAX(N($Q17),N($R17))>1.1,"Past job ran over budget","")
A18: AC-RI-DUCT | B18: AC | C18: 03 Rough-in (Labour) | D18: Distribution Ductwork | F18: lb | K18: Y | L18: =($E18*$G18+$I18)*(1+IF($K18="N",0,INPUTS!$C$23)) -> 0 | M18: =$E18*$H18+$J18 -> 0 | N18: =$M18*IF(OR($B18="V",$B18="AC"),'LABOUR RATES'!$E$26,'LABOUR RATES'!$E$11) -> 0 | O18: =$M18*IF(OR($B18="V",$B18="AC"),'LABOUR RATES'!$C$27,'LABOUR RATES'!$C$12) -> 0 | P18: =$L18+$N18+$O18 -> 0 | Q18: =IF(OR($B18="",$C18=""),"",IFERROR(SUMIFS('KNOWIFY REVIEW'!$AF$4:$AF$400,'KNOWIFY REVIEW'!$AB$4:$AB$400,$B18,'KNOWIFY REVIEW'!$AC$4:$AC$400,$C18,'KNOWIFY REVIEW'!$AD$4:$AD$400,1)/SUMIFS('KNOWIFY REVIEW'!$AE$4:$AE$400,'KNOWIFY REVIEW'!$AB$4:$AB$400,$B18,'KNOWIFY REVIEW'!$AC$4:$AC$400,$C18,'KNOWIFY REVIEW'!$AD$4:$AD$400,1),"")) | R18: =IF(OR($B18="",$C18=""),"",IFERROR(SUMIFS('KNOWIFY REVIEW'!$AH$4:$AH$400,'KNOWIFY REVIEW'!$AB$4:$AB$400,$B18,'KNOWIFY REVIEW'!$AC$4:$AC$400,IF(OR($C18=INPUTS!$B$69,$C18=INPUTS!$B$70),INPUTS!$B$71,$C18),'KNOWIFY REVIEW'!$AD$4:$AD$400,1)/SUMIFS('KNOWIFY REVIEW'!$AG$4:$AG$400,'KNOWIFY REVIEW'!$AB$4:$AB$400,$B18,'KNOWIFY REVIEW'!$AC$4:$AC$400,IF(OR($C18=INPUTS!$B$69,$C18=INPUTS!$B$70),INPUTS!$B$71,$C18),'KNOWIFY REVIEW'!$AD$4:$AD$400,1),"")) | S18: =IF(MAX(N($Q18),N($R18))>1.1,"Past job ran over budget","")
... A29: AC-TS-TEST | B29: AC | C29: 07 Testing, TAB & Commissioning | D29: Testing | F29: LS | K29: Y | L29: =($E29*$G29+$I29)*(1+IF($K29="N",0,INPUTS!$C$23)) -> 0 | M29: =$E29*$H29+$J29 -> 0 | N29: =$M29*IF(OR($B29="V",$B29="AC"),'LABOUR RATES'!$E$26,'LABOUR RATES'!$E$11) -> 0 | O29: =$M29*IF(OR($B29="V",$B29="AC"),'LABOUR RATES'!$C$27,'LABOUR RATES'!$C$12) -> 0 | P29: =$L29+$N29+$O29 -> 0 | Q29: =IF(OR($B29="",$C29=""),"",IFERROR(SUMIFS('KNOWIFY REVIEW'!$AF$4:$AF$400,'KNOWIFY REVIEW'!$AB$4:$AB$400,$B29,'KNOWIFY REVIEW'!$AC$4:$AC$400,$C29,'KNOWIFY REVIEW'!$AD$4:$AD$400,1)/SUMIFS('KNOWIFY REVIEW'!$AE$4:$AE$400,'KNOWIFY REVIEW'!$AB$4:$AB$400,$B29,'KNOWIFY REVIEW'!$AC$4:$AC$400,$C29,'KNOWIFY REVIEW'!$AD$4:$AD$400,1),"")) | R29: =IF(OR($B29="",$C29=""),"",IFERROR(SUMIFS('KNOWIFY REVIEW'!$AH$4:$AH$400,'KNOWIFY REVIEW'!$AB$4:$AB$400,$B29,'KNOWIFY REVIEW'!$AC$4:$AC$400,IF(OR($C29=INPUTS!$B$69,$C29=INPUTS!$B$70),INPUTS!$B$71,$C29),'KNOWIFY REVIEW'!$AD$4:$AD$400,1)/SUMIFS('KNOWIFY REVIEW'!$AG$4:$AG$400,'KNOWIFY REVIEW'!$AB$4:$AB$400,$B29,'KNOWIFY REVIEW'!$AC$4:$AC$400,IF(OR($C29=INPUTS!$B$69,$C29=INPUTS!$B$70),INPUTS!$B$71,$C29),'KNOWIFY REVIEW'!$AD$4:$AD$400,1),"")) | S29: =IF(MAX(N($Q29),N($R29))>1.1,"Past job ran over budget","")
K30: Y | L30: =($E30*$G30+$I30)*(1+IF($K30="N",0,INPUTS!$C$23)) -> 0 | M30: =$E30*$H30+$J30 -> 0 | N30: =$M30*IF(OR($B30="V",$B30="AC"),'LABOUR RATES'!$E$26,'LABOUR RATES'!$E$11) -> 0 | O30: =$M30*IF(OR($B30="V",$B30="AC"),'LABOUR RATES'!$C$27,'LABOUR RATES'!$C$12) -> 0 | P30: =$L30+$N30+$O30 -> 0 | Q30: =IF(OR($B30="",$C30=""),"",IFERROR(SUMIFS('KNOWIFY REVIEW'!$AF$4:$AF$400,'KNOWIFY REVIEW'!$AB$4:$AB$400,$B30,'KNOWIFY REVIEW'!$AC$4:$AC$400,$C30,'KNOWIFY REVIEW'!$AD$4:$AD$400,1)/SUMIFS('KNOWIFY REVIEW'!$AE$4:$AE$400,'KNOWIFY REVIEW'!$AB$4:$AB$400,$B30,'KNOWIFY REVIEW'!$AC$4:$AC$400,$C30,'KNOWIFY REVIEW'!$AD$4:$AD$400,1),"")) | R30: =IF(OR($B30="",$C30=""),"",IFERROR(SUMIFS('KNOWIFY REVIEW'!$AH$4:$AH$400,'KNOWIFY REVIEW'!$AB$4:$AB$400,$B30,'KNOWIFY REVIEW'!$AC$4:$AC$400,IF(OR($C30=INPUTS!$B$69,$C30=INPUTS!$B$70),INPUTS!$B$71,$C30),'KNOWIFY REVIEW'!$AD$4:$AD$400,1)/SUMIFS('KNOWIFY REVIEW'!$AG$4:$AG$400,'KNOWIFY REVIEW'!$AB$4:$AB$400,$B30,'KNOWIFY REVIEW'!$AC$4:$AC$400,IF(OR($C30=INPUTS!$B$69,$C30=INPUTS!$B$70),INPUTS!$B$71,$C30),'KNOWIFY REVIEW'!$AD$4:$AD$400,1),"")) | S30: =IF(MAX(N($Q30),N($R30))>1.1,"Past job ran over budget","")
K31: Y | L31: =($E31*$G31+$I31)*(1+IF($K31="N",0,INPUTS!$C$23)) -> 0 | M31: =$E31*$H31+$J31 -> 0 | N31: =$M31*IF(OR($B31="V",$B31="AC"),'LABOUR RATES'!$E$26,'LABOUR RATES'!$E$11) -> 0 | O31: =$M31*IF(OR($B31="V",$B31="AC"),'LABOUR RATES'!$C$27,'LABOUR RATES'!$C$12) -> 0 | P31: =$L31+$N31+$O31 -> 0 | Q31: =IF(OR($B31="",$C31=""),"",IFERROR(SUMIFS('KNOWIFY REVIEW'!$AF$4:$AF$400,'KNOWIFY REVIEW'!$AB$4:$AB$400,$B31,'KNOWIFY REVIEW'!$AC$4:$AC$400,$C31,'KNOWIFY REVIEW'!$AD$4:$AD$400,1)/SUMIFS('KNOWIFY REVIEW'!$AE$4:$AE$400,'KNOWIFY REVIEW'!$AB$4:$AB$400,$B31,'KNOWIFY REVIEW'!$AC$4:$AC$400,$C31,'KNOWIFY REVIEW'!$AD$4:$AD$400,1),"")) | R31: =IF(OR($B31="",$C31=""),"",IFERROR(SUMIFS('KNOWIFY REVIEW'!$AH$4:$AH$400,'KNOWIFY REVIEW'!$AB$4:$AB$400,$B31,'KNOWIFY REVIEW'!$AC$4:$AC$400,IF(OR($C31=INPUTS!$B$69,$C31=INPUTS!$B$70),INPUTS!$B$71,$C31),'KNOWIFY REVIEW'!$AD$4:$AD$400,1)/SUMIFS('KNOWIFY REVIEW'!$AG$4:$AG$400,'KNOWIFY REVIEW'!$AB$4:$AB$400,$B31,'KNOWIFY REVIEW'!$AC$4:$AC$400,IF(OR($C31=INPUTS!$B$69,$C31=INPUTS!$B$70),INPUTS!$B$71,$C31),'KNOWIFY REVIEW'!$AD$4:$AD$400,1),"")) | S31: =IF(MAX(N($Q31),N($R31))>1.1,"Past job ran over budget","")
K32: Y | L32: =($E32*$G32+$I32)*(1+IF($K32="N",0,INPUTS!$C$23)) -> 0 | M32: =$E32*$H32+$J32 -> 0 | N32: =$M32*IF(OR($B32="V",$B32="AC"),'LABOUR RATES'!$E$26,'LABOUR RATES'!$E$11) -> 0 | O32: =$M32*IF(OR($B32="V",$B32="AC"),'LABOUR RATES'!$C$27,'LABOUR RATES'!$C$12) -> 0 | P32: =$L32+$N32+$O32 -> 0 | Q32: =IF(OR($B32="",$C32=""),"",IFERROR(SUMIFS('KNOWIFY REVIEW'!$AF$4:$AF$400,'KNOWIFY REVIEW'!$AB$4:$AB$400,$B32,'KNOWIFY REVIEW'!$AC$4:$AC$400,$C32,'KNOWIFY REVIEW'!$AD$4:$AD$400,1)/SUMIFS('KNOWIFY REVIEW'!$AE$4:$AE$400,'KNOWIFY REVIEW'!$AB$4:$AB$400,$B32,'KNOWIFY REVIEW'!$AC$4:$AC$400,$C32,'KNOWIFY REVIEW'!$AD$4:$AD$400,1),"")) | R32: =IF(OR($B32="",$C32=""),"",IFERROR(SUMIFS('KNOWIFY REVIEW'!$AH$4:$AH$400,'KNOWIFY REVIEW'!$AB$4:$AB$400,$B32,'KNOWIFY REVIEW'!$AC$4:$AC$400,IF(OR($C32=INPUTS!$B$69,$C32=INPUTS!$B$70),INPUTS!$B$71,$C32),'KNOWIFY REVIEW'!$AD$4:$AD$400,1)/SUMIFS('KNOWIFY REVIEW'!$AG$4:$AG$400,'KNOWIFY REVIEW'!$AB$4:$AB$400,$B32,'KNOWIFY REVIEW'!$AC$4:$AC$400,IF(OR($C32=INPUTS!$B$69,$C32=INPUTS!$B$70),INPUTS!$B$71,$C32),'KNOWIFY REVIEW'!$AD$4:$AD$400,1),"")) | S32: =IF(MAX(N($Q32),N($R32))>1.1,"Past job ran over budget","")
K33: Y | L33: =($E33*$G33+$I33)*(1+IF($K33="N",0,INPUTS!$C$23)) -> 0 | M33: =$E33*$H33+$J33 -> 0 | N33: =$M33*IF(OR($B33="V",$B33="AC"),'LABOUR RATES'!$E$26,'LABOUR RATES'!$E$11) -> 0 | O33: =$M33*IF(OR($B33="V",$B33="AC"),'LABOUR RATES'!$C$27,'LABOUR RATES'!$C$12) -> 0 | P33: =$L33+$N33+$O33 -> 0 | Q33: =IF(OR($B33="",$C33=""),"",IFERROR(SUMIFS('KNOWIFY REVIEW'!$AF$4:$AF$400,'KNOWIFY REVIEW'!$AB$4:$AB$400,$B33,'KNOWIFY REVIEW'!$AC$4:$AC$400,$C33,'KNOWIFY REVIEW'!$AD$4:$AD$400,1)/SUMIFS('KNOWIFY REVIEW'!$AE$4:$AE$400,'KNOWIFY REVIEW'!$AB$4:$AB$400,$B33,'KNOWIFY REVIEW'!$AC$4:$AC$400,$C33,'KNOWIFY REVIEW'!$AD$4:$AD$400,1),"")) | R33: =IF(OR($B33="",$C33=""),"",IFERROR(SUMIFS('KNOWIFY REVIEW'!$AH$4:$AH$400,'KNOWIFY REVIEW'!$AB$4:$AB$400,$B33,'KNOWIFY REVIEW'!$AC$4:$AC$400,IF(OR($C33=INPUTS!$B$69,$C33=INPUTS!$B$70),INPUTS!$B$71,$C33),'KNOWIFY REVIEW'!$AD$4:$AD$400,1)/SUMIFS('KNOWIFY REVIEW'!$AG$4:$AG$400,'KNOWIFY REVIEW'!$AB$4:$AB$400,$B33,'KNOWIFY REVIEW'!$AC$4:$AC$400,IF(OR($C33=INPUTS!$B$69,$C33=INPUTS!$B$70),INPUTS!$B$71,$C33),'KNOWIFY REVIEW'!$AD$4:$AD$400,1),"")) | S33: =IF(MAX(N($Q33),N($R33))>1.1,"Past job ran over budget","")
K34: Y | L34: =($E34*$G34+$I34)*(1+IF($K34="N",0,INPUTS!$C$23)) -> 0 | M34: =$E34*$H34+$J34 -> 0 | N34: =$M34*IF(OR($B34="V",$B34="AC"),'LABOUR RATES'!$E$26,'LABOUR RATES'!$E$11) -> 0 | O34: =$M34*IF(OR($B34="V",$B34="AC"),'LABOUR RATES'!$C$27,'LABOUR RATES'!$C$12) -> 0 | P34: =$L34+$N34+$O34 -> 0 | Q34: =IF(OR($B34="",$C34=""),"",IFERROR(SUMIFS('KNOWIFY REVIEW'!$AF$4:$AF$400,'KNOWIFY REVIEW'!$AB$4:$AB$400,$B34,'KNOWIFY REVIEW'!$AC$4:$AC$400,$C34,'KNOWIFY REVIEW'!$AD$4:$AD$400,1)/SUMIFS('KNOWIFY REVIEW'!$AE$4:$AE$400,'KNOWIFY REVIEW'!$AB$4:$AB$400,$B34,'KNOWIFY REVIEW'!$AC$4:$AC$400,$C34,'KNOWIFY REVIEW'!$AD$4:$AD$400,1),"")) | R34: =IF(OR($B34="",$C34=""),"",IFERROR(SUMIFS('KNOWIFY REVIEW'!$AH$4:$AH$400,'KNOWIFY REVIEW'!$AB$4:$AB$400,$B34,'KNOWIFY REVIEW'!$AC$4:$AC$400,IF(OR($C34=INPUTS!$B$69,$C34=INPUTS!$B$70),INPUTS!$B$71,$C34),'KNOWIFY REVIEW'!$AD$4:$AD$400,1)/SUMIFS('KNOWIFY REVIEW'!$AG$4:$AG$400,'KNOWIFY REVIEW'!$AB$4:$AB$400,$B34,'KNOWIFY REVIEW'!$AC$4:$AC$400,IF(OR($C34=INPUTS!$B$69,$C34=INPUTS!$B$70),INPUTS!$B$71,$C34),'KNOWIFY REVIEW'!$AD$4:$AD$400,1),"")) | S34: =IF(MAX(N($Q34),N($R34))>1.1,"Past job ran over budget","")
K35: Y | L35: =($E35*$G35+$I35)*(1+IF($K35="N",0,INPUTS!$C$23)) -> 0 | M35: =$E35*$H35+$J35 -> 0 | N35: =$M35*IF(OR($B35="V",$B35="AC"),'LABOUR RATES'!$E$26,'LABOUR RATES'!$E$11) -> 0 | O35: =$M35*IF(OR($B35="V",$B35="AC"),'LABOUR RATES'!$C$27,'LABOUR RATES'!$C$12) -> 0 | P35: =$L35+$N35+$O35 -> 0 | Q35: =IF(OR($B35="",$C35=""),"",IFERROR(SUMIFS('KNOWIFY REVIEW'!$AF$4:$AF$400,'KNOWIFY REVIEW'!$AB$4:$AB$400,$B35,'KNOWIFY REVIEW'!$AC$4:$AC$400,$C35,'KNOWIFY REVIEW'!$AD$4:$AD$400,1)/SUMIFS('KNOWIFY REVIEW'!$AE$4:$AE$400,'KNOWIFY REVIEW'!$AB$4:$AB$400,$B35,'KNOWIFY REVIEW'!$AC$4:$AC$400,$C35,'KNOWIFY REVIEW'!$AD$4:$AD$400,1),"")) | R35: =IF(OR($B35="",$C35=""),"",IFERROR(SUMIFS('KNOWIFY REVIEW'!$AH$4:$AH$400,'KNOWIFY REVIEW'!$AB$4:$AB$400,$B35,'KNOWIFY REVIEW'!$AC$4:$AC$400,IF(OR($C35=INPUTS!$B$69,$C35=INPUTS!$B$70),INPUTS!$B$71,$C35),'KNOWIFY REVIEW'!$AD$4:$AD$400,1)/SUMIFS('KNOWIFY REVIEW'!$AG$4:$AG$400,'KNOWIFY REVIEW'!$AB$4:$AB$400,$B35,'KNOWIFY REVIEW'!$AC$4:$AC$400,IF(OR($C35=INPUTS!$B$69,$C35=INPUTS!$B$70),INPUTS!$B$71,$C35),'KNOWIFY REVIEW'!$AD$4:$AD$400,1),"")) | S35: =IF(MAX(N($Q35),N($R35))>1.1,"Past job ran over budget","")
K36: Y | L36: =($E36*$G36+$I36)*(1+IF($K36="N",0,INPUTS!$C$23)) -> 0 | M36: =$E36*$H36+$J36 -> 0 | N36: =$M36*IF(OR($B36="V",$B36="AC"),'LABOUR RATES'!$E$26,'LABOUR RATES'!$E$11) -> 0 | O36: =$M36*IF(OR($B36="V",$B36="AC"),'LABOUR RATES'!$C$27,'LABOUR RATES'!$C$12) -> 0 | P36: =$L36+$N36+$O36 -> 0 | Q36: =IF(OR($B36="",$C36=""),"",IFERROR(SUMIFS('KNOWIFY REVIEW'!$AF$4:$AF$400,'KNOWIFY REVIEW'!$AB$4:$AB$400,$B36,'KNOWIFY REVIEW'!$AC$4:$AC$400,$C36,'KNOWIFY REVIEW'!$AD$4:$AD$400,1)/SUMIFS('KNOWIFY REVIEW'!$AE$4:$AE$400,'KNOWIFY REVIEW'!$AB$4:$AB$400,$B36,'KNOWIFY REVIEW'!$AC$4:$AC$400,$C36,'KNOWIFY REVIEW'!$AD$4:$AD$400,1),"")) | R36: =IF(OR($B36="",$C36=""),"",IFERROR(SUMIFS('KNOWIFY REVIEW'!$AH$4:$AH$400,'KNOWIFY REVIEW'!$AB$4:$AB$400,$B36,'KNOWIFY REVIEW'!$AC$4:$AC$400,IF(OR($C36=INPUTS!$B$69,$C36=INPUTS!$B$70),INPUTS!$B$71,$C36),'KNOWIFY REVIEW'!$AD$4:$AD$400,1)/SUMIFS('KNOWIFY REVIEW'!$AG$4:$AG$400,'KNOWIFY REVIEW'!$AB$4:$AB$400,$B36,'KNOWIFY REVIEW'!$AC$4:$AC$400,IF(OR($C36=INPUTS!$B$69,$C36=INPUTS!$B$70),INPUTS!$B$71,$C36),'KNOWIFY REVIEW'!$AD$4:$AD$400,1),"")) | S36: =IF(MAX(N($Q36),N($R36))>1.1,"Past job ran over budget","")
K37: Y | L37: =($E37*$G37+$I37)*(1+IF($K37="N",0,INPUTS!$C$23)) -> 0 | M37: =$E37*$H37+$J37 -> 0 | N37: =$M37*IF(OR($B37="V",$B37="AC"),'LABOUR RATES'!$E$26,'LABOUR RATES'!$E$11) -> 0 | O37: =$M37*IF(OR($B37="V",$B37="AC"),'LABOUR RATES'!$C$27,'LABOUR RATES'!$C$12) -> 0 | P37: =$L37+$N37+$O37 -> 0 | Q37: =IF(OR($B37="",$C37=""),"",IFERROR(SUMIFS('KNOWIFY REVIEW'!$AF$4:$AF$400,'KNOWIFY REVIEW'!$AB$4:$AB$400,$B37,'KNOWIFY REVIEW'!$AC$4:$AC$400,$C37,'KNOWIFY REVIEW'!$AD$4:$AD$400,1)/SUMIFS('KNOWIFY REVIEW'!$AE$4:$AE$400,'KNOWIFY REVIEW'!$AB$4:$AB$400,$B37,'KNOWIFY REVIEW'!$AC$4:$AC$400,$C37,'KNOWIFY REVIEW'!$AD$4:$AD$400,1),"")) | R37: =IF(OR($B37="",$C37=""),"",IFERROR(SUMIFS('KNOWIFY REVIEW'!$AH$4:$AH$400,'KNOWIFY REVIEW'!$AB$4:$AB$400,$B37,'KNOWIFY REVIEW'!$AC$4:$AC$400,IF(OR($C37=INPUTS!$B$69,$C37=INPUTS!$B$70),INPUTS!$B$71,$C37),'KNOWIFY REVIEW'!$AD$4:$AD$400,1)/SUMIFS('KNOWIFY REVIEW'!$AG$4:$AG$400,'KNOWIFY REVIEW'!$AB$4:$AB$400,$B37,'KNOWIFY REVIEW'!$AC$4:$AC$400,IF(OR($C37=INPUTS!$B$69,$C37=INPUTS!$B$70),INPUTS!$B$71,$C37),'KNOWIFY REVIEW'!$AD$4:$AD$400,1),"")) | S37: =IF(MAX(N($Q37),N($R37))>1.1,"Past job ran over budget","")
K38: Y | L38: =($E38*$G38+$I38)*(1+IF($K38="N",0,INPUTS!$C$23)) -> 0 | M38: =$E38*$H38+$J38 -> 0 | N38: =$M38*IF(OR($B38="V",$B38="AC"),'LABOUR RATES'!$E$26,'LABOUR RATES'!$E$11) -> 0 | O38: =$M38*IF(OR($B38="V",$B38="AC"),'LABOUR RATES'!$C$27,'LABOUR RATES'!$C$12) -> 0 | P38: =$L38+$N38+$O38 -> 0 | Q38: =IF(OR($B38="",$C38=""),"",IFERROR(SUMIFS('KNOWIFY REVIEW'!$AF$4:$AF$400,'KNOWIFY REVIEW'!$AB$4:$AB$400,$B38,'KNOWIFY REVIEW'!$AC$4:$AC$400,$C38,'KNOWIFY REVIEW'!$AD$4:$AD$400,1)/SUMIFS('KNOWIFY REVIEW'!$AE$4:$AE$400,'KNOWIFY REVIEW'!$AB$4:$AB$400,$B38,'KNOWIFY REVIEW'!$AC$4:$AC$400,$C38,'KNOWIFY REVIEW'!$AD$4:$AD$400,1),"")) | R38: =IF(OR($B38="",$C38=""),"",IFERROR(SUMIFS('KNOWIFY REVIEW'!$AH$4:$AH$400,'KNOWIFY REVIEW'!$AB$4:$AB$400,$B38,'KNOWIFY REVIEW'!$AC$4:$AC$400,IF(OR($C38=INPUTS!$B$69,$C38=INPUTS!$B$70),INPUTS!$B$71,$C38),'KNOWIFY REVIEW'!$AD$4:$AD$400,1)/SUMIFS('KNOWIFY REVIEW'!$AG$4:$AG$400,'KNOWIFY REVIEW'!$AB$4:$AB$400,$B38,'KNOWIFY REVIEW'!$AC$4:$AC$400,IF(OR($C38=INPUTS!$B$69,$C38=INPUTS!$B$70),INPUTS!$B$71,$C38),'KNOWIFY REVIEW'!$AD$4:$AD$400,1),"")) | S38: =IF(MAX(N($Q38),N($R38))>1.1,"Past job ran over budget","")
K39: Y | L39: =($E39*$G39+$I39)*(1+IF($K39="N",0,INPUTS!$C$23)) -> 0 | M39: =$E39*$H39+$J39 -> 0 | N39: =$M39*IF(OR($B39="V",$B39="AC"),'LABOUR RATES'!$E$26,'LABOUR RATES'!$E$11) -> 0 | O39: =$M39*IF(OR($B39="V",$B39="AC"),'LABOUR RATES'!$C$27,'LABOUR RATES'!$C$12) -> 0 | P39: =$L39+$N39+$O39 -> 0 | Q39: =IF(OR($B39="",$C39=""),"",IFERROR(SUMIFS('KNOWIFY REVIEW'!$AF$4:$AF$400,'KNOWIFY REVIEW'!$AB$4:$AB$400,$B39,'KNOWIFY REVIEW'!$AC$4:$AC$400,$C39,'KNOWIFY REVIEW'!$AD$4:$AD$400,1)/SUMIFS('KNOWIFY REVIEW'!$AE$4:$AE$400,'KNOWIFY REVIEW'!$AB$4:$AB$400,$B39,'KNOWIFY REVIEW'!$AC$4:$AC$400,$C39,'KNOWIFY REVIEW'!$AD$4:$AD$400,1),"")) | R39: =IF(OR($B39="",$C39=""),"",IFERROR(SUMIFS('KNOWIFY REVIEW'!$AH$4:$AH$400,'KNOWIFY REVIEW'!$AB$4:$AB$400,$B39,'KNOWIFY REVIEW'!$AC$4:$AC$400,IF(OR($C39=INPUTS!$B$69,$C39=INPUTS!$B$70),INPUTS!$B$71,$C39),'KNOWIFY REVIEW'!$AD$4:$AD$400,1)/SUMIFS('KNOWIFY REVIEW'!$AG$4:$AG$400,'KNOWIFY REVIEW'!$AB$4:$AB$400,$B39,'KNOWIFY REVIEW'!$AC$4:$AC$400,IF(OR($C39=INPUTS!$B$69,$C39=INPUTS!$B$70),INPUTS!$B$71,$C39),'KNOWIFY REVIEW'!$AD$4:$AD$400,1),"")) | S39: =IF(MAX(N($Q39),N($R39))>1.1,"Past job ran over budget","")
K40: Y | L40: =($E40*$G40+$I40)*(1+IF($K40="N",0,INPUTS!$C$23)) -> 0 | M40: =$E40*$H40+$J40 -> 0 | N40: =$M40*IF(OR($B40="V",$B40="AC"),'LABOUR RATES'!$E$26,'LABOUR RATES'!$E$11) -> 0 | O40: =$M40*IF(OR($B40="V",$B40="AC"),'LABOUR RATES'!$C$27,'LABOUR RATES'!$C$12) -> 0 | P40: =$L40+$N40+$O40 -> 0 | Q40: =IF(OR($B40="",$C40=""),"",IFERROR(SUMIFS('KNOWIFY REVIEW'!$AF$4:$AF$400,'KNOWIFY REVIEW'!$AB$4:$AB$400,$B40,'KNOWIFY REVIEW'!$AC$4:$AC$400,$C40,'KNOWIFY REVIEW'!$AD$4:$AD$400,1)/SUMIFS('KNOWIFY REVIEW'!$AE$4:$AE$400,'KNOWIFY REVIEW'!$AB$4:$AB$400,$B40,'KNOWIFY REVIEW'!$AC$4:$AC$400,$C40,'KNOWIFY REVIEW'!$AD$4:$AD$400,1),"")) | R40: =IF(OR($B40="",$C40=""),"",IFERROR(SUMIFS('KNOWIFY REVIEW'!$AH$4:$AH$400,'KNOWIFY REVIEW'!$AB$4:$AB$400,$B40,'KNOWIFY REVIEW'!$AC$4:$AC$400,IF(OR($C40=INPUTS!$B$69,$C40=INPUTS!$B$70),INPUTS!$B$71,$C40),'KNOWIFY REVIEW'!$AD$4:$AD$400,1)/SUMIFS('KNOWIFY REVIEW'!$AG$4:$AG$400,'KNOWIFY REVIEW'!$AB$4:$AB$400,$B40,'KNOWIFY REVIEW'!$AC$4:$AC$400,IF(OR($C40=INPUTS!$B$69,$C40=INPUTS!$B$70),INPUTS!$B$71,$C40),'KNOWIFY REVIEW'!$AD$4:$AD$400,1),"")) | S40: =IF(MAX(N($Q40),N($R40))>1.1,"Past job ran over budget","")
K41: Y | L41: =($E41*$G41+$I41)*(1+IF($K41="N",0,INPUTS!$C$23)) -> 0 | M41: =$E41*$H41+$J41 -> 0 | N41: =$M41*IF(OR($B41="V",$B41="AC"),'LABOUR RATES'!$E$26,'LABOUR RATES'!$E$11) -> 0 | O41: =$M41*IF(OR($B41="V",$B41="AC"),'LABOUR RATES'!$C$27,'LABOUR RATES'!$C$12) -> 0 | P41: =$L41+$N41+$O41 -> 0 | Q41: =IF(OR($B41="",$C41=""),"",IFERROR(SUMIFS('KNOWIFY REVIEW'!$AF$4:$AF$400,'KNOWIFY REVIEW'!$AB$4:$AB$400,$B41,'KNOWIFY REVIEW'!$AC$4:$AC$400,$C41,'KNOWIFY REVIEW'!$AD$4:$AD$400,1)/SUMIFS('KNOWIFY REVIEW'!$AE$4:$AE$400,'KNOWIFY REVIEW'!$AB$4:$AB$400,$B41,'KNOWIFY REVIEW'!$AC$4:$AC$400,$C41,'KNOWIFY REVIEW'!$AD$4:$AD$400,1),"")) | R41: =IF(OR($B41="",$C41=""),"",IFERROR(SUMIFS('KNOWIFY REVIEW'!$AH$4:$AH$400,'KNOWIFY REVIEW'!$AB$4:$AB$400,$B41,'KNOWIFY REVIEW'!$AC$4:$AC$400,IF(OR($C41=INPUTS!$B$69,$C41=INPUTS!$B$70),INPUTS!$B$71,$C41),'KNOWIFY REVIEW'!$AD$4:$AD$400,1)/SUMIFS('KNOWIFY REVIEW'!$AG$4:$AG$400,'KNOWIFY REVIEW'!$AB$4:$AB$400,$B41,'KNOWIFY REVIEW'!$AC$4:$AC$400,IF(OR($C41=INPUTS!$B$69,$C41=INPUTS!$B$70),INPUTS!$B$71,$C41),'KNOWIFY REVIEW'!$AD$4:$AD$400,1),"")) | S41: =IF(MAX(N($Q41),N($R41))>1.1,"Past job ran over budget","")
... K156: Y | L156: =($E156*$G156+$I156)*(1+IF($K156="N",0,INPUTS!$C$23)) -> 0 | M156: =$E156*$H156+$J156 -> 0 | N156: =$M156*IF(OR($B156="V",$B156="AC"),'LABOUR RATES'!$E$26,'LABOUR RATES'!$E$11) -> 0 | O156: =$M156*IF(OR($B156="V",$B156="AC"),'LABOUR RATES'!$C$27,'LABOUR RATES'!$C$12) -> 0 | P156: =$L156+$N156+$O156 -> 0 | Q156: =IF(OR($B156="",$C156=""),"",IFERROR(SUMIFS('KNOWIFY REVIEW'!$AF$4:$AF$400,'KNOWIFY REVIEW'!$AB$4:$AB$400,$B156,'KNOWIFY REVIEW'!$AC$4:$AC$400,$C156,'KNOWIFY REVIEW'!$AD$4:$AD$400,1)/SUMIFS('KNOWIFY REVIEW'!$AE$4:$AE$400,'KNOWIFY REVIEW'!$AB$4:$AB$400,$B156,'KNOWIFY REVIEW'!$AC$4:$AC$400,$C156,'KNOWIFY REVIEW'!$AD$4:$AD$400,1),"")) | R156: =IF(OR($B156="",$C156=""),"",IFERROR(SUMIFS('KNOWIFY REVIEW'!$AH$4:$AH$400,'KNOWIFY REVIEW'!$AB$4:$AB$400,$B156,'KNOWIFY REVIEW'!$AC$4:$AC$400,IF(OR($C156=INPUTS!$B$69,$C156=INPUTS!$B$70),INPUTS!$B$71,$C156),'KNOWIFY REVIEW'!$AD$4:$AD$400,1)/SUMIFS('KNOWIFY REVIEW'!$AG$4:$AG$400,'KNOWIFY REVIEW'!$AB$4:$AB$400,$B156,'KNOWIFY REVIEW'!$AC$4:$AC$400,IF(OR($C156=INPUTS!$B$69,$C156=INPUTS!$B$70),INPUTS!$B$71,$C156),'KNOWIFY REVIEW'!$AD$4:$AD$400,1),"")) | S156: =IF(MAX(N($Q156),N($R156))>1.1,"Past job ran over budget","")

Sheet SUBS & GC
A1: SUBTRADES & GENERAL CONDITIONS
A2: Allocation %: enter a split per division, or leave all four blank to auto-split by direct cost.
H3: Direct cost by division | I3: =SUMIFS('PLUMBING EST'!$P$7:$P$156,'PLUMBING EST'!$B$7:$B$156,"P")+SUMIFS('HVAC EST'!$P$7:$P$156,'HVAC EST'!$B$7:$B$156,"P") -> 233323.62 | J3: =SUMIFS('PLUMBING EST'!$P$7:$P$156,'PLUMBING EST'!$B$7:$B$156,"H")+SUMIFS('HVAC EST'!$P$7:$P$156,'HVAC EST'!$B$7:$B$156,"H") -> 0 | K3: =SUMIFS('PLUMBING EST'!$P$7:$P$156,'PLUMBING EST'!$B$7:$B$156,"V")+SUMIFS('HVAC EST'!$P$7:$P$156,'HVAC EST'!$B$7:$B$156,"V") -> 0 | L3: =SUMIFS('PLUMBING EST'!$P$7:$P$156,'PLUMBING EST'!$B$7:$B$156,"AC")+SUMIFS('HVAC EST'!$P$7:$P$156,'HVAC EST'!$B$7:$B$156,"AC") -> 0
H4: Auto split share | I4: =IFERROR(I3/SUM($I$3:$L$3),0) -> 1 | J4: =IFERROR(J3/SUM($I$3:$L$3),0) -> 0 | K4: =IFERROR(K3/SUM($I$3:$L$3),0) -> 0 | L4: =IFERROR(L3/SUM($I$3:$L$3),0) -> 0
A5: SUBTRADES (each becomes its own SOV line, as in Knowify)
A6: # | B6: Item | C6: Company / Basis | D6: Phase | E6: Qty | F6: Unit | G6: Rate $ | H6: Amount $ | I6: % P | J6: % H | K6: % V | L6: % AC | M6: Plumbing $ | N6: Hydronic $ | O6: Ventilation $ | P6: A/C $ | Q6: Check
A7: 1 | B7: Insulation and Heat Trace | C7: Adler | D7: 03 Rough-in (Labour) | E7: 1 | F7: LS | H7: =E7*G7 -> 0 | I7: 1 | M7: =$H7*IF(SUM($I7:$L7)=0,I$4,I7) -> 0 | N7: =$H7*IF(SUM($I7:$L7)=0,J$4,J7) -> 0 | O7: =$H7*IF(SUM($I7:$L7)=0,K$4,K7) -> 0 | P7: =$H7*IF(SUM($I7:$L7)=0,L$4,L7) -> 0 | Q7: =IF($H7=0,"",IF(ABS(SUM(M7:P7)-$H7)<0.01,"OK","CHECK"))
A8: 2 | B8: Duct Insulation | D8: 03 Rough-in (Labour) | E8: 1 | F8: LS | H8: =E8*G8 -> 0 | K8: 0.5 | L8: 0.5 | M8: =$H8*IF(SUM($I8:$L8)=0,I$4,I8) -> 0 | N8: =$H8*IF(SUM($I8:$L8)=0,J$4,J8) -> 0 | O8: =$H8*IF(SUM($I8:$L8)=0,K$4,K8) -> 0 | P8: =$H8*IF(SUM($I8:$L8)=0,L$4,L8) -> 0 | Q8: =IF($H8=0,"",IF(ABS(SUM(M8:P8)-$H8)<0.01,"OK","CHECK"))
A9: 3 | B9: Fire Sprinklers | D9: 03 Rough-in (Labour) | E9: 1 | F9: LS | H9: =E9*G9 -> 0 | I9: 1 | M9: =$H9*IF(SUM($I9:$L9)=0,I$4,I9) -> 0 | N9: =$H9*IF(SUM($I9:$L9)=0,J$4,J9) -> 0 | O9: =$H9*IF(SUM($I9:$L9)=0,K$4,K9) -> 0 | P9: =$H9*IF(SUM($I9:$L9)=0,L$4,L9) -> 0 | Q9: =IF($H9=0,"",IF(ABS(SUM(M9:P9)-$H9)<0.01,"OK","CHECK"))
A10: 4 | B10: P&H Controls | D10: 06 Fixtures & Equipment Supply | E10: 1 | F10: LS | H10: =E10*G10 -> 0 | I10: 0.5 | J10: 0.5 | M10: =$H10*IF(SUM($I10:$L10)=0,I$4,I10) -> 0 | N10: =$H10*IF(SUM($I10:$L10)=0,J$4,J10) -> 0 | O10: =$H10*IF(SUM($I10:$L10)=0,K$4,K10) -> 0 | P10: =$H10*IF(SUM($I10:$L10)=0,L$4,L10) -> 0 | Q10: =IF($H10=0,"",IF(ABS(SUM(M10:P10)-$H10)<0.01,"OK","CHECK"))
A11: 5 | B11: HVAC Controls | C11: Olympic Controls | D11: 06 Fixtures & Equipment Supply | E11: 1 | F11: LS | H11: =E11*G11 -> 0 | K11: 0.5 | L11: 0.5 | M11: =$H11*IF(SUM($I11:$L11)=0,I$4,I11) -> 0 | N11: =$H11*IF(SUM($I11:$L11)=0,J$4,J11) -> 0 | O11: =$H11*IF(SUM($I11:$L11)=0,K$4,K11) -> 0 | P11: =$H11*IF(SUM($I11:$L11)=0,L$4,L11) -> 0 | Q11: =IF($H11=0,"",IF(ABS(SUM(M11:P11)-$H11)<0.01,"OK","CHECK"))
A12: 6 | B12: TAB and Commissioning | C12: Western Mechanical | D12: 07 Testing, TAB & Commissioning | E12: 1 | F12: LS | H12: =E12*G12 -> 0 | K12: 1 | M12: =$H12*IF(SUM($I12:$L12)=0,I$4,I12) -> 0 | N12: =$H12*IF(SUM($I12:$L12)=0,J$4,J12) -> 0 | O12: =$H12*IF(SUM($I12:$L12)=0,K$4,K12) -> 0 | P12: =$H12*IF(SUM($I12:$L12)=0,L$4,L12) -> 0 | Q12: =IF($H12=0,"",IF(ABS(SUM(M12:P12)-$H12)<0.01,"OK","CHECK"))
A13: 7 | B13: A/C Commissioning | D13: 07 Testing, TAB & Commissioning | E13: 1 | F13: LS | H13: =E13*G13 -> 0 | L13: 1 | M13: =$H13*IF(SUM($I13:$L13)=0,I$4,I13) -> 0 | N13: =$H13*IF(SUM($I13:$L13)=0,J$4,J13) -> 0 | O13: =$H13*IF(SUM($I13:$L13)=0,K$4,K13) -> 0 | P13: =$H13*IF(SUM($I13:$L13)=0,L$4,L13) -> 0 | Q13: =IF($H13=0,"",IF(ABS(SUM(M13:P13)-$H13)<0.01,"OK","CHECK"))
A14: 8 | B14: Canning / Piping Plans | C14: Paris Mechanical | D14: 01 Shop Drawings, Permits & Mobilization | E14: 1 | F14: LS | H14: =E14*G14 -> 0 | I14: 1 | M14: =$H14*IF(SUM($I14:$L14)=0,I$4,I14) -> 0 | N14: =$H14*IF(SUM($I14:$L14)=0,J$4,J14) -> 0 | O14: =$H14*IF(SUM($I14:$L14)=0,K$4,K14) -> 0 | P14: =$H14*IF(SUM($I14:$L14)=0,L$4,L14) -> 0 | Q14: =IF($H14=0,"",IF(ABS(SUM(M14:P14)-$H14)<0.01,"OK","CHECK"))
A15: 9 | B15: Coring / Scanning | D15: 03 Rough-in (Labour) | E15: 1 | F15: LS | H15: =E15*G15 -> 0 | M15: =$H15*IF(SUM($I15:$L15)=0,I$4,I15) -> 0 | N15: =$H15*IF(SUM($I15:$L15)=0,J$4,J15) -> 0 | O15: =$H15*IF(SUM($I15:$L15)=0,K$4,K15) -> 0 | P15: =$H15*IF(SUM($I15:$L15)=0,L$4,L15) -> 0 | Q15: =IF($H15=0,"",IF(ABS(SUM(M15:P15)-$H15)<0.01,"OK","CHECK"))
A16: 10 | B16: Fixtures Caulking | C16: Paris Mechanical | D16: 04 Finishing (Labour) | E16: 1 | F16: LS | H16: =E16*G16 -> 0 | I16: 1 | M16: =$H16*IF(SUM($I16:$L16)=0,I$4,I16) -> 0 | N16: =$H16*IF(SUM($I16:$L16)=0,J$4,J16) -> 0 | O16: =$H16*IF(SUM($I16:$L16)=0,K$4,K16) -> 0 | P16: =$H16*IF(SUM($I16:$L16)=0,L$4,L16) -> 0 | Q16: =IF($H16=0,"",IF(ABS(SUM(M16:P16)-$H16)<0.01,"OK","CHECK"))
A17: 11 | B17: Water Balancing | C17: Western Mechanical | D17: 07 Testing, TAB & Commissioning | E17: 1 | F17: LS | H17: =E17*G17 -> 0 | I17: 1 | M17: =$H17*IF(SUM($I17:$L17)=0,I$4,I17) -> 0 | N17: =$H17*IF(SUM($I17:$L17)=0,J$4,J17) -> 0 | O17: =$H17*IF(SUM($I17:$L17)=0,K$4,K17) -> 0 | P17: =$H17*IF(SUM($I17:$L17)=0,L$4,L17) -> 0 | Q17: =IF($H17=0,"",IF(ABS(SUM(M17:P17)-$H17)<0.01,"OK","CHECK"))
A18: 12 | B18: Sump Pumps | D18: 06 Fixtures & Equipment Supply | E18: 1 | F18: LS | H18: =E18*G18 -> 0 | I18: 1 | M18: =$H18*IF(SUM($I18:$L18)=0,I$4,I18) -> 0 | N18: =$H18*IF(SUM($I18:$L18)=0,J$4,J18) -> 0 | O18: =$H18*IF(SUM($I18:$L18)=0,K$4,K18) -> 0 | P18: =$H18*IF(SUM($I18:$L18)=0,L$4,L18) -> 0 | Q18: =IF($H18=0,"",IF(ABS(SUM(M18:P18)-$H18)<0.01,"OK","CHECK"))
A19: 13 | B19: Chemical Treatment | D19: 07 Testing, TAB & Commissioning | E19: 1 | F19: LS | H19: =E19*G19 -> 0 | J19: 1 | M19: =$H19*IF(SUM($I19:$L19)=0,I$4,I19) -> 0 | N19: =$H19*IF(SUM($I19:$L19)=0,J$4,J19) -> 0 | O19: =$H19*IF(SUM($I19:$L19)=0,K$4,K19) -> 0 | P19: =$H19*IF(SUM($I19:$L19)=0,L$4,L19) -> 0 | Q19: =IF($H19=0,"",IF(ABS(SUM(M19:P19)-$H19)<0.01,"OK","CHECK"))
A20: 14 | B20: P&H Seismic / Schedule | D20: 03 Rough-in (Labour) | E20: 1 | F20: LS | H20: =E20*G20 -> 0 | I20: 0.5 | J20: 0.5 | M20: =$H20*IF(SUM($I20:$L20)=0,I$4,I20) -> 0 | N20: =$H20*IF(SUM($I20:$L20)=0,J$4,J20) -> 0 | O20: =$H20*IF(SUM($I20:$L20)=0,K$4,K20) -> 0 | P20: =$H20*IF(SUM($I20:$L20)=0,L$4,L20) -> 0 | Q20: =IF($H20=0,"",IF(ABS(SUM(M20:P20)-$H20)<0.01,"OK","CHECK"))
A21: 15 | B21: HVAC Seismic / Schedule | D21: 03 Rough-in (Labour) | E21: 1 | F21: LS | H21: =E21*G21 -> 0 | K21: 0.5 | L21: 0.5 | M21: =$H21*IF(SUM($I21:$L21)=0,I$4,I21) -> 0 | N21: =$H21*IF(SUM($I21:$L21)=0,J$4,J21) -> 0 | O21: =$H21*IF(SUM($I21:$L21)=0,K$4,K21) -> 0 | P21: =$H21*IF(SUM($I21:$L21)=0,L$4,L21) -> 0 | Q21: =IF($H21=0,"",IF(ABS(SUM(M21:P21)-$H21)<0.01,"OK","CHECK"))
A22: 16 | B22: As-built Drawings | C22: Paris Mechanical | D22: 08 Completion & Final Documents | E22: 1 | F22: LS | H22: =E22*G22 -> 0 | M22: =$H22*IF(SUM($I22:$L22)=0,I$4,I22) -> 0 | N22: =$H22*IF(SUM($I22:$L22)=0,J$4,J22) -> 0 | O22: =$H22*IF(SUM($I22:$L22)=0,K$4,K22) -> 0 | P22: =$H22*IF(SUM($I22:$L22)=0,L$4,L22) -> 0 | Q22: =IF($H22=0,"",IF(ABS(SUM(M22:P22)-$H22)<0.01,"OK","CHECK"))
A23: 17 | B23: O&M Manuals | C23: Paris Mechanical | D23: 08 Completion & Final Documents | E23: 1 | F23: LS | H23: =E23*G23 -> 0 | M23: =$H23*IF(SUM($I23:$L23)=0,I$4,I23) -> 0 | N23: =$H23*IF(SUM($I23:$L23)=0,J$4,J23) -> 0 | O23: =$H23*IF(SUM($I23:$L23)=0,K$4,K23) -> 0 | P23: =$H23*IF(SUM($I23:$L23)=0,L$4,L23) -> 0 | Q23: =IF($H23=0,"",IF(ABS(SUM(M23:P23)-$H23)<0.01,"OK","CHECK"))
A24: 18 | B24: Plumbing Bond | D24: 01 Shop Drawings, Permits & Mobilization | E24: 1 | F24: LS | H24: =E24*G24 -> 0 | I24: 1 | M24: =$H24*IF(SUM($I24:$L24)=0,I$4,I24) -> 0 | N24: =$H24*IF(SUM($I24:$L24)=0,J$4,J24) -> 0 | O24: =$H24*IF(SUM($I24:$L24)=0,K$4,K24) -> 0 | P24: =$H24*IF(SUM($I24:$L24)=0,L$4,L24) -> 0 | Q24: =IF($H24=0,"",IF(ABS(SUM(M24:P24)-$H24)<0.01,"OK","CHECK"))
A25: 19 | B25: HVAC Bond | D25: 01 Shop Drawings, Permits & Mobilization | E25: 1 | F25: LS | H25: =E25*G25 -> 0 | K25: 0.5 | L25: 0.5 | M25: =$H25*IF(SUM($I25:$L25)=0,I$4,I25) -> 0 | N25: =$H25*IF(SUM($I25:$L25)=0,J$4,J25) -> 0 | O25: =$H25*IF(SUM($I25:$L25)=0,K$4,K25) -> 0 | P25: =$H25*IF(SUM($I25:$L25)=0,L$4,L25) -> 0 | Q25: =IF($H25=0,"",IF(ABS(SUM(M25:P25)-$H25)<0.01,"OK","CHECK"))
A26: 20 | B26: Welding | D26: 03 Rough-in (Labour) | E26: 1 | F26: LS | H26: =E26*G26 -> 0 | K26: 1 | M26: =$H26*IF(SUM($I26:$L26)=0,I$4,I26) -> 0 | N26: =$H26*IF(SUM($I26:$L26)=0,J$4,J26) -> 0 | O26: =$H26*IF(SUM($I26:$L26)=0,K$4,K26) -> 0 | P26: =$H26*IF(SUM($I26:$L26)=0,L$4,L26) -> 0 | Q26: =IF($H26=0,"",IF(ABS(SUM(M26:P26)-$H26)<0.01,"OK","CHECK"))
A27: 21 | B27: Gas Service / Other | D27: 03 Rough-in (Labour) | E27: 1 | F27: LS | H27: =E27*G27 -> 0 | M27: =$H27*IF(SUM($I27:$L27)=0,I$4,I27) -> 0 | N27: =$H27*IF(SUM($I27:$L27)=0,J$4,J27) -> 0 | O27: =$H27*IF(SUM($I27:$L27)=0,K$4,K27) -> 0 | P27: =$H27*IF(SUM($I27:$L27)=0,L$4,L27) -> 0 | Q27: =IF($H27=0,"",IF(ABS(SUM(M27:P27)-$H27)<0.01,"OK","CHECK"))
A28: 22 | E28: 1 | F28: LS | H28: =E28*G28 -> 0 | M28: =$H28*IF(SUM($I28:$L28)=0,I$4,I28) -> 0 | N28: =$H28*IF(SUM($I28:$L28)=0,J$4,J28) -> 0 | O28: =$H28*IF(SUM($I28:$L28)=0,K$4,K28) -> 0 | P28: =$H28*IF(SUM($I28:$L28)=0,L$4,L28) -> 0 | Q28: =IF($H28=0,"",IF(ABS(SUM(M28:P28)-$H28)<0.01,"OK","CHECK"))
B29: SUBTRADES TOTAL | H29: =SUM(H7:H28) -> 0 | M29: =SUM(M7:M28) -> 0 | N29: =SUM(N7:N28) -> 0 | O29: =SUM(O7:O28) -> 0 | P29: =SUM(P7:P28) -> 0
A31: GENERAL CONDITIONS (Qty x Rate)
A32: # | B32: Item | C32: Company / Basis | D32: Phase | E32: Qty | F32: Unit | G32: Rate $ | H32: Amount $ | I32: % P | J32: % H | K32: % V | L32: % AC | M32: Plumbing $ | N32: Hydronic $ | O32: Ventilation $ | P32: A/C $ | Q32: Check
A33: 1 | B33: Supervision - Plumbing | D33: 09 Office, Supervision & General | E33: =INPUTS!$C$21 -> 24 | F33: months | H33: =E33*G33 -> 0 | I33: 1 | M33: =$H33*IF(SUM($I33:$L33)=0,I$4,I33) -> 0 | N33: =$H33*IF(SUM($I33:$L33)=0,J$4,J33) -> 0 | O33: =$H33*IF(SUM($I33:$L33)=0,K$4,K33) -> 0 | P33: =$H33*IF(SUM($I33:$L33)=0,L$4,L33) -> 0 | Q33: =IF($H33=0,"",IF(ABS(SUM(M33:P33)-$H33)<0.01,"OK","CHECK"))
A34: 2 | B34: Supervision - Hydronic | D34: 09 Office, Supervision & General | E34: =INPUTS!$C$21 -> 24 | F34: months | H34: =E34*G34 -> 0 | J34: 1 | M34: =$H34*IF(SUM($I34:$L34)=0,I$4,I34) -> 0 | N34: =$H34*IF(SUM($I34:$L34)=0,J$4,J34) -> 0 | O34: =$H34*IF(SUM($I34:$L34)=0,K$4,K34) -> 0 | P34: =$H34*IF(SUM($I34:$L34)=0,L$4,L34) -> 0 | Q34: =IF($H34=0,"",IF(ABS(SUM(M34:P34)-$H34)<0.01,"OK","CHECK"))
A35: 3 | B35: Supervision - Ventilation | D35: 09 Office, Supervision & General | E35: =INPUTS!$C$22 -> 24 | F35: months | H35: =E35*G35 -> 0 | K35: 1 | M35: =$H35*IF(SUM($I35:$L35)=0,I$4,I35) -> 0 | N35: =$H35*IF(SUM($I35:$L35)=0,J$4,J35) -> 0 | O35: =$H35*IF(SUM($I35:$L35)=0,K$4,K35) -> 0 | P35: =$H35*IF(SUM($I35:$L35)=0,L$4,L35) -> 0 | Q35: =IF($H35=0,"",IF(ABS(SUM(M35:P35)-$H35)<0.01,"OK","CHECK"))
A36: 4 | B36: Supervision - A/C | D36: 09 Office, Supervision & General | E36: =INPUTS!$C$22 -> 24 | F36: months | H36: =E36*G36 -> 0 | L36: 1 | M36: =$H36*IF(SUM($I36:$L36)=0,I$4,I36) -> 0 | N36: =$H36*IF(SUM($I36:$L36)=0,J$4,J36) -> 0 | O36: =$H36*IF(SUM($I36:$L36)=0,K$4,K36) -> 0 | P36: =$H36*IF(SUM($I36:$L36)=0,L$4,L36) -> 0 | Q36: =IF($H36=0,"",IF(ABS(SUM(M36:P36)-$H36)<0.01,"OK","CHECK"))
A37: 5 | B37: Office Project Manager (dedicated to this job) | C37: Dedicated office PM, per month | D37: 09 Office, Supervision & General | E37: =MAX(INPUTS!$C$21,INPUTS!$C$22) -> 24 | F37: months | G37: 7500 | H37: =E37*G37 -> 180000 | M37: =$H37*IF(SUM($I37:$L37)=0,I$4,I37) -> 180000 | N37: =$H37*IF(SUM($I37:$L37)=0,J$4,J37) -> 0 | O37: =$H37*IF(SUM($I37:$L37)=0,K$4,K37) -> 0 | P37: =$H37*IF(SUM($I37:$L37)=0,L$4,L37) -> 0 | Q37: =IF($H37=0,"",IF(ABS(SUM(M37:P37)-$H37)<0.01,"OK","CHECK")) -> OK
A38: 6 | B38: Health & Safety | D38: 09 Office, Supervision & General | E38: =MAX(INPUTS!$C$21,INPUTS!$C$22) -> 24 | F38: months | H38: =E38*G38 -> 0 | M38: =$H38*IF(SUM($I38:$L38)=0,I$4,I38) -> 0 | N38: =$H38*IF(SUM($I38:$L38)=0,J$4,J38) -> 0 | O38: =$H38*IF(SUM($I38:$L38)=0,K$4,K38) -> 0 | P38: =$H38*IF(SUM($I38:$L38)=0,L$4,L38) -> 0 | Q38: =IF($H38=0,"",IF(ABS(SUM(M38:P38)-$H38)<0.01,"OK","CHECK"))
A39: 7 | B39: Bonus - Plumbing | D39: 09 Office, Supervision & General | E39: 1 | F39: LS | H39: =E39*G39 -> 0 | I39: 1 | M39: =$H39*IF(SUM($I39:$L39)=0,I$4,I39) -> 0 | N39: =$H39*IF(SUM($I39:$L39)=0,J$4,J39) -> 0 | O39: =$H39*IF(SUM($I39:$L39)=0,K$4,K39) -> 0 | P39: =$H39*IF(SUM($I39:$L39)=0,L$4,L39) -> 0 | Q39: =IF($H39=0,"",IF(ABS(SUM(M39:P39)-$H39)<0.01,"OK","CHECK"))
A40: 8 | B40: Bonus - Hydronic | D40: 09 Office, Supervision & General | E40: 1 | F40: LS | H40: =E40*G40 -> 0 | J40: 1 | M40: =$H40*IF(SUM($I40:$L40)=0,I$4,I40) -> 0 | N40: =$H40*IF(SUM($I40:$L40)=0,J$4,J40) -> 0 | O40: =$H40*IF(SUM($I40:$L40)=0,K$4,K40) -> 0 | P40: =$H40*IF(SUM($I40:$L40)=0,L$4,L40) -> 0 | Q40: =IF($H40=0,"",IF(ABS(SUM(M40:P40)-$H40)<0.01,"OK","CHECK"))
A41: 9 | B41: Bonus - Ventilation | D41: 09 Office, Supervision & General | E41: 1 | F41: LS | H41: =E41*G41 -> 0 | K41: 1 | M41: =$H41*IF(SUM($I41:$L41)=0,I$4,I41) -> 0 | N41: =$H41*IF(SUM($I41:$L41)=0,J$4,J41) -> 0 | O41: =$H41*IF(SUM($I41:$L41)=0,K$4,K41) -> 0 | P41: =$H41*IF(SUM($I41:$L41)=0,L$4,L41) -> 0 | Q41: =IF($H41=0,"",IF(ABS(SUM(M41:P41)-$H41)<0.01,"OK","CHECK"))
A42: 10 | B42: Bonus - A/C | D42: 09 Office, Supervision & General | E42: 1 | F42: LS | H42: =E42*G42 -> 0 | L42: 1 | M42: =$H42*IF(SUM($I42:$L42)=0,I$4,I42) -> 0 | N42: =$H42*IF(SUM($I42:$L42)=0,J$4,J42) -> 0 | O42: =$H42*IF(SUM($I42:$L42)=0,K$4,K42) -> 0 | P42: =$H42*IF(SUM($I42:$L42)=0,L$4,L42) -> 0 | Q42: =IF($H42=0,"",IF(ABS(SUM(M42:P42)-$H42)<0.01,"OK","CHECK"))
A43: 11 | B43: Bonus - Office | D43: 09 Office, Supervision & General | E43: 1 | F43: LS | H43: =E43*G43 -> 0 | M43: =$H43*IF(SUM($I43:$L43)=0,I$4,I43) -> 0 | N43: =$H43*IF(SUM($I43:$L43)=0,J$4,J43) -> 0 | O43: =$H43*IF(SUM($I43:$L43)=0,K$4,K43) -> 0 | P43: =$H43*IF(SUM($I43:$L43)=0,L$4,L43) -> 0 | Q43: =IF($H43=0,"",IF(ABS(SUM(M43:P43)-$H43)<0.01,"OK","CHECK"))
A44: 12 | B44: Shop Drawings | D44: 01 Shop Drawings, Permits & Mobilization | E44: 1 | F44: LS | H44: =E44*G44 -> 0 | M44: =$H44*IF(SUM($I44:$L44)=0,I$4,I44) -> 0 | N44: =$H44*IF(SUM($I44:$L44)=0,J$4,J44) -> 0 | O44: =$H44*IF(SUM($I44:$L44)=0,K$4,K44) -> 0 | P44: =$H44*IF(SUM($I44:$L44)=0,L$4,L44) -> 0 | Q44: =IF($H44=0,"",IF(ABS(SUM(M44:P44)-$H44)<0.01,"OK","CHECK"))
A45: 13 | B45: Plumbing & Gas Permit | D45: 01 Shop Drawings, Permits & Mobilization | E45: 1 | F45: LS | H45: =E45*G45 -> 0 | I45: 1 | M45: =$H45*IF(SUM($I45:$L45)=0,I$4,I45) -> 0 | N45: =$H45*IF(SUM($I45:$L45)=0,J$4,J45) -> 0 | O45: =$H45*IF(SUM($I45:$L45)=0,K$4,K45) -> 0 | P45: =$H45*IF(SUM($I45:$L45)=0,L$4,L45) -> 0 | Q45: =IF($H45=0,"",IF(ABS(SUM(M45:P45)-$H45)<0.01,"OK","CHECK"))
A46: 14 | B46: Prints | D46: 01 Shop Drawings, Permits & Mobilization | E46: 1 | F46: LS | H46: =E46*G46 -> 0 | M46: =$H46*IF(SUM($I46:$L46)=0,I$4,I46) -> 0 | N46: =$H46*IF(SUM($I46:$L46)=0,J$4,J46) -> 0 | O46: =$H46*IF(SUM($I46:$L46)=0,K$4,K46) -> 0 | P46: =$H46*IF(SUM($I46:$L46)=0,L$4,L46) -> 0 | Q46: =IF($H46=0,"",IF(ABS(SUM(M46:P46)-$H46)<0.01,"OK","CHECK"))
A47: 15 | B47: Rentals | D47: 09 Office, Supervision & General | E47: 4 | F47: months | H47: =E47*G47 -> 0 | M47: =$H47*IF(SUM($I47:$L47)=0,I$4,I47) -> 0 | N47: =$H47*IF(SUM($I47:$L47)=0,J$4,J47) -> 0 | O47: =$H47*IF(SUM($I47:$L47)=0,K$4,K47) -> 0 | P47: =$H47*IF(SUM($I47:$L47)=0,L$4,L47) -> 0 | Q47: =IF($H47=0,"",IF(ABS(SUM(M47:P47)-$H47)<0.01,"OK","CHECK"))
A48: 16 | B48: Trailer | D48: 09 Office, Supervision & General | E48: 12 | F48: months | H48: =E48*G48 -> 0 | M48: =$H48*IF(SUM($I48:$L48)=0,I$4,I48) -> 0 | N48: =$H48*IF(SUM($I48:$L48)=0,J$4,J48) -> 0 | O48: =$H48*IF(SUM($I48:$L48)=0,K$4,K48) -> 0 | P48: =$H48*IF(SUM($I48:$L48)=0,L$4,L48) -> 0 | Q48: =IF($H48=0,"",IF(ABS(SUM(M48:P48)-$H48)<0.01,"OK","CHECK"))
A49: 17 | B49: Legal Fees | D49: 09 Office, Supervision & General | E49: =MAX(INPUTS!$C$21,INPUTS!$C$22) -> 24 | F49: months | H49: =E49*G49 -> 0 | M49: =$H49*IF(SUM($I49:$L49)=0,I$4,I49) -> 0 | N49: =$H49*IF(SUM($I49:$L49)=0,J$4,J49) -> 0 | O49: =$H49*IF(SUM($I49:$L49)=0,K$4,K49) -> 0 | P49: =$H49*IF(SUM($I49:$L49)=0,L$4,L49) -> 0 | Q49: =IF($H49=0,"",IF(ABS(SUM(M49:P49)-$H49)<0.01,"OK","CHECK"))
A50: 18 | B50: Freight | D50: 09 Office, Supervision & General | E50: =MAX(INPUTS!$C$21,INPUTS!$C$22) -> 24 | F50: months | H50: =E50*G50 -> 0 | M50: =$H50*IF(SUM($I50:$L50)=0,I$4,I50) -> 0 | N50: =$H50*IF(SUM($I50:$L50)=0,J$4,J50) -> 0 | O50: =$H50*IF(SUM($I50:$L50)=0,K$4,K50) -> 0 | P50: =$H50*IF(SUM($I50:$L50)=0,L$4,L50) -> 0 | Q50: =IF($H50=0,"",IF(ABS(SUM(M50:P50)-$H50)<0.01,"OK","CHECK"))
A51: 19 | B51: Warranty Reserve - Plumbing | D51: 08 Completion & Final Documents | E51: 1 | F51: LS | G51: =ROUNDUP(INPUTS!$C$27*(SUMIFS('PLUMBING EST'!$L$7:$L$156,'PLUMBING EST'!$B$7:$B$156,"P",'PLUMBING EST'!$C$7:$C$156,INPUTS!$B$72)+SUMIFS('HVAC EST'!$L$7:$L$156,'HVAC EST'!$B$7:$B$156,"P",'HVAC EST'!$C$7:$C$156,INPUTS!$B$72)),-2) -> 0 | H51: =E51*G51 -> 0 | I51: 1 | M51: =$H51*IF(SUM($I51:$L51)=0,I$4,I51) -> 0 | N51: =$H51*IF(SUM($I51:$L51)=0,J$4,J51) -> 0 | O51: =$H51*IF(SUM($I51:$L51)=0,K$4,K51) -> 0 | P51: =$H51*IF(SUM($I51:$L51)=0,L$4,L51) -> 0 | Q51: =IF($H51=0,"",IF(ABS(SUM(M51:P51)-$H51)<0.01,"OK","CHECK"))
A52: 20 | B52: Warranty Reserve - Hydronic | D52: 08 Completion & Final Documents | E52: 1 | F52: LS | G52: =ROUNDUP(INPUTS!$C$27*(SUMIFS('PLUMBING EST'!$L$7:$L$156,'PLUMBING EST'!$B$7:$B$156,"H",'PLUMBING EST'!$C$7:$C$156,INPUTS!$B$72)+SUMIFS('HVAC EST'!$L$7:$L$156,'HVAC EST'!$B$7:$B$156,"H",'HVAC EST'!$C$7:$C$156,INPUTS!$B$72)),-2) -> 0 | H52: =E52*G52 -> 0 | J52: 1 | M52: =$H52*IF(SUM($I52:$L52)=0,I$4,I52) -> 0 | N52: =$H52*IF(SUM($I52:$L52)=0,J$4,J52) -> 0 | O52: =$H52*IF(SUM($I52:$L52)=0,K$4,K52) -> 0 | P52: =$H52*IF(SUM($I52:$L52)=0,L$4,L52) -> 0 | Q52: =IF($H52=0,"",IF(ABS(SUM(M52:P52)-$H52)<0.01,"OK","CHECK"))
A53: 21 | B53: Warranty Reserve - Ventilation | D53: 08 Completion & Final Documents | E53: 1 | F53: LS | G53: =ROUNDUP(INPUTS!$C$27*(SUMIFS('PLUMBING EST'!$L$7:$L$156,'PLUMBING EST'!$B$7:$B$156,"V",'PLUMBING EST'!$C$7:$C$156,INPUTS!$B$72)+SUMIFS('HVAC EST'!$L$7:$L$156,'HVAC EST'!$B$7:$B$156,"V",'HVAC EST'!$C$7:$C$156,INPUTS!$B$72)),-2) -> 0 | H53: =E53*G53 -> 0 | K53: 1 | M53: =$H53*IF(SUM($I53:$L53)=0,I$4,I53) -> 0 | N53: =$H53*IF(SUM($I53:$L53)=0,J$4,J53) -> 0 | O53: =$H53*IF(SUM($I53:$L53)=0,K$4,K53) -> 0 | P53: =$H53*IF(SUM($I53:$L53)=0,L$4,L53) -> 0 | Q53: =IF($H53=0,"",IF(ABS(SUM(M53:P53)-$H53)<0.01,"OK","CHECK"))
A54: 22 | B54: Warranty Reserve - Air Conditioning | D54: 08 Completion & Final Documents | E54: 1 | F54: LS | G54: =ROUNDUP(INPUTS!$C$27*(SUMIFS('PLUMBING EST'!$L$7:$L$156,'PLUMBING EST'!$B$7:$B$156,"AC",'PLUMBING EST'!$C$7:$C$156,INPUTS!$B$72)+SUMIFS('HVAC EST'!$L$7:$L$156,'HVAC EST'!$B$7:$B$156,"AC",'HVAC EST'!$C$7:$C$156,INPUTS!$B$72)),-2) -> 0 | H54: =E54*G54 -> 0 | L54: 1 | M54: =$H54*IF(SUM($I54:$L54)=0,I$4,I54) -> 0 | N54: =$H54*IF(SUM($I54:$L54)=0,J$4,J54) -> 0 | O54: =$H54*IF(SUM($I54:$L54)=0,K$4,K54) -> 0 | P54: =$H54*IF(SUM($I54:$L54)=0,L$4,L54) -> 0 | Q54: =IF($H54=0,"",IF(ABS(SUM(M54:P54)-$H54)<0.01,"OK","CHECK"))
A55: 23 | H55: =E55*G55 -> 0 | M55: =$H55*IF(SUM($I55:$L55)=0,I$4,I55) -> 0 | N55: =$H55*IF(SUM($I55:$L55)=0,J$4,J55) -> 0 | O55: =$H55*IF(SUM($I55:$L55)=0,K$4,K55) -> 0 | P55: =$H55*IF(SUM($I55:$L55)=0,L$4,L55) -> 0 | Q55: =IF($H55=0,"",IF(ABS(SUM(M55:P55)-$H55)<0.01,"OK","CHECK"))
A56: 24 | H56: =E56*G56 -> 0 | M56: =$H56*IF(SUM($I56:$L56)=0,I$4,I56) -> 0 | N56: =$H56*IF(SUM($I56:$L56)=0,J$4,J56) -> 0 | O56: =$H56*IF(SUM($I56:$L56)=0,K$4,K56) -> 0 | P56: =$H56*IF(SUM($I56:$L56)=0,L$4,L56) -> 0 | Q56: =IF($H56=0,"",IF(ABS(SUM(M56:P56)-$H56)<0.01,"OK","CHECK"))
A57: 25 | H57: =E57*G57 -> 0 | M57: =$H57*IF(SUM($I57:$L57)=0,I$4,I57) -> 0 | N57: =$H57*IF(SUM($I57:$L57)=0,J$4,J57) -> 0 | O57: =$H57*IF(SUM($I57:$L57)=0,K$4,K57) -> 0 | P57: =$H57*IF(SUM($I57:$L57)=0,L$4,L57) -> 0 | Q57: =IF($H57=0,"",IF(ABS(SUM(M57:P57)-$H57)<0.01,"OK","CHECK"))
A58: 26 | H58: =E58*G58 -> 0 | M58: =$H58*IF(SUM($I58:$L58)=0,I$4,I58) -> 0 | N58: =$H58*IF(SUM($I58:$L58)=0,J$4,J58) -> 0 | O58: =$H58*IF(SUM($I58:$L58)=0,K$4,K58) -> 0 | P58: =$H58*IF(SUM($I58:$L58)=0,L$4,L58) -> 0 | Q58: =IF($H58=0,"",IF(ABS(SUM(M58:P58)-$H58)<0.01,"OK","CHECK"))
A59: 27 | H59: =E59*G59 -> 0 | M59: =$H59*IF(SUM($I59:$L59)=0,I$4,I59) -> 0 | N59: =$H59*IF(SUM($I59:$L59)=0,J$4,J59) -> 0 | O59: =$H59*IF(SUM($I59:$L59)=0,K$4,K59) -> 0 | P59: =$H59*IF(SUM($I59:$L59)=0,L$4,L59) -> 0 | Q59: =IF($H59=0,"",IF(ABS(SUM(M59:P59)-$H59)<0.01,"OK","CHECK"))
A60: 28 | H60: =E60*G60 -> 0 | M60: =$H60*IF(SUM($I60:$L60)=0,I$4,I60) -> 0 | N60: =$H60*IF(SUM($I60:$L60)=0,J$4,J60) -> 0 | O60: =$H60*IF(SUM($I60:$L60)=0,K$4,K60) -> 0 | P60: =$H60*IF(SUM($I60:$L60)=0,L$4,L60) -> 0 | Q60: =IF($H60=0,"",IF(ABS(SUM(M60:P60)-$H60)<0.01,"OK","CHECK"))
B61: GENERAL CONDITIONS TOTAL | H61: =SUM(H33:H60) -> 180000 | M61: =SUM(M33:M60) -> 180000 | N61: =SUM(N33:N60) -> 0 | O61: =SUM(O33:O60) -> 0 | P61: =SUM(P33:P60) -> 0

Sheet BID SUMMARY
A1: BID SUMMARY: full cost, then margin
A2: =IF(INPUTS!C4="","(enter project name on INPUTS)",INPUTS!C4)&" | "&INPUTS!C11&", "&INPUTS!C12 -> (enter project name on INPUTS) | 2650 East 41st Ave, Vancouver | K2: Bid status: | L2: =I37 -> OK
A5: Code | B5: Division | C5: Hours | D5: Labour $ (wage+burden) | E5: Overhead $ | F5: Material $ (incl PST) | G5: Consumables $ | H5: Subtrades $ | I5: Gen. Cond. $ | J5: Contingency $ | K5: TOTAL COST $ | L5: Target Margin | M5: Sell Price $ | N5: CONTRACT $ (rounded) | O5: Gross Profit $ | P5: Actual Margin | Q5: Markup on Cost | R5: Per Unit $ | S5: Per Sq Ft $ | T5: Hrs / Unit
A6: =INPUTS!C33 -> P | B6: =INPUTS!B33 -> Plumbing | C6: =SUMIFS('PLUMBING EST'!$M$7:$M$156,'PLUMBING EST'!$B$7:$B$156,$A6)+SUMIFS('HVAC EST'!$M$7:$M$156,'HVAC EST'!$B$7:$B$156,$A6) -> 1476 | D6: =SUMIFS('PLUMBING EST'!$N$7:$N$156,'PLUMBING EST'!$B$7:$B$156,$A6)+SUMIFS('HVAC EST'!$N$7:$N$156,'HVAC EST'!$B$7:$B$156,$A6) -> 95563.62 | E6: =SUMIFS('PLUMBING EST'!$O$7:$O$156,'PLUMBING EST'!$B$7:$B$156,$A6)+SUMIFS('HVAC EST'!$O$7:$O$156,'HVAC EST'!$B$7:$B$156,$A6) -> 32472 | F6: =SUMIFS('PLUMBING EST'!$L$7:$L$156,'PLUMBING EST'!$B$7:$B$156,$A6)+SUMIFS('HVAC EST'!$L$7:$L$156,'HVAC EST'!$B$7:$B$156,$A6) -> 105288 | G6: =F6*INPUTS!$C$25 -> 2105.76 | H6: ='SUBS & GC'!M29 -> 0 | I6: ='SUBS & GC'!M61 -> 180000 | J6: =SUM(D6:I6)*INPUTS!$C$26 -> 0 | K6: =SUM(D6:J6) -> 415429.38 | L6: =INPUTS!D33 -> 0.15 | M6: =IFERROR(K6/(1-L6),0) -> 488740.45 | N6: =IF(M6<=0,0,CEILING(M6,INPUTS!$C$28)) -> 488800 | O6: =N6-K6 -> 73370.62 | P6: =IFERROR(O6/N6,0) -> 0.15010356 | Q6: =IFERROR(O6/K6,0) -> 0.17661394 | R6: =IFERROR(N6/INPUTS!$C$18,0) -> 3973.9837 | S6: =IFERROR(N6/INPUTS!$C$17,0) -> 0 | T6: =IFERROR(C6/INPUTS!$C$18,0) -> 12
A7: =INPUTS!C34 -> H | B7: =INPUTS!B34 -> Hydronic | C7: =SUMIFS('PLUMBING EST'!$M$7:$M$156,'PLUMBING EST'!$B$7:$B$156,$A7)+SUMIFS('HVAC EST'!$M$7:$M$156,'HVAC EST'!$B$7:$B$156,$A7) -> 0 | D7: =SUMIFS('PLUMBING EST'!$N$7:$N$156,'PLUMBING EST'!$B$7:$B$156,$A7)+SUMIFS('HVAC EST'!$N$7:$N$156,'HVAC EST'!$B$7:$B$156,$A7) -> 0 | E7: =SUMIFS('PLUMBING EST'!$O$7:$O$156,'PLUMBING EST'!$B$7:$B$156,$A7)+SUMIFS('HVAC EST'!$O$7:$O$156,'HVAC EST'!$B$7:$B$156,$A7) -> 0 | F7: =SUMIFS('PLUMBING EST'!$L$7:$L$156,'PLUMBING EST'!$B$7:$B$156,$A7)+SUMIFS('HVAC EST'!$L$7:$L$156,'HVAC EST'!$B$7:$B$156,$A7) -> 0 | G7: =F7*INPUTS!$C$25 -> 0 | H7: ='SUBS & GC'!N29 -> 0 | I7: ='SUBS & GC'!N61 -> 0 | J7: =SUM(D7:I7)*INPUTS!$C$26 -> 0 | K7: =SUM(D7:J7) -> 0 | L7: =INPUTS!D34 -> 0.15 | M7: =IFERROR(K7/(1-L7),0) -> 0 | N7: =IF(M7<=0,0,CEILING(M7,INPUTS!$C$28)) -> 0 | O7: =N7-K7 -> 0 | P7: =IFERROR(O7/N7,0) -> 0 | Q7: =IFERROR(O7/K7,0) -> 0 | R7: =IFERROR(N7/INPUTS!$C$18,0) -> 0 | S7: =IFERROR(N7/INPUTS!$C$17,0) -> 0 | T7: =IFERROR(C7/INPUTS!$C$18,0) -> 0
A8: =INPUTS!C35 -> V | B8: =INPUTS!B35 -> Ventilation | C8: =SUMIFS('PLUMBING EST'!$M$7:$M$156,'PLUMBING EST'!$B$7:$B$156,$A8)+SUMIFS('HVAC EST'!$M$7:$M$156,'HVAC EST'!$B$7:$B$156,$A8) -> 0 | D8: =SUMIFS('PLUMBING EST'!$N$7:$N$156,'PLUMBING EST'!$B$7:$B$156,$A8)+SUMIFS('HVAC EST'!$N$7:$N$156,'HVAC EST'!$B$7:$B$156,$A8) -> 0 | E8: =SUMIFS('PLUMBING EST'!$O$7:$O$156,'PLUMBING EST'!$B$7:$B$156,$A8)+SUMIFS('HVAC EST'!$O$7:$O$156,'HVAC EST'!$B$7:$B$156,$A8) -> 0 | F8: =SUMIFS('PLUMBING EST'!$L$7:$L$156,'PLUMBING EST'!$B$7:$B$156,$A8)+SUMIFS('HVAC EST'!$L$7:$L$156,'HVAC EST'!$B$7:$B$156,$A8) -> 0 | G8: =F8*INPUTS!$C$25 -> 0 | H8: ='SUBS & GC'!O29 -> 0 | I8: ='SUBS & GC'!O61 -> 0 | J8: =SUM(D8:I8)*INPUTS!$C$26 -> 0 | K8: =SUM(D8:J8) -> 0 | L8: =INPUTS!D35 -> 0.15 | M8: =IFERROR(K8/(1-L8),0) -> 0 | N8: =IF(M8<=0,0,CEILING(M8,INPUTS!$C$28)) -> 0 | O8: =N8-K8 -> 0 | P8: =IFERROR(O8/N8,0) -> 0 | Q8: =IFERROR(O8/K8,0) -> 0 | R8: =IFERROR(N8/INPUTS!$C$18,0) -> 0 | S8: =IFERROR(N8/INPUTS!$C$17,0) -> 0 | T8: =IFERROR(C8/INPUTS!$C$18,0) -> 0
A9: =INPUTS!C36 -> AC | B9: =INPUTS!B36 -> Air Conditioning | C9: =SUMIFS('PLUMBING EST'!$M$7:$M$156,'PLUMBING EST'!$B$7:$B$156,$A9)+SUMIFS('HVAC EST'!$M$7:$M$156,'HVAC EST'!$B$7:$B$156,$A9) -> 0 | D9: =SUMIFS('PLUMBING EST'!$N$7:$N$156,'PLUMBING EST'!$B$7:$B$156,$A9)+SUMIFS('HVAC EST'!$N$7:$N$156,'HVAC EST'!$B$7:$B$156,$A9) -> 0 | E9: =SUMIFS('PLUMBING EST'!$O$7:$O$156,'PLUMBING EST'!$B$7:$B$156,$A9)+SUMIFS('HVAC EST'!$O$7:$O$156,'HVAC EST'!$B$7:$B$156,$A9) -> 0 | F9: =SUMIFS('PLUMBING EST'!$L$7:$L$156,'PLUMBING EST'!$B$7:$B$156,$A9)+SUMIFS('HVAC EST'!$L$7:$L$156,'HVAC EST'!$B$7:$B$156,$A9) -> 0 | G9: =F9*INPUTS!$C$25 -> 0 | H9: ='SUBS & GC'!P29 -> 0 | I9: ='SUBS & GC'!P61 -> 0 | J9: =SUM(D9:I9)*INPUTS!$C$26 -> 0 | K9: =SUM(D9:J9) -> 0 | L9: =INPUTS!D36 -> 0.15 | M9: =IFERROR(K9/(1-L9),0) -> 0 | N9: =IF(M9<=0,0,CEILING(M9,INPUTS!$C$28)) -> 0 | O9: =N9-K9 -> 0 | P9: =IFERROR(O9/N9,0) -> 0 | Q9: =IFERROR(O9/K9,0) -> 0 | R9: =IFERROR(N9/INPUTS!$C$18,0) -> 0 | S9: =IFERROR(N9/INPUTS!$C$17,0) -> 0 | T9: =IFERROR(C9/INPUTS!$C$18,0) -> 0
B10: TOTAL MECHANICAL | C10: =SUM(C6:C9) -> 1476 | D10: =SUM(D6:D9) -> 95563.62 | E10: =SUM(E6:E9) -> 32472 | F10: =SUM(F6:F9) -> 105288 | G10: =SUM(G6:G9) -> 2105.76 | H10: =SUM(H6:H9) -> 0 | I10: =SUM(I6:I9) -> 180000 | J10: =SUM(J6:J9) -> 0 | K10: =SUM(K6:K9) -> 415429.38 | M10: =SUM(M6:M9) -> 488740.45 | N10: =SUM(N6:N9) -> 488800 | O10: =SUM(O6:O9) -> 73370.62 | P10: =IFERROR(O10/N10,0) -> 0.15010356 | Q10: =IFERROR(O10/K10,0) -> 0.17661394 | R10: =IFERROR(N10/INPUTS!$C$18,0) -> 3973.9837 | S10: =IFERROR(N10/INPUTS!$C$17,0) -> 0 | T10: =IFERROR(C10/INPUTS!$C$18,0) -> 12
M11: GST (not in contract cost) | N11: =N10*INPUTS!$C$24 -> 24440
M12: Contract + GST | N12: =N10+N11 -> 513240
B14: COST OF GOODS MIX (whole job)
B15: Cost Type | D15: This Bid $ | E15: % of Contract | F15: % of Total Cost | G15: Knowify Job % of Cost | H15: Your Typical % of Cost | I15: Bid vs Typical
B16: Labour (wage + burden) | D16: =D10 -> 95563.62 | E16: =IFERROR(D16/$N$10,0) -> 0.19550659 | F16: =IFERROR(D16/$K$10,0) -> 0.23003578 | G16: ='KNOWIFY REVIEW'!G14 -> 0.29390662 | H16: =IF(INPUTS!C79="","",INPUTS!C79) | I16: =IF(H16="","",F16-H16) | K16: Knowify job % uses projected cost (larger of budget or actual, per phase).
B17: Overhead | D17: =E10 -> 32472 | E17: =IFERROR(D17/$N$10,0) -> 0.066432079 | F17: =IFERROR(D17/$K$10,0) -> 0.07816491 | G17: ="not tracked" -> not tracked | H17: =IF(INPUTS!C80="","",INPUTS!C80) | I17: =IF(H17="","",F17-H17) | K17: Knowify does not carry company overhead; its office and safety time sits in labour.
B18: Material: pipe, fittings, valves (+PST, consumables) | D18: =F10+G10-(SUMIFS('PLUMBING EST'!$L$7:$L$156,'PLUMBING EST'!$C$7:$C$156,INPUTS!$B$72)+SUMIFS('HVAC EST'!$L$7:$L$156,'HVAC EST'!$C$7:$C$156,INPUTS!$B$72)) -> 107393.76 | E18: =IFERROR(D18/$N$10,0) -> 0.219709 | F18: =IFERROR(D18/$K$10,0) -> 0.25851267 | G18: ='KNOWIFY REVIEW'!G10 -> 0.25875213 | H18: =IF(INPUTS!C81="","",INPUTS!C81) -> 0.26 | I18: =IF(H18="","",F18-H18) -> -0.0014873257 | K18: Knowify 'General Conditions' = its Equipment cost type (tools, rentals).
B19: Fixtures & Equipment Supply | D19: =SUMIFS('PLUMBING EST'!$L$7:$L$156,'PLUMBING EST'!$C$7:$C$156,INPUTS!$B$72)+SUMIFS('HVAC EST'!$L$7:$L$156,'HVAC EST'!$C$7:$C$156,INPUTS!$B$72) -> 0 | E19: =IFERROR(D19/$N$10,0) -> 0 | F19: =IFERROR(D19/$K$10,0) -> 0 | G19: ='KNOWIFY REVIEW'!G12 -> 0.20380429 | H19: =IF(INPUTS!C82="","",INPUTS!C82) | I19: =IF(H19="","",F19-H19)
B20: Subtrades | D20: =H10 -> 0 | E20: =IFERROR(D20/$N$10,0) -> 0 | F20: =IFERROR(D20/$K$10,0) -> 0 | G20: ='KNOWIFY REVIEW'!G16 -> 0.24329786 | H20: =IF(INPUTS!C83="","",INPUTS!C83) | I20: =IF(H20="","",F20-H20)
B21: General Conditions | D21: =I10 -> 180000 | E21: =IFERROR(D21/$N$10,0) -> 0.36824877 | F21: =IFERROR(D21/$K$10,0) -> 0.43328664 | G21: ='KNOWIFY REVIEW'!G17 -> 0.00023910078 | H21: =IF(INPUTS!C84="","",INPUTS!C84) | I21: =IF(H21="","",F21-H21)
B22: Contingency | D22: =J10 -> 0 | E22: =IFERROR(D22/$N$10,0) -> 0 | F22: =IFERROR(D22/$K$10,0) -> 0 | G22: ="" | H22: =IF(INPUTS!C85="","",INPUTS!C85) | I22: =IF(H22="","",F22-H22)
B23: Gross Profit | D23: =O10 -> 73370.62 | E23: =IFERROR(D23/$N$10,0) -> 0.15010356
B24: TOTAL | D24: =SUM(D16:D23) -> 488800 | E24: =SUM(E16:E23) -> 1 | F24: =SUM(F16:F22) -> 1
B26: CHECKS (all must read OK before the bid goes out)
B27: P&H crew mix = 100% and labour ties to wage breakdown | I27: ='LABOUR RATES'!C14 -> OK
B28: HVAC crew mix = 100% and labour ties to wage breakdown | I28: ='LABOUR RATES'!C29 -> OK
B29: P+H labour $ = LABOUR RATES P&H cost by wage breakdown | I29: =IF(ABS(D6+D7-'LABOUR RATES'!G11)<1,"OK","CHECK") -> OK
B30: V+AC labour $ = LABOUR RATES HVAC cost by wage breakdown | I30: =IF(ABS(D8+D9-'LABOUR RATES'!G26)<1,"OK","CHECK") -> OK
B31: Every estimate row has a valid Div and Phase | I31: =IF(SUMPRODUCT(('PLUMBING EST'!$P$7:$P$156<>0)*(ISNA(MATCH('PLUMBING EST'!$B$7:$B$156,INPUTS!$C$33:$C$36,0))+ISNA(MATCH('PLUMBING EST'!$C$7:$C$156,INPUTS!$B$67:$B$75,0))))+SUMPRODUCT(('HVAC EST'!$P$7:$P$156<>0)*(ISNA(MATCH('HVAC EST'!$B$7:$B$156,INPUTS!$C$33:$C$36,0))+ISNA(MATCH('HVAC EST'!$C$7:$C$156,INPUTS!$B$67:$B$75,0))))=0,"OK","CHECK") -> OK
B32: Subtrades fully allocated to divisions | I32: =IF(ABS('SUBS & GC'!H29-SUM('SUBS & GC'!M29:P29))<1,"OK","CHECK") -> OK
B33: General conditions fully allocated to divisions | I33: =IF(ABS('SUBS & GC'!H61-SUM('SUBS & GC'!M61:P61))<1,"OK","CHECK") -> OK
B34: Level weights total 100% | I34: =INPUTS!F64 -> OK
B35: BUDGET total cost = BID SUMMARY total cost (every sub/GC row has a phase) | I35: =IF(ABS(BUDGET!J11-K10)<1,"OK","CHECK") -> OK
B36: SCHEDULE OF VALUES total = contract | I36: =IF(ABS('SCHEDULE OF VALUES'!C5-N10)<1,"OK","CHECK") -> OK
B37: OVERALL | I37: =IF(COUNTIF(I27:I36,"OK")=10,"OK","CHECK") -> OK

Sheet BUDGET
A1: PROJECT BUDGET (cost, by division and phase)
B2: =IF(INPUTS!C4="","",INPUTS!C4)&" Quote: "&INPUTS!C5 -> Quote:
B4: PROJECT ROLL-UP
B5: Division | C5: Hours | D5: Labour $ | E5: Overhead $ | F5: Material $ (incl consumables) | G5: Subtrades $ | H5: Gen. Cond. $ | I5: Contingency $ | J5: TOTAL COST $ | K5: Margin $ | L5: CONTRACT $
B6: ='BID SUMMARY'!B6 -> Plumbing | C6: ='BID SUMMARY'!C6 -> 1476 | D6: ='BID SUMMARY'!D6 -> 95563.62 | E6: ='BID SUMMARY'!E6 -> 32472 | F6: ='BID SUMMARY'!F6+'BID SUMMARY'!G6 -> 107393.76 | G6: ='BID SUMMARY'!H6 -> 0 | H6: ='BID SUMMARY'!I6 -> 180000 | I6: ='BID SUMMARY'!J6 -> 0 | J6: ='BID SUMMARY'!K6 -> 415429.38 | K6: ='BID SUMMARY'!O6 -> 73370.62 | L6: ='BID SUMMARY'!N6 -> 488800
B7: ='BID SUMMARY'!B7 -> Hydronic | C7: ='BID SUMMARY'!C7 -> 0 | D7: ='BID SUMMARY'!D7 -> 0 | E7: ='BID SUMMARY'!E7 -> 0 | F7: ='BID SUMMARY'!F7+'BID SUMMARY'!G7 -> 0 | G7: ='BID SUMMARY'!H7 -> 0 | H7: ='BID SUMMARY'!I7 -> 0 | I7: ='BID SUMMARY'!J7 -> 0 | J7: ='BID SUMMARY'!K7 -> 0 | K7: ='BID SUMMARY'!O7 -> 0 | L7: ='BID SUMMARY'!N7 -> 0
B8: ='BID SUMMARY'!B8 -> Ventilation | C8: ='BID SUMMARY'!C8 -> 0 | D8: ='BID SUMMARY'!D8 -> 0 | E8: ='BID SUMMARY'!E8 -> 0 | F8: ='BID SUMMARY'!F8+'BID SUMMARY'!G8 -> 0 | G8: ='BID SUMMARY'!H8 -> 0 | H8: ='BID SUMMARY'!I8 -> 0 | I8: ='BID SUMMARY'!J8 -> 0 | J8: ='BID SUMMARY'!K8 -> 0 | K8: ='BID SUMMARY'!O8 -> 0 | L8: ='BID SUMMARY'!N8 -> 0
B9: ='BID SUMMARY'!B9 -> Air Conditioning | C9: ='BID SUMMARY'!C9 -> 0 | D9: ='BID SUMMARY'!D9 -> 0 | E9: ='BID SUMMARY'!E9 -> 0 | F9: ='BID SUMMARY'!F9+'BID SUMMARY'!G9 -> 0 | G9: ='BID SUMMARY'!H9 -> 0 | H9: ='BID SUMMARY'!I9 -> 0 | I9: ='BID SUMMARY'!J9 -> 0 | J9: ='BID SUMMARY'!K9 -> 0 | K9: ='BID SUMMARY'!O9 -> 0 | L9: ='BID SUMMARY'!N9 -> 0
B10: TOTAL | C10: =SUM(C6:C9) -> 1476 | D10: =SUM(D6:D9) -> 95563.62 | E10: =SUM(E6:E9) -> 32472 | F10: =SUM(F6:F9) -> 107393.76 | G10: =SUM(G6:G9) -> 0 | H10: =SUM(H6:H9) -> 180000 | I10: =SUM(I6:I9) -> 0 | J10: =SUM(J6:J9) -> 415429.38 | ... L10: =SUM(L6:L9) -> 488800
B11: Total cost rebuilt from phase detail below (must equal J10) | J11: =J27+J46+J65+J84 -> 415429.38 | K11: =IF(ABS(J11-J10)<1,"OK","CHECK") -> OK
B12: Material on 03 Rough-in and 04 Finishing rows is shown under 05 Material Supply (Knowify setup).
B14: =UPPER(INPUTS!B33)&" (P)" -> PLUMBING (P)
B15: Phase | C15: Hours | D15: Labour $ | E15: Overhead $ | F15: Material $ | G15: Subtrades $ | H15: Gen. Cond. $ | J15: TOTAL BUDGET $ | K15: % of Division
B16: =INPUTS!$B$67 -> 01 Shop Drawings, Permits & Mobilization | C16: =SUMIFS('PLUMBING EST'!$M$7:$M$156,'PLUMBING EST'!$B$7:$B$156,"P",'PLUMBING EST'!$C$7:$C$156,INPUTS!$B$67)+SUMIFS('HVAC EST'!$M$7:$M$156,'HVAC EST'!$B$7:$B$156,"P",'HVAC EST'!$C$7:$C$156,INPUTS!$B$67) -> 0 | D16: =SUMIFS('PLUMBING EST'!$N$7:$N$156,'PLUMBING EST'!$B$7:$B$156,"P",'PLUMBING EST'!$C$7:$C$156,INPUTS!$B$67)+SUMIFS('HVAC EST'!$N$7:$N$156,'HVAC EST'!$B$7:$B$156,"P",'HVAC EST'!$C$7:$C$156,INPUTS!$B$67) -> 0 | E16: =SUMIFS('PLUMBING EST'!$O$7:$O$156,'PLUMBING EST'!$B$7:$B$156,"P",'PLUMBING EST'!$C$7:$C$156,INPUTS!$B$67)+SUMIFS('HVAC EST'!$O$7:$O$156,'HVAC EST'!$B$7:$B$156,"P",'HVAC EST'!$C$7:$C$156,INPUTS!$B$67) -> 0 | F16: =SUMIFS('PLUMBING EST'!$L$7:$L$156,'PLUMBING EST'!$B$7:$B$156,"P",'PLUMBING EST'!$C$7:$C$156,INPUTS!$B$67)+SUMIFS('HVAC EST'!$L$7:$L$156,'HVAC EST'!$B$7:$B$156,"P",'HVAC EST'!$C$7:$C$156,INPUTS!$B$67) -> 0 | G16: =SUMIFS('SUBS & GC'!$M$7:$M$28,'SUBS & GC'!$D$7:$D$28,INPUTS!$B$67) -> 0 | H16: =SUMIFS('SUBS & GC'!$M$33:$M$60,'SUBS & GC'!$D$33:$D$60,INPUTS!$B$67) -> 0 | J16: =SUM(D16:H16) -> 0 | K16: =IFERROR(J16/$J$27,0) -> 0
B17: =INPUTS!$B$68 -> 02 Foundation & Underground | C17: =SUMIFS('PLUMBING EST'!$M$7:$M$156,'PLUMBING EST'!$B$7:$B$156,"P",'PLUMBING EST'!$C$7:$C$156,INPUTS!$B$68)+SUMIFS('HVAC EST'!$M$7:$M$156,'HVAC EST'!$B$7:$B$156,"P",'HVAC EST'!$C$7:$C$156,INPUTS!$B$68) -> 0 | D17: =SUMIFS('PLUMBING EST'!$N$7:$N$156,'PLUMBING EST'!$B$7:$B$156,"P",'PLUMBING EST'!$C$7:$C$156,INPUTS!$B$68)+SUMIFS('HVAC EST'!$N$7:$N$156,'HVAC EST'!$B$7:$B$156,"P",'HVAC EST'!$C$7:$C$156,INPUTS!$B$68) -> 0 | E17: =SUMIFS('PLUMBING EST'!$O$7:$O$156,'PLUMBING EST'!$B$7:$B$156,"P",'PLUMBING EST'!$C$7:$C$156,INPUTS!$B$68)+SUMIFS('HVAC EST'!$O$7:$O$156,'HVAC EST'!$B$7:$B$156,"P",'HVAC EST'!$C$7:$C$156,INPUTS!$B$68) -> 0 | F17: =SUMIFS('PLUMBING EST'!$L$7:$L$156,'PLUMBING EST'!$B$7:$B$156,"P",'PLUMBING EST'!$C$7:$C$156,INPUTS!$B$68)+SUMIFS('HVAC EST'!$L$7:$L$156,'HVAC EST'!$B$7:$B$156,"P",'HVAC EST'!$C$7:$C$156,INPUTS!$B$68) -> 0 | G17: =SUMIFS('SUBS & GC'!$M$7:$M$28,'SUBS & GC'!$D$7:$D$28,INPUTS!$B$68) -> 0 | H17: =SUMIFS('SUBS & GC'!$M$33:$M$60,'SUBS & GC'!$D$33:$D$60,INPUTS!$B$68) -> 0 | J17: =SUM(D17:H17) -> 0 | K17: =IFERROR(J17/$J$27,0) -> 0
B18: =INPUTS!$B$69 -> 03 Rough-in (Labour) | C18: =SUMIFS('PLUMBING EST'!$M$7:$M$156,'PLUMBING EST'!$B$7:$B$156,"P",'PLUMBING EST'!$C$7:$C$156,INPUTS!$B$69)+SUMIFS('HVAC EST'!$M$7:$M$156,'HVAC EST'!$B$7:$B$156,"P",'HVAC EST'!$C$7:$C$156,INPUTS!$B$69) -> 1476 | D18: =SUMIFS('PLUMBING EST'!$N$7:$N$156,'PLUMBING EST'!$B$7:$B$156,"P",'PLUMBING EST'!$C$7:$C$156,INPUTS!$B$69)+SUMIFS('HVAC EST'!$N$7:$N$156,'HVAC EST'!$B$7:$B$156,"P",'HVAC EST'!$C$7:$C$156,INPUTS!$B$69) -> 95563.62 | E18: =SUMIFS('PLUMBING EST'!$O$7:$O$156,'PLUMBING EST'!$B$7:$B$156,"P",'PLUMBING EST'!$C$7:$C$156,INPUTS!$B$69)+SUMIFS('HVAC EST'!$O$7:$O$156,'HVAC EST'!$B$7:$B$156,"P",'HVAC EST'!$C$7:$C$156,INPUTS!$B$69) -> 32472 | F18: =0 -> 0 | G18: =SUMIFS('SUBS & GC'!$M$7:$M$28,'SUBS & GC'!$D$7:$D$28,INPUTS!$B$69) -> 0 | H18: =SUMIFS('SUBS & GC'!$M$33:$M$60,'SUBS & GC'!$D$33:$D$60,INPUTS!$B$69) -> 0 | J18: =SUM(D18:H18) -> 128035.62 | K18: =IFERROR(J18/$J$27,0) -> 0.30820069
B19: =INPUTS!$B$70 -> 04 Finishing (Labour) | C19: =SUMIFS('PLUMBING EST'!$M$7:$M$156,'PLUMBING EST'!$B$7:$B$156,"P",'PLUMBING EST'!$C$7:$C$156,INPUTS!$B$70)+SUMIFS('HVAC EST'!$M$7:$M$156,'HVAC EST'!$B$7:$B$156,"P",'HVAC EST'!$C$7:$C$156,INPUTS!$B$70) -> 0 | D19: =SUMIFS('PLUMBING EST'!$N$7:$N$156,'PLUMBING EST'!$B$7:$B$156,"P",'PLUMBING EST'!$C$7:$C$156,INPUTS!$B$70)+SUMIFS('HVAC EST'!$N$7:$N$156,'HVAC EST'!$B$7:$B$156,"P",'HVAC EST'!$C$7:$C$156,INPUTS!$B$70) -> 0 | E19: =SUMIFS('PLUMBING EST'!$O$7:$O$156,'PLUMBING EST'!$B$7:$B$156,"P",'PLUMBING EST'!$C$7:$C$156,INPUTS!$B$70)+SUMIFS('HVAC EST'!$O$7:$O$156,'HVAC EST'!$B$7:$B$156,"P",'HVAC EST'!$C$7:$C$156,INPUTS!$B$70) -> 0 | F19: =0 -> 0 | G19: =SUMIFS('SUBS & GC'!$M$7:$M$28,'SUBS & GC'!$D$7:$D$28,INPUTS!$B$70) -> 0 | H19: =SUMIFS('SUBS & GC'!$M$33:$M$60,'SUBS & GC'!$D$33:$D$60,INPUTS!$B$70) -> 0 | J19: =SUM(D19:H19) -> 0 | K19: =IFERROR(J19/$J$27,0) -> 0
B20: =INPUTS!$B$71 -> 05 Material Supply | C20: =SUMIFS('PLUMBING EST'!$M$7:$M$156,'PLUMBING EST'!$B$7:$B$156,"P",'PLUMBING EST'!$C$7:$C$156,INPUTS!$B$71)+SUMIFS('HVAC EST'!$M$7:$M$156,'HVAC EST'!$B$7:$B$156,"P",'HVAC EST'!$C$7:$C$156,INPUTS!$B$71) -> 0 | D20: =SUMIFS('PLUMBING EST'!$N$7:$N$156,'PLUMBING EST'!$B$7:$B$156,"P",'PLUMBING EST'!$C$7:$C$156,INPUTS!$B$71)+SUMIFS('HVAC EST'!$N$7:$N$156,'HVAC EST'!$B$7:$B$156,"P",'HVAC EST'!$C$7:$C$156,INPUTS!$B$71) -> 0 | E20: =SUMIFS('PLUMBING EST'!$O$7:$O$156,'PLUMBING EST'!$B$7:$B$156,"P",'PLUMBING EST'!$C$7:$C$156,INPUTS!$B$71)+SUMIFS('HVAC EST'!$O$7:$O$156,'HVAC EST'!$B$7:$B$156,"P",'HVAC EST'!$C$7:$C$156,INPUTS!$B$71) -> 0 | F20: =SUMIFS('PLUMBING EST'!$L$7:$L$156,'PLUMBING EST'!$B$7:$B$156,"P",'PLUMBING EST'!$C$7:$C$156,INPUTS!$B$71)+SUMIFS('HVAC EST'!$L$7:$L$156,'HVAC EST'!$B$7:$B$156,"P",'HVAC EST'!$C$7:$C$156,INPUTS!$B$71)+SUMIFS('PLUMBING EST'!$L$7:$L$156,'PLUMBING EST'!$B$7:$B$156,"P",'PLUMBING EST'!$C$7:$C$156,INPUTS!$B$69)+SUMIFS('HVAC EST'!$L$7:$L$156,'HVAC EST'!$B$7:$B$156,"P",'HVAC EST'!$C$7:$C$156,INPUTS!$B$69)+SUMIFS('PLUMBING EST'!$L$7:$L$156,'PLUMBING EST'!$B$7:$B$156,"P",'PLUMBING EST'!$C$7:$C$156,INPUTS!$B$70)+SUMIFS('HVAC EST'!$L$7:$L$156,'HVAC EST'!$B$7:$B$156,"P",'HVAC EST'!$C$7:$C$156,INPUTS!$B$70) -> 105288 | G20: =SUMIFS('SUBS & GC'!$M$7:$M$28,'SUBS & GC'!$D$7:$D$28,INPUTS!$B$71) -> 0 | H20: =SUMIFS('SUBS & GC'!$M$33:$M$60,'SUBS & GC'!$D$33:$D$60,INPUTS!$B$71) -> 0 | J20: =SUM(D20:H20) -> 105288 | K20: =IFERROR(J20/$J$27,0) -> 0.2534438
B21: =INPUTS!$B$72 -> 06 Fixtures & Equipment Supply | C21: =SUMIFS('PLUMBING EST'!$M$7:$M$156,'PLUMBING EST'!$B$7:$B$156,"P",'PLUMBING EST'!$C$7:$C$156,INPUTS!$B$72)+SUMIFS('HVAC EST'!$M$7:$M$156,'HVAC EST'!$B$7:$B$156,"P",'HVAC EST'!$C$7:$C$156,INPUTS!$B$72) -> 0 | D21: =SUMIFS('PLUMBING EST'!$N$7:$N$156,'PLUMBING EST'!$B$7:$B$156,"P",'PLUMBING EST'!$C$7:$C$156,INPUTS!$B$72)+SUMIFS('HVAC EST'!$N$7:$N$156,'HVAC EST'!$B$7:$B$156,"P",'HVAC EST'!$C$7:$C$156,INPUTS!$B$72) -> 0 | E21: =SUMIFS('PLUMBING EST'!$O$7:$O$156,'PLUMBING EST'!$B$7:$B$156,"P",'PLUMBING EST'!$C$7:$C$156,INPUTS!$B$72)+SUMIFS('HVAC EST'!$O$7:$O$156,'HVAC EST'!$B$7:$B$156,"P",'HVAC EST'!$C$7:$C$156,INPUTS!$B$72) -> 0 | F21: =SUMIFS('PLUMBING EST'!$L$7:$L$156,'PLUMBING EST'!$B$7:$B$156,"P",'PLUMBING EST'!$C$7:$C$156,INPUTS!$B$72)+SUMIFS('HVAC EST'!$L$7:$L$156,'HVAC EST'!$B$7:$B$156,"P",'HVAC EST'!$C$7:$C$156,INPUTS!$B$72) -> 0 | G21: =SUMIFS('SUBS & GC'!$M$7:$M$28,'SUBS & GC'!$D$7:$D$28,INPUTS!$B$72) -> 0 | H21: =SUMIFS('SUBS & GC'!$M$33:$M$60,'SUBS & GC'!$D$33:$D$60,INPUTS!$B$72) -> 0 | J21: =SUM(D21:H21) -> 0 | K21: =IFERROR(J21/$J$27,0) -> 0
B22: =INPUTS!$B$73 -> 07 Testing, TAB & Commissioning | C22: =SUMIFS('PLUMBING EST'!$M$7:$M$156,'PLUMBING EST'!$B$7:$B$156,"P",'PLUMBING EST'!$C$7:$C$156,INPUTS!$B$73)+SUMIFS('HVAC EST'!$M$7:$M$156,'HVAC EST'!$B$7:$B$156,"P",'HVAC EST'!$C$7:$C$156,INPUTS!$B$73) -> 0 | D22: =SUMIFS('PLUMBING EST'!$N$7:$N$156,'PLUMBING EST'!$B$7:$B$156,"P",'PLUMBING EST'!$C$7:$C$156,INPUTS!$B$73)+SUMIFS('HVAC EST'!$N$7:$N$156,'HVAC EST'!$B$7:$B$156,"P",'HVAC EST'!$C$7:$C$156,INPUTS!$B$73) -> 0 | E22: =SUMIFS('PLUMBING EST'!$O$7:$O$156,'PLUMBING EST'!$B$7:$B$156,"P",'PLUMBING EST'!$C$7:$C$156,INPUTS!$B$73)+SUMIFS('HVAC EST'!$O$7:$O$156,'HVAC EST'!$B$7:$B$156,"P",'HVAC EST'!$C$7:$C$156,INPUTS!$B$73) -> 0 | F22: =SUMIFS('PLUMBING EST'!$L$7:$L$156,'PLUMBING EST'!$B$7:$B$156,"P",'PLUMBING EST'!$C$7:$C$156,INPUTS!$B$73)+SUMIFS('HVAC EST'!$L$7:$L$156,'HVAC EST'!$B$7:$B$156,"P",'HVAC EST'!$C$7:$C$156,INPUTS!$B$73) -> 0 | G22: =SUMIFS('SUBS & GC'!$M$7:$M$28,'SUBS & GC'!$D$7:$D$28,INPUTS!$B$73) -> 0 | H22: =SUMIFS('SUBS & GC'!$M$33:$M$60,'SUBS & GC'!$D$33:$D$60,INPUTS!$B$73) -> 0 | J22: =SUM(D22:H22) -> 0 | K22: =IFERROR(J22/$J$27,0) -> 0
B23: =INPUTS!$B$74 -> 08 Completion & Final Documents | C23: =SUMIFS('PLUMBING EST'!$M$7:$M$156,'PLUMBING EST'!$B$7:$B$156,"P",'PLUMBING EST'!$C$7:$C$156,INPUTS!$B$74)+SUMIFS('HVAC EST'!$M$7:$M$156,'HVAC EST'!$B$7:$B$156,"P",'HVAC EST'!$C$7:$C$156,INPUTS!$B$74) -> 0 | D23: =SUMIFS('PLUMBING EST'!$N$7:$N$156,'PLUMBING EST'!$B$7:$B$156,"P",'PLUMBING EST'!$C$7:$C$156,INPUTS!$B$74)+SUMIFS('HVAC EST'!$N$7:$N$156,'HVAC EST'!$B$7:$B$156,"P",'HVAC EST'!$C$7:$C$156,INPUTS!$B$74) -> 0 | E23: =SUMIFS('PLUMBING EST'!$O$7:$O$156,'PLUMBING EST'!$B$7:$B$156,"P",'PLUMBING EST'!$C$7:$C$156,INPUTS!$B$74)+SUMIFS('HVAC EST'!$O$7:$O$156,'HVAC EST'!$B$7:$B$156,"P",'HVAC EST'!$C$7:$C$156,INPUTS!$B$74) -> 0 | F23: =SUMIFS('PLUMBING EST'!$L$7:$L$156,'PLUMBING EST'!$B$7:$B$156,"P",'PLUMBING EST'!$C$7:$C$156,INPUTS!$B$74)+SUMIFS('HVAC EST'!$L$7:$L$156,'HVAC EST'!$B$7:$B$156,"P",'HVAC EST'!$C$7:$C$156,INPUTS!$B$74) -> 0 | G23: =SUMIFS('SUBS & GC'!$M$7:$M$28,'SUBS & GC'!$D$7:$D$28,INPUTS!$B$74) -> 0 | H23: =SUMIFS('SUBS & GC'!$M$33:$M$60,'SUBS & GC'!$D$33:$D$60,INPUTS!$B$74) -> 0 | J23: =SUM(D23:H23) -> 0 | K23: =IFERROR(J23/$J$27,0) -> 0
B24: =INPUTS!$B$75 -> 09 Office, Supervision & General | C24: =SUMIFS('PLUMBING EST'!$M$7:$M$156,'PLUMBING EST'!$B$7:$B$156,"P",'PLUMBING EST'!$C$7:$C$156,INPUTS!$B$75)+SUMIFS('HVAC EST'!$M$7:$M$156,'HVAC EST'!$B$7:$B$156,"P",'HVAC EST'!$C$7:$C$156,INPUTS!$B$75) -> 0 | D24: =SUMIFS('PLUMBING EST'!$N$7:$N$156,'PLUMBING EST'!$B$7:$B$156,"P",'PLUMBING EST'!$C$7:$C$156,INPUTS!$B$75)+SUMIFS('HVAC EST'!$N$7:$N$156,'HVAC EST'!$B$7:$B$156,"P",'HVAC EST'!$C$7:$C$156,INPUTS!$B$75) -> 0 | E24: =SUMIFS('PLUMBING EST'!$O$7:$O$156,'PLUMBING EST'!$B$7:$B$156,"P",'PLUMBING EST'!$C$7:$C$156,INPUTS!$B$75)+SUMIFS('HVAC EST'!$O$7:$O$156,'HVAC EST'!$B$7:$B$156,"P",'HVAC EST'!$C$7:$C$156,INPUTS!$B$75) -> 0 | F24: =SUMIFS('PLUMBING EST'!$L$7:$L$156,'PLUMBING EST'!$B$7:$B$156,"P",'PLUMBING EST'!$C$7:$C$156,INPUTS!$B$75)+SUMIFS('HVAC EST'!$L$7:$L$156,'HVAC EST'!$B$7:$B$156,"P",'HVAC EST'!$C$7:$C$156,INPUTS!$B$75) -> 0 | G24: =SUMIFS('SUBS & GC'!$M$7:$M$28,'SUBS & GC'!$D$7:$D$28,INPUTS!$B$75) -> 0 | H24: =SUMIFS('SUBS & GC'!$M$33:$M$60,'SUBS & GC'!$D$33:$D$60,INPUTS!$B$75) -> 180000 | J24: =SUM(D24:H24) -> 180000 | K24: =IFERROR(J24/$J$27,0) -> 0.43328664
B25: Consumables allowance | F25: ='BID SUMMARY'!G6 -> 2105.76 | J25: =F25 -> 2105.76 | K25: =IFERROR(J25/$J$27,0) -> 0.005068876
B26: Contingency | J26: ='BID SUMMARY'!J6 -> 0 | K26: =IFERROR(J26/$J$27,0) -> 0
B27: TOTAL COST BUDGET | C27: =SUM(C16:C26) -> 1476 | D27: =SUM(D16:D26) -> 95563.62 | E27: =SUM(E16:E26) -> 32472 | F27: =SUM(F16:F26) -> 107393.76 | G27: =SUM(G16:G26) -> 0 | H27: =SUM(H16:H26) -> 180000 | J27: =SUM(J16:J26) -> 415429.38
B28: Margin (fee) | J28: ='BID SUMMARY'!O6 -> 73370.62
B29: CONTRACT VALUE | J29: =J27+J28 -> 488800
B33: =UPPER(INPUTS!B34)&" (H)" -> HYDRONIC (H)
B34: Phase | C34: Hours | D34: Labour $ | E34: Overhead $ | F34: Material $ | G34: Subtrades $ | H34: Gen. Cond. $ | J34: TOTAL BUDGET $ | K34: % of Division
B35: =INPUTS!$B$67 -> 01 Shop Drawings, Permits & Mobilization | C35: =SUMIFS('PLUMBING EST'!$M$7:$M$156,'PLUMBING EST'!$B$7:$B$156,"H",'PLUMBING EST'!$C$7:$C$156,INPUTS!$B$67)+SUMIFS('HVAC EST'!$M$7:$M$156,'HVAC EST'!$B$7:$B$156,"H",'HVAC EST'!$C$7:$C$156,INPUTS!$B$67) -> 0 | D35: =SUMIFS('PLUMBING EST'!$N$7:$N$156,'PLUMBING EST'!$B$7:$B$156,"H",'PLUMBING EST'!$C$7:$C$156,INPUTS!$B$67)+SUMIFS('HVAC EST'!$N$7:$N$156,'HVAC EST'!$B$7:$B$156,"H",'HVAC EST'!$C$7:$C$156,INPUTS!$B$67) -> 0 | E35: =SUMIFS('PLUMBING EST'!$O$7:$O$156,'PLUMBING EST'!$B$7:$B$156,"H",'PLUMBING EST'!$C$7:$C$156,INPUTS!$B$67)+SUMIFS('HVAC EST'!$O$7:$O$156,'HVAC EST'!$B$7:$B$156,"H",'HVAC EST'!$C$7:$C$156,INPUTS!$B$67) -> 0 | F35: =SUMIFS('PLUMBING EST'!$L$7:$L$156,'PLUMBING EST'!$B$7:$B$156,"H",'PLUMBING EST'!$C$7:$C$156,INPUTS!$B$67)+SUMIFS('HVAC EST'!$L$7:$L$156,'HVAC EST'!$B$7:$B$156,"H",'HVAC EST'!$C$7:$C$156,INPUTS!$B$67) -> 0 | G35: =SUMIFS('SUBS & GC'!$N$7:$N$28,'SUBS & GC'!$D$7:$D$28,INPUTS!$B$67) -> 0 | H35: =SUMIFS('SUBS & GC'!$N$33:$N$60,'SUBS & GC'!$D$33:$D$60,INPUTS!$B$67) -> 0 | J35: =SUM(D35:H35) -> 0 | K35: =IFERROR(J35/$J$46,0) -> 0
B36: =INPUTS!$B$68 -> 02 Foundation & Underground | C36: =SUMIFS('PLUMBING EST'!$M$7:$M$156,'PLUMBING EST'!$B$7:$B$156,"H",'PLUMBING EST'!$C$7:$C$156,INPUTS!$B$68)+SUMIFS('HVAC EST'!$M$7:$M$156,'HVAC EST'!$B$7:$B$156,"H",'HVAC EST'!$C$7:$C$156,INPUTS!$B$68) -> 0 | D36: =SUMIFS('PLUMBING EST'!$N$7:$N$156,'PLUMBING EST'!$B$7:$B$156,"H",'PLUMBING EST'!$C$7:$C$156,INPUTS!$B$68)+SUMIFS('HVAC EST'!$N$7:$N$156,'HVAC EST'!$B$7:$B$156,"H",'HVAC EST'!$C$7:$C$156,INPUTS!$B$68) -> 0 | E36: =SUMIFS('PLUMBING EST'!$O$7:$O$156,'PLUMBING EST'!$B$7:$B$156,"H",'PLUMBING EST'!$C$7:$C$156,INPUTS!$B$68)+SUMIFS('HVAC EST'!$O$7:$O$156,'HVAC EST'!$B$7:$B$156,"H",'HVAC EST'!$C$7:$C$156,INPUTS!$B$68) -> 0 | F36: =SUMIFS('PLUMBING EST'!$L$7:$L$156,'PLUMBING EST'!$B$7:$B$156,"H",'PLUMBING EST'!$C$7:$C$156,INPUTS!$B$68)+SUMIFS('HVAC EST'!$L$7:$L$156,'HVAC EST'!$B$7:$B$156,"H",'HVAC EST'!$C$7:$C$156,INPUTS!$B$68) -> 0 | G36: =SUMIFS('SUBS & GC'!$N$7:$N$28,'SUBS & GC'!$D$7:$D$28,INPUTS!$B$68) -> 0 | H36: =SUMIFS('SUBS & GC'!$N$33:$N$60,'SUBS & GC'!$D$33:$D$60,INPUTS!$B$68) -> 0 | J36: =SUM(D36:H36) -> 0 | K36: =IFERROR(J36/$J$46,0) -> 0
B37: =INPUTS!$B$69 -> 03 Rough-in (Labour) | C37: =SUMIFS('PLUMBING EST'!$M$7:$M$156,'PLUMBING EST'!$B$7:$B$156,"H",'PLUMBING EST'!$C$7:$C$156,INPUTS!$B$69)+SUMIFS('HVAC EST'!$M$7:$M$156,'HVAC EST'!$B$7:$B$156,"H",'HVAC EST'!$C$7:$C$156,INPUTS!$B$69) -> 0 | D37: =SUMIFS('PLUMBING EST'!$N$7:$N$156,'PLUMBING EST'!$B$7:$B$156,"H",'PLUMBING EST'!$C$7:$C$156,INPUTS!$B$69)+SUMIFS('HVAC EST'!$N$7:$N$156,'HVAC EST'!$B$7:$B$156,"H",'HVAC EST'!$C$7:$C$156,INPUTS!$B$69) -> 0 | E37: =SUMIFS('PLUMBING EST'!$O$7:$O$156,'PLUMBING EST'!$B$7:$B$156,"H",'PLUMBING EST'!$C$7:$C$156,INPUTS!$B$69)+SUMIFS('HVAC EST'!$O$7:$O$156,'HVAC EST'!$B$7:$B$156,"H",'HVAC EST'!$C$7:$C$156,INPUTS!$B$69) -> 0 | F37: =0 -> 0 | G37: =SUMIFS('SUBS & GC'!$N$7:$N$28,'SUBS & GC'!$D$7:$D$28,INPUTS!$B$69) -> 0 | H37: =SUMIFS('SUBS & GC'!$N$33:$N$60,'SUBS & GC'!$D$33:$D$60,INPUTS!$B$69) -> 0 | J37: =SUM(D37:H37) -> 0 | K37: =IFERROR(J37/$J$46,0) -> 0
B38: =INPUTS!$B$70 -> 04 Finishing (Labour) | C38: =SUMIFS('PLUMBING EST'!$M$7:$M$156,'PLUMBING EST'!$B$7:$B$156,"H",'PLUMBING EST'!$C$7:$C$156,INPUTS!$B$70)+SUMIFS('HVAC EST'!$M$7:$M$156,'HVAC EST'!$B$7:$B$156,"H",'HVAC EST'!$C$7:$C$156,INPUTS!$B$70) -> 0 | D38: =SUMIFS('PLUMBING EST'!$N$7:$N$156,'PLUMBING EST'!$B$7:$B$156,"H",'PLUMBING EST'!$C$7:$C$156,INPUTS!$B$70)+SUMIFS('HVAC EST'!$N$7:$N$156,'HVAC EST'!$B$7:$B$156,"H",'HVAC EST'!$C$7:$C$156,INPUTS!$B$70) -> 0 | E38: =SUMIFS('PLUMBING EST'!$O$7:$O$156,'PLUMBING EST'!$B$7:$B$156,"H",'PLUMBING EST'!$C$7:$C$156,INPUTS!$B$70)+SUMIFS('HVAC EST'!$O$7:$O$156,'HVAC EST'!$B$7:$B$156,"H",'HVAC EST'!$C$7:$C$156,INPUTS!$B$70) -> 0 | F38: =0 -> 0 | G38: =SUMIFS('SUBS & GC'!$N$7:$N$28,'SUBS & GC'!$D$7:$D$28,INPUTS!$B$70) -> 0 | H38: =SUMIFS('SUBS & GC'!$N$33:$N$60,'SUBS & GC'!$D$33:$D$60,INPUTS!$B$70) -> 0 | J38: =SUM(D38:H38) -> 0 | K38: =IFERROR(J38/$J$46,0) -> 0
B39: =INPUTS!$B$71 -> 05 Material Supply | C39: =SUMIFS('PLUMBING EST'!$M$7:$M$156,'PLUMBING EST'!$B$7:$B$156,"H",'PLUMBING EST'!$C$7:$C$156,INPUTS!$B$71)+SUMIFS('HVAC EST'!$M$7:$M$156,'HVAC EST'!$B$7:$B$156,"H",'HVAC EST'!$C$7:$C$156,INPUTS!$B$71) -> 0 | D39: =SUMIFS('PLUMBING EST'!$N$7:$N$156,'PLUMBING EST'!$B$7:$B$156,"H",'PLUMBING EST'!$C$7:$C$156,INPUTS!$B$71)+SUMIFS('HVAC EST'!$N$7:$N$156,'HVAC EST'!$B$7:$B$156,"H",'HVAC EST'!$C$7:$C$156,INPUTS!$B$71) -> 0 | E39: =SUMIFS('PLUMBING EST'!$O$7:$O$156,'PLUMBING EST'!$B$7:$B$156,"H",'PLUMBING EST'!$C$7:$C$156,INPUTS!$B$71)+SUMIFS('HVAC EST'!$O$7:$O$156,'HVAC EST'!$B$7:$B$156,"H",'HVAC EST'!$C$7:$C$156,INPUTS!$B$71) -> 0 | F39: =SUMIFS('PLUMBING EST'!$L$7:$L$156,'PLUMBING EST'!$B$7:$B$156,"H",'PLUMBING EST'!$C$7:$C$156,INPUTS!$B$71)+SUMIFS('HVAC EST'!$L$7:$L$156,'HVAC EST'!$B$7:$B$156,"H",'HVAC EST'!$C$7:$C$156,INPUTS!$B$71)+SUMIFS('PLUMBING EST'!$L$7:$L$156,'PLUMBING EST'!$B$7:$B$156,"H",'PLUMBING EST'!$C$7:$C$156,INPUTS!$B$69)+SUMIFS('HVAC EST'!$L$7:$L$156,'HVAC EST'!$B$7:$B$156,"H",'HVAC EST'!$C$7:$C$156,INPUTS!$B$69)+SUMIFS('PLUMBING EST'!$L$7:$L$156,'PLUMBING EST'!$B$7:$B$156,"H",'PLUMBING EST'!$C$7:$C$156,INPUTS!$B$70)+SUMIFS('HVAC EST'!$L$7:$L$156,'HVAC EST'!$B$7:$B$156,"H",'HVAC EST'!$C$7:$C$156,INPUTS!$B$70) -> 0 | G39: =SUMIFS('SUBS & GC'!$N$7:$N$28,'SUBS & GC'!$D$7:$D$28,INPUTS!$B$71) -> 0 | H39: =SUMIFS('SUBS & GC'!$N$33:$N$60,'SUBS & GC'!$D$33:$D$60,INPUTS!$B$71) -> 0 | J39: =SUM(D39:H39) -> 0 | K39: =IFERROR(J39/$J$46,0) -> 0
B40: =INPUTS!$B$72 -> 06 Fixtures & Equipment Supply | C40: =SUMIFS('PLUMBING EST'!$M$7:$M$156,'PLUMBING EST'!$B$7:$B$156,"H",'PLUMBING EST'!$C$7:$C$156,INPUTS!$B$72)+SUMIFS('HVAC EST'!$M$7:$M$156,'HVAC EST'!$B$7:$B$156,"H",'HVAC EST'!$C$7:$C$156,INPUTS!$B$72) -> 0 | D40: =SUMIFS('PLUMBING EST'!$N$7:$N$156,'PLUMBING EST'!$B$7:$B$156,"H",'PLUMBING EST'!$C$7:$C$156,INPUTS!$B$72)+SUMIFS('HVAC EST'!$N$7:$N$156,'HVAC EST'!$B$7:$B$156,"H",'HVAC EST'!$C$7:$C$156,INPUTS!$B$72) -> 0 | E40: =SUMIFS('PLUMBING EST'!$O$7:$O$156,'PLUMBING EST'!$B$7:$B$156,"H",'PLUMBING EST'!$C$7:$C$156,INPUTS!$B$72)+SUMIFS('HVAC EST'!$O$7:$O$156,'HVAC EST'!$B$7:$B$156,"H",'HVAC EST'!$C$7:$C$156,INPUTS!$B$72) -> 0 | F40: =SUMIFS('PLUMBING EST'!$L$7:$L$156,'PLUMBING EST'!$B$7:$B$156,"H",'PLUMBING EST'!$C$7:$C$156,INPUTS!$B$72)+SUMIFS('HVAC EST'!$L$7:$L$156,'HVAC EST'!$B$7:$B$156,"H",'HVAC EST'!$C$7:$C$156,INPUTS!$B$72) -> 0 | G40: =SUMIFS('SUBS & GC'!$N$7:$N$28,'SUBS & GC'!$D$7:$D$28,INPUTS!$B$72) -> 0 | H40: =SUMIFS('SUBS & GC'!$N$33:$N$60,'SUBS & GC'!$D$33:$D$60,INPUTS!$B$72) -> 0 | J40: =SUM(D40:H40) -> 0 | K40: =IFERROR(J40/$J$46,0) -> 0
B41: =INPUTS!$B$73 -> 07 Testing, TAB & Commissioning | C41: =SUMIFS('PLUMBING EST'!$M$7:$M$156,'PLUMBING EST'!$B$7:$B$156,"H",'PLUMBING EST'!$C$7:$C$156,INPUTS!$B$73)+SUMIFS('HVAC EST'!$M$7:$M$156,'HVAC EST'!$B$7:$B$156,"H",'HVAC EST'!$C$7:$C$156,INPUTS!$B$73) -> 0 | D41: =SUMIFS('PLUMBING EST'!$N$7:$N$156,'PLUMBING EST'!$B$7:$B$156,"H",'PLUMBING EST'!$C$7:$C$156,INPUTS!$B$73)+SUMIFS('HVAC EST'!$N$7:$N$156,'HVAC EST'!$B$7:$B$156,"H",'HVAC EST'!$C$7:$C$156,INPUTS!$B$73) -> 0 | E41: =SUMIFS('PLUMBING EST'!$O$7:$O$156,'PLUMBING EST'!$B$7:$B$156,"H",'PLUMBING EST'!$C$7:$C$156,INPUTS!$B$73)+SUMIFS('HVAC EST'!$O$7:$O$156,'HVAC EST'!$B$7:$B$156,"H",'HVAC EST'!$C$7:$C$156,INPUTS!$B$73) -> 0 | F41: =SUMIFS('PLUMBING EST'!$L$7:$L$156,'PLUMBING EST'!$B$7:$B$156,"H",'PLUMBING EST'!$C$7:$C$156,INPUTS!$B$73)+SUMIFS('HVAC EST'!$L$7:$L$156,'HVAC EST'!$B$7:$B$156,"H",'HVAC EST'!$C$7:$C$156,INPUTS!$B$73) -> 0 | G41: =SUMIFS('SUBS & GC'!$N$7:$N$28,'SUBS & GC'!$D$7:$D$28,INPUTS!$B$73) -> 0 | H41: =SUMIFS('SUBS & GC'!$N$33:$N$60,'SUBS & GC'!$D$33:$D$60,INPUTS!$B$73) -> 0 | J41: =SUM(D41:H41) -> 0 | K41: =IFERROR(J41/$J$46,0) -> 0
B42: =INPUTS!$B$74 -> 08 Completion & Final Documents | C42: =SUMIFS('PLUMBING EST'!$M$7:$M$156,'PLUMBING EST'!$B$7:$B$156,"H",'PLUMBING EST'!$C$7:$C$156,INPUTS!$B$74)+SUMIFS('HVAC EST'!$M$7:$M$156,'HVAC EST'!$B$7:$B$156,"H",'HVAC EST'!$C$7:$C$156,INPUTS!$B$74) -> 0 | D42: =SUMIFS('PLUMBING EST'!$N$7:$N$156,'PLUMBING EST'!$B$7:$B$156,"H",'PLUMBING EST'!$C$7:$C$156,INPUTS!$B$74)+SUMIFS('HVAC EST'!$N$7:$N$156,'HVAC EST'!$B$7:$B$156,"H",'HVAC EST'!$C$7:$C$156,INPUTS!$B$74) -> 0 | E42: =SUMIFS('PLUMBING EST'!$O$7:$O$156,'PLUMBING EST'!$B$7:$B$156,"H",'PLUMBING EST'!$C$7:$C$156,INPUTS!$B$74)+SUMIFS('HVAC EST'!$O$7:$O$156,'HVAC EST'!$B$7:$B$156,"H",'HVAC EST'!$C$7:$C$156,INPUTS!$B$74) -> 0 | F42: =SUMIFS('PLUMBING EST'!$L$7:$L$156,'PLUMBING EST'!$B$7:$B$156,"H",'PLUMBING EST'!$C$7:$C$156,INPUTS!$B$74)+SUMIFS('HVAC EST'!$L$7:$L$156,'HVAC EST'!$B$7:$B$156,"H",'HVAC EST'!$C$7:$C$156,INPUTS!$B$74) -> 0 | G42: =SUMIFS('SUBS & GC'!$N$7:$N$28,'SUBS & GC'!$D$7:$D$28,INPUTS!$B$74) -> 0 | H42: =SUMIFS('SUBS & GC'!$N$33:$N$60,'SUBS & GC'!$D$33:$D$60,INPUTS!$B$74) -> 0 | J42: =SUM(D42:H42) -> 0 | K42: =IFERROR(J42/$J$46,0) -> 0
B43: =INPUTS!$B$75 -> 09 Office, Supervision & General | C43: =SUMIFS('PLUMBING EST'!$M$7:$M$156,'PLUMBING EST'!$B$7:$B$156,"H",'PLUMBING EST'!$C$7:$C$156,INPUTS!$B$75)+SUMIFS('HVAC EST'!$M$7:$M$156,'HVAC EST'!$B$7:$B$156,"H",'HVAC EST'!$C$7:$C$156,INPUTS!$B$75) -> 0 | D43: =SUMIFS('PLUMBING EST'!$N$7:$N$156,'PLUMBING EST'!$B$7:$B$156,"H",'PLUMBING EST'!$C$7:$C$156,INPUTS!$B$75)+SUMIFS('HVAC EST'!$N$7:$N$156,'HVAC EST'!$B$7:$B$156,"H",'HVAC EST'!$C$7:$C$156,INPUTS!$B$75) -> 0 | E43: =SUMIFS('PLUMBING EST'!$O$7:$O$156,'PLUMBING EST'!$B$7:$B$156,"H",'PLUMBING EST'!$C$7:$C$156,INPUTS!$B$75)+SUMIFS('HVAC EST'!$O$7:$O$156,'HVAC EST'!$B$7:$B$156,"H",'HVAC EST'!$C$7:$C$156,INPUTS!$B$75) -> 0 | F43: =SUMIFS('PLUMBING EST'!$L$7:$L$156,'PLUMBING EST'!$B$7:$B$156,"H",'PLUMBING EST'!$C$7:$C$156,INPUTS!$B$75)+SUMIFS('HVAC EST'!$L$7:$L$156,'HVAC EST'!$B$7:$B$156,"H",'HVAC EST'!$C$7:$C$156,INPUTS!$B$75) -> 0 | G43: =SUMIFS('SUBS & GC'!$N$7:$N$28,'SUBS & GC'!$D$7:$D$28,INPUTS!$B$75) -> 0 | H43: =SUMIFS('SUBS & GC'!$N$33:$N$60,'SUBS & GC'!$D$33:$D$60,INPUTS!$B$75) -> 0 | J43: =SUM(D43:H43) -> 0 | K43: =IFERROR(J43/$J$46,0) -> 0
B44: Consumables allowance | F44: ='BID SUMMARY'!G7 -> 0 | J44: =F44 -> 0 | K44: =IFERROR(J44/$J$46,0) -> 0
B45: Contingency | J45: ='BID SUMMARY'!J7 -> 0 | K45: =IFERROR(J45/$J$46,0) -> 0
B46: TOTAL COST BUDGET | C46: =SUM(C35:C45) -> 0 | D46: =SUM(D35:D45) -> 0 | E46: =SUM(E35:E45) -> 0 | F46: =SUM(F35:F45) -> 0 | G46: =SUM(G35:G45) -> 0 | H46: =SUM(H35:H45) -> 0 | J46: =SUM(J35:J45) -> 0
B47: Margin (fee) | J47: ='BID SUMMARY'!O7 -> 0
B48: CONTRACT VALUE | J48: =J46+J47 -> 0
B52: =UPPER(INPUTS!B35)&" (V)" -> VENTILATION (V)
B53: Phase | C53: Hours | D53: Labour $ | E53: Overhead $ | F53: Material $ | G53: Subtrades $ | H53: Gen. Cond. $ | J53: TOTAL BUDGET $ | K53: % of Division
B54: =INPUTS!$B$67 -> 01 Shop Drawings, Permits & Mobilization | C54: =SUMIFS('PLUMBING EST'!$M$7:$M$156,'PLUMBING EST'!$B$7:$B$156,"V",'PLUMBING EST'!$C$7:$C$156,INPUTS!$B$67)+SUMIFS('HVAC EST'!$M$7:$M$156,'HVAC EST'!$B$7:$B$156,"V",'HVAC EST'!$C$7:$C$156,INPUTS!$B$67) -> 0 | D54: =SUMIFS('PLUMBING EST'!$N$7:$N$156,'PLUMBING EST'!$B$7:$B$156,"V",'PLUMBING EST'!$C$7:$C$156,INPUTS!$B$67)+SUMIFS('HVAC EST'!$N$7:$N$156,'HVAC EST'!$B$7:$B$156,"V",'HVAC EST'!$C$7:$C$156,INPUTS!$B$67) -> 0 | E54: =SUMIFS('PLUMBING EST'!$O$7:$O$156,'PLUMBING EST'!$B$7:$B$156,"V",'PLUMBING EST'!$C$7:$C$156,INPUTS!$B$67)+SUMIFS('HVAC EST'!$O$7:$O$156,'HVAC EST'!$B$7:$B$156,"V",'HVAC EST'!$C$7:$C$156,INPUTS!$B$67) -> 0 | F54: =SUMIFS('PLUMBING EST'!$L$7:$L$156,'PLUMBING EST'!$B$7:$B$156,"V",'PLUMBING EST'!$C$7:$C$156,INPUTS!$B$67)+SUMIFS('HVAC EST'!$L$7:$L$156,'HVAC EST'!$B$7:$B$156,"V",'HVAC EST'!$C$7:$C$156,INPUTS!$B$67) -> 0 | G54: =SUMIFS('SUBS & GC'!$O$7:$O$28,'SUBS & GC'!$D$7:$D$28,INPUTS!$B$67) -> 0 | H54: =SUMIFS('SUBS & GC'!$O$33:$O$60,'SUBS & GC'!$D$33:$D$60,INPUTS!$B$67) -> 0 | J54: =SUM(D54:H54) -> 0 | K54: =IFERROR(J54/$J$65,0) -> 0
B55: =INPUTS!$B$68 -> 02 Foundation & Underground | C55: =SUMIFS('PLUMBING EST'!$M$7:$M$156,'PLUMBING EST'!$B$7:$B$156,"V",'PLUMBING EST'!$C$7:$C$156,INPUTS!$B$68)+SUMIFS('HVAC EST'!$M$7:$M$156,'HVAC EST'!$B$7:$B$156,"V",'HVAC EST'!$C$7:$C$156,INPUTS!$B$68) -> 0 | D55: =SUMIFS('PLUMBING EST'!$N$7:$N$156,'PLUMBING EST'!$B$7:$B$156,"V",'PLUMBING EST'!$C$7:$C$156,INPUTS!$B$68)+SUMIFS('HVAC EST'!$N$7:$N$156,'HVAC EST'!$B$7:$B$156,"V",'HVAC EST'!$C$7:$C$156,INPUTS!$B$68) -> 0 | E55: =SUMIFS('PLUMBING EST'!$O$7:$O$156,'PLUMBING EST'!$B$7:$B$156,"V",'PLUMBING EST'!$C$7:$C$156,INPUTS!$B$68)+SUMIFS('HVAC EST'!$O$7:$O$156,'HVAC EST'!$B$7:$B$156,"V",'HVAC EST'!$C$7:$C$156,INPUTS!$B$68) -> 0 | F55: =SUMIFS('PLUMBING EST'!$L$7:$L$156,'PLUMBING EST'!$B$7:$B$156,"V",'PLUMBING EST'!$C$7:$C$156,INPUTS!$B$68)+SUMIFS('HVAC EST'!$L$7:$L$156,'HVAC EST'!$B$7:$B$156,"V",'HVAC EST'!$C$7:$C$156,INPUTS!$B$68) -> 0 | G55: =SUMIFS('SUBS & GC'!$O$7:$O$28,'SUBS & GC'!$D$7:$D$28,INPUTS!$B$68) -> 0 | H55: =SUMIFS('SUBS & GC'!$O$33:$O$60,'SUBS & GC'!$D$33:$D$60,INPUTS!$B$68) -> 0 | J55: =SUM(D55:H55) -> 0 | K55: =IFERROR(J55/$J$65,0) -> 0
B56: =INPUTS!$B$69 -> 03 Rough-in (Labour) | C56: =SUMIFS('PLUMBING EST'!$M$7:$M$156,'PLUMBING EST'!$B$7:$B$156,"V",'PLUMBING EST'!$C$7:$C$156,INPUTS!$B$69)+SUMIFS('HVAC EST'!$M$7:$M$156,'HVAC EST'!$B$7:$B$156,"V",'HVAC EST'!$C$7:$C$156,INPUTS!$B$69) -> 0 | D56: =SUMIFS('PLUMBING EST'!$N$7:$N$156,'PLUMBING EST'!$B$7:$B$156,"V",'PLUMBING EST'!$C$7:$C$156,INPUTS!$B$69)+SUMIFS('HVAC EST'!$N$7:$N$156,'HVAC EST'!$B$7:$B$156,"V",'HVAC EST'!$C$7:$C$156,INPUTS!$B$69) -> 0 | E56: =SUMIFS('PLUMBING EST'!$O$7:$O$156,'PLUMBING EST'!$B$7:$B$156,"V",'PLUMBING EST'!$C$7:$C$156,INPUTS!$B$69)+SUMIFS('HVAC EST'!$O$7:$O$156,'HVAC EST'!$B$7:$B$156,"V",'HVAC EST'!$C$7:$C$156,INPUTS!$B$69) -> 0 | F56: =0 -> 0 | G56: =SUMIFS('SUBS & GC'!$O$7:$O$28,'SUBS & GC'!$D$7:$D$28,INPUTS!$B$69) -> 0 | H56: =SUMIFS('SUBS & GC'!$O$33:$O$60,'SUBS & GC'!$D$33:$D$60,INPUTS!$B$69) -> 0 | J56: =SUM(D56:H56) -> 0 | K56: =IFERROR(J56/$J$65,0) -> 0
B57: =INPUTS!$B$70 -> 04 Finishing (Labour) | C57: =SUMIFS('PLUMBING EST'!$M$7:$M$156,'PLUMBING EST'!$B$7:$B$156,"V",'PLUMBING EST'!$C$7:$C$156,INPUTS!$B$70)+SUMIFS('HVAC EST'!$M$7:$M$156,'HVAC EST'!$B$7:$B$156,"V",'HVAC EST'!$C$7:$C$156,INPUTS!$B$70) -> 0 | D57: =SUMIFS('PLUMBING EST'!$N$7:$N$156,'PLUMBING EST'!$B$7:$B$156,"V",'PLUMBING EST'!$C$7:$C$156,INPUTS!$B$70)+SUMIFS('HVAC EST'!$N$7:$N$156,'HVAC EST'!$B$7:$B$156,"V",'HVAC EST'!$C$7:$C$156,INPUTS!$B$70) -> 0 | E57: =SUMIFS('PLUMBING EST'!$O$7:$O$156,'PLUMBING EST'!$B$7:$B$156,"V",'PLUMBING EST'!$C$7:$C$156,INPUTS!$B$70)+SUMIFS('HVAC EST'!$O$7:$O$156,'HVAC EST'!$B$7:$B$156,"V",'HVAC EST'!$C$7:$C$156,INPUTS!$B$70) -> 0 | F57: =0 -> 0 | G57: =SUMIFS('SUBS & GC'!$O$7:$O$28,'SUBS & GC'!$D$7:$D$28,INPUTS!$B$70) -> 0 | H57: =SUMIFS('SUBS & GC'!$O$33:$O$60,'SUBS & GC'!$D$33:$D$60,INPUTS!$B$70) -> 0 | J57: =SUM(D57:H57) -> 0 | K57: =IFERROR(J57/$J$65,0) -> 0
B58: =INPUTS!$B$71 -> 05 Material Supply | C58: =SUMIFS('PLUMBING EST'!$M$7:$M$156,'PLUMBING EST'!$B$7:$B$156,"V",'PLUMBING EST'!$C$7:$C$156,INPUTS!$B$71)+SUMIFS('HVAC EST'!$M$7:$M$156,'HVAC EST'!$B$7:$B$156,"V",'HVAC EST'!$C$7:$C$156,INPUTS!$B$71) -> 0 | D58: =SUMIFS('PLUMBING EST'!$N$7:$N$156,'PLUMBING EST'!$B$7:$B$156,"V",'PLUMBING EST'!$C$7:$C$156,INPUTS!$B$71)+SUMIFS('HVAC EST'!$N$7:$N$156,'HVAC EST'!$B$7:$B$156,"V",'HVAC EST'!$C$7:$C$156,INPUTS!$B$71) -> 0 | E58: =SUMIFS('PLUMBING EST'!$O$7:$O$156,'PLUMBING EST'!$B$7:$B$156,"V",'PLUMBING EST'!$C$7:$C$156,INPUTS!$B$71)+SUMIFS('HVAC EST'!$O$7:$O$156,'HVAC EST'!$B$7:$B$156,"V",'HVAC EST'!$C$7:$C$156,INPUTS!$B$71) -> 0 | F58: =SUMIFS('PLUMBING EST'!$L$7:$L$156,'PLUMBING EST'!$B$7:$B$156,"V",'PLUMBING EST'!$C$7:$C$156,INPUTS!$B$71)+SUMIFS('HVAC EST'!$L$7:$L$156,'HVAC EST'!$B$7:$B$156,"V",'HVAC EST'!$C$7:$C$156,INPUTS!$B$71)+SUMIFS('PLUMBING EST'!$L$7:$L$156,'PLUMBING EST'!$B$7:$B$156,"V",'PLUMBING EST'!$C$7:$C$156,INPUTS!$B$69)+SUMIFS('HVAC EST'!$L$7:$L$156,'HVAC EST'!$B$7:$B$156,"V",'HVAC EST'!$C$7:$C$156,INPUTS!$B$69)+SUMIFS('PLUMBING EST'!$L$7:$L$156,'PLUMBING EST'!$B$7:$B$156,"V",'PLUMBING EST'!$C$7:$C$156,INPUTS!$B$70)+SUMIFS('HVAC EST'!$L$7:$L$156,'HVAC EST'!$B$7:$B$156,"V",'HVAC EST'!$C$7:$C$156,INPUTS!$B$70) -> 0 | G58: =SUMIFS('SUBS & GC'!$O$7:$O$28,'SUBS & GC'!$D$7:$D$28,INPUTS!$B$71) -> 0 | H58: =SUMIFS('SUBS & GC'!$O$33:$O$60,'SUBS & GC'!$D$33:$D$60,INPUTS!$B$71) -> 0 | J58: =SUM(D58:H58) -> 0 | K58: =IFERROR(J58/$J$65,0) -> 0
B59: =INPUTS!$B$72 -> 06 Fixtures & Equipment Supply | C59: =SUMIFS('PLUMBING EST'!$M$7:$M$156,'PLUMBING EST'!$B$7:$B$156,"V",'PLUMBING EST'!$C$7:$C$156,INPUTS!$B$72)+SUMIFS('HVAC EST'!$M$7:$M$156,'HVAC EST'!$B$7:$B$156,"V",'HVAC EST'!$C$7:$C$156,INPUTS!$B$72) -> 0 | D59: =SUMIFS('PLUMBING EST'!$N$7:$N$156,'PLUMBING EST'!$B$7:$B$156,"V",'PLUMBING EST'!$C$7:$C$156,INPUTS!$B$72)+SUMIFS('HVAC EST'!$N$7:$N$156,'HVAC EST'!$B$7:$B$156,"V",'HVAC EST'!$C$7:$C$156,INPUTS!$B$72) -> 0 | E59: =SUMIFS('PLUMBING EST'!$O$7:$O$156,'PLUMBING EST'!$B$7:$B$156,"V",'PLUMBING EST'!$C$7:$C$156,INPUTS!$B$72)+SUMIFS('HVAC EST'!$O$7:$O$156,'HVAC EST'!$B$7:$B$156,"V",'HVAC EST'!$C$7:$C$156,INPUTS!$B$72) -> 0 | F59: =SUMIFS('PLUMBING EST'!$L$7:$L$156,'PLUMBING EST'!$B$7:$B$156,"V",'PLUMBING EST'!$C$7:$C$156,INPUTS!$B$72)+SUMIFS('HVAC EST'!$L$7:$L$156,'HVAC EST'!$B$7:$B$156,"V",'HVAC EST'!$C$7:$C$156,INPUTS!$B$72) -> 0 | G59: =SUMIFS('SUBS & GC'!$O$7:$O$28,'SUBS & GC'!$D$7:$D$28,INPUTS!$B$72) -> 0 | H59: =SUMIFS('SUBS & GC'!$O$33:$O$60,'SUBS & GC'!$D$33:$D$60,INPUTS!$B$72) -> 0 | J59: =SUM(D59:H59) -> 0 | K59: =IFERROR(J59/$J$65,0) -> 0
B60: =INPUTS!$B$73 -> 07 Testing, TAB & Commissioning | C60: =SUMIFS('PLUMBING EST'!$M$7:$M$156,'PLUMBING EST'!$B$7:$B$156,"V",'PLUMBING EST'!$C$7:$C$156,INPUTS!$B$73)+SUMIFS('HVAC EST'!$M$7:$M$156,'HVAC EST'!$B$7:$B$156,"V",'HVAC EST'!$C$7:$C$156,INPUTS!$B$73) -> 0 | D60: =SUMIFS('PLUMBING EST'!$N$7:$N$156,'PLUMBING EST'!$B$7:$B$156,"V",'PLUMBING EST'!$C$7:$C$156,INPUTS!$B$73)+SUMIFS('HVAC EST'!$N$7:$N$156,'HVAC EST'!$B$7:$B$156,"V",'HVAC EST'!$C$7:$C$156,INPUTS!$B$73) -> 0 | E60: =SUMIFS('PLUMBING EST'!$O$7:$O$156,'PLUMBING EST'!$B$7:$B$156,"V",'PLUMBING EST'!$C$7:$C$156,INPUTS!$B$73)+SUMIFS('HVAC EST'!$O$7:$O$156,'HVAC EST'!$B$7:$B$156,"V",'HVAC EST'!$C$7:$C$156,INPUTS!$B$73) -> 0 | F60: =SUMIFS('PLUMBING EST'!$L$7:$L$156,'PLUMBING EST'!$B$7:$B$156,"V",'PLUMBING EST'!$C$7:$C$156,INPUTS!$B$73)+SUMIFS('HVAC EST'!$L$7:$L$156,'HVAC EST'!$B$7:$B$156,"V",'HVAC EST'!$C$7:$C$156,INPUTS!$B$73) -> 0 | G60: =SUMIFS('SUBS & GC'!$O$7:$O$28,'SUBS & GC'!$D$7:$D$28,INPUTS!$B$73) -> 0 | H60: =SUMIFS('SUBS & GC'!$O$33:$O$60,'SUBS & GC'!$D$33:$D$60,INPUTS!$B$73) -> 0 | J60: =SUM(D60:H60) -> 0 | K60: =IFERROR(J60/$J$65,0) -> 0
B61: =INPUTS!$B$74 -> 08 Completion & Final Documents | C61: =SUMIFS('PLUMBING EST'!$M$7:$M$156,'PLUMBING EST'!$B$7:$B$156,"V",'PLUMBING EST'!$C$7:$C$156,INPUTS!$B$74)+SUMIFS('HVAC EST'!$M$7:$M$156,'HVAC EST'!$B$7:$B$156,"V",'HVAC EST'!$C$7:$C$156,INPUTS!$B$74) -> 0 | D61: =SUMIFS('PLUMBING EST'!$N$7:$N$156,'PLUMBING EST'!$B$7:$B$156,"V",'PLUMBING EST'!$C$7:$C$156,INPUTS!$B$74)+SUMIFS('HVAC EST'!$N$7:$N$156,'HVAC EST'!$B$7:$B$156,"V",'HVAC EST'!$C$7:$C$156,INPUTS!$B$74) -> 0 | E61: =SUMIFS('PLUMBING EST'!$O$7:$O$156,'PLUMBING EST'!$B$7:$B$156,"V",'PLUMBING EST'!$C$7:$C$156,INPUTS!$B$74)+SUMIFS('HVAC EST'!$O$7:$O$156,'HVAC EST'!$B$7:$B$156,"V",'HVAC EST'!$C$7:$C$156,INPUTS!$B$74) -> 0 | F61: =SUMIFS('PLUMBING EST'!$L$7:$L$156,'PLUMBING EST'!$B$7:$B$156,"V",'PLUMBING EST'!$C$7:$C$156,INPUTS!$B$74)+SUMIFS('HVAC EST'!$L$7:$L$156,'HVAC EST'!$B$7:$B$156,"V",'HVAC EST'!$C$7:$C$156,INPUTS!$B$74) -> 0 | G61: =SUMIFS('SUBS & GC'!$O$7:$O$28,'SUBS & GC'!$D$7:$D$28,INPUTS!$B$74) -> 0 | H61: =SUMIFS('SUBS & GC'!$O$33:$O$60,'SUBS & GC'!$D$33:$D$60,INPUTS!$B$74) -> 0 | J61: =SUM(D61:H61) -> 0 | K61: =IFERROR(J61/$J$65,0) -> 0
B62: =INPUTS!$B$75 -> 09 Office, Supervision & General | C62: =SUMIFS('PLUMBING EST'!$M$7:$M$156,'PLUMBING EST'!$B$7:$B$156,"V",'PLUMBING EST'!$C$7:$C$156,INPUTS!$B$75)+SUMIFS('HVAC EST'!$M$7:$M$156,'HVAC EST'!$B$7:$B$156,"V",'HVAC EST'!$C$7:$C$156,INPUTS!$B$75) -> 0 | D62: =SUMIFS('PLUMBING EST'!$N$7:$N$156,'PLUMBING EST'!$B$7:$B$156,"V",'PLUMBING EST'!$C$7:$C$156,INPUTS!$B$75)+SUMIFS('HVAC EST'!$N$7:$N$156,'HVAC EST'!$B$7:$B$156,"V",'HVAC EST'!$C$7:$C$156,INPUTS!$B$75) -> 0 | E62: =SUMIFS('PLUMBING EST'!$O$7:$O$156,'PLUMBING EST'!$B$7:$B$156,"V",'PLUMBING EST'!$C$7:$C$156,INPUTS!$B$75)+SUMIFS('HVAC EST'!$O$7:$O$156,'HVAC EST'!$B$7:$B$156,"V",'HVAC EST'!$C$7:$C$156,INPUTS!$B$75) -> 0 | F62: =SUMIFS('PLUMBING EST'!$L$7:$L$156,'PLUMBING EST'!$B$7:$B$156,"V",'PLUMBING EST'!$C$7:$C$156,INPUTS!$B$75)+SUMIFS('HVAC EST'!$L$7:$L$156,'HVAC EST'!$B$7:$B$156,"V",'HVAC EST'!$C$7:$C$156,INPUTS!$B$75) -> 0 | G62: =SUMIFS('SUBS & GC'!$O$7:$O$28,'SUBS & GC'!$D$7:$D$28,INPUTS!$B$75) -> 0 | H62: =SUMIFS('SUBS & GC'!$O$33:$O$60,'SUBS & GC'!$D$33:$D$60,INPUTS!$B$75) -> 0 | J62: =SUM(D62:H62) -> 0 | K62: =IFERROR(J62/$J$65,0) -> 0
B63: Consumables allowance | F63: ='BID SUMMARY'!G8 -> 0 | J63: =F63 -> 0 | K63: =IFERROR(J63/$J$65,0) -> 0
B64: Contingency | J64: ='BID SUMMARY'!J8 -> 0 | K64: =IFERROR(J64/$J$65,0) -> 0
B65: TOTAL COST BUDGET | C65: =SUM(C54:C64) -> 0 | D65: =SUM(D54:D64) -> 0 | E65: =SUM(E54:E64) -> 0 | F65: =SUM(F54:F64) -> 0 | G65: =SUM(G54:G64) -> 0 | H65: =SUM(H54:H64) -> 0 | J65: =SUM(J54:J64) -> 0
B66: Margin (fee) | J66: ='BID SUMMARY'!O8 -> 0
B67: CONTRACT VALUE | J67: =J65+J66 -> 0
B71: =UPPER(INPUTS!B36)&" (AC)" -> AIR CONDITIONING (AC)
B72: Phase | C72: Hours | D72: Labour $ | E72: Overhead $ | F72: Material $ | G72: Subtrades $ | H72: Gen. Cond. $ | J72: TOTAL BUDGET $ | K72: % of Division
B73: =INPUTS!$B$67 -> 01 Shop Drawings, Permits & Mobilization | C73: =SUMIFS('PLUMBING EST'!$M$7:$M$156,'PLUMBING EST'!$B$7:$B$156,"AC",'PLUMBING EST'!$C$7:$C$156,INPUTS!$B$67)+SUMIFS('HVAC EST'!$M$7:$M$156,'HVAC EST'!$B$7:$B$156,"AC",'HVAC EST'!$C$7:$C$156,INPUTS!$B$67) -> 0 | D73: =SUMIFS('PLUMBING EST'!$N$7:$N$156,'PLUMBING EST'!$B$7:$B$156,"AC",'PLUMBING EST'!$C$7:$C$156,INPUTS!$B$67)+SUMIFS('HVAC EST'!$N$7:$N$156,'HVAC EST'!$B$7:$B$156,"AC",'HVAC EST'!$C$7:$C$156,INPUTS!$B$67) -> 0 | E73: =SUMIFS('PLUMBING EST'!$O$7:$O$156,'PLUMBING EST'!$B$7:$B$156,"AC",'PLUMBING EST'!$C$7:$C$156,INPUTS!$B$67)+SUMIFS('HVAC EST'!$O$7:$O$156,'HVAC EST'!$B$7:$B$156,"AC",'HVAC EST'!$C$7:$C$156,INPUTS!$B$67) -> 0 | F73: =SUMIFS('PLUMBING EST'!$L$7:$L$156,'PLUMBING EST'!$B$7:$B$156,"AC",'PLUMBING EST'!$C$7:$C$156,INPUTS!$B$67)+SUMIFS('HVAC EST'!$L$7:$L$156,'HVAC EST'!$B$7:$B$156,"AC",'HVAC EST'!$C$7:$C$156,INPUTS!$B$67) -> 0 | G73: =SUMIFS('SUBS & GC'!$P$7:$P$28,'SUBS & GC'!$D$7:$D$28,INPUTS!$B$67) -> 0 | H73: =SUMIFS('SUBS & GC'!$P$33:$P$60,'SUBS & GC'!$D$33:$D$60,INPUTS!$B$67) -> 0 | J73: =SUM(D73:H73) -> 0 | K73: =IFERROR(J73/$J$84,0) -> 0
B74: =INPUTS!$B$68 -> 02 Foundation & Underground | C74: =SUMIFS('PLUMBING EST'!$M$7:$M$156,'PLUMBING EST'!$B$7:$B$156,"AC",'PLUMBING EST'!$C$7:$C$156,INPUTS!$B$68)+SUMIFS('HVAC EST'!$M$7:$M$156,'HVAC EST'!$B$7:$B$156,"AC",'HVAC EST'!$C$7:$C$156,INPUTS!$B$68) -> 0 | D74: =SUMIFS('PLUMBING EST'!$N$7:$N$156,'PLUMBING EST'!$B$7:$B$156,"AC",'PLUMBING EST'!$C$7:$C$156,INPUTS!$B$68)+SUMIFS('HVAC EST'!$N$7:$N$156,'HVAC EST'!$B$7:$B$156,"AC",'HVAC EST'!$C$7:$C$156,INPUTS!$B$68) -> 0 | E74: =SUMIFS('PLUMBING EST'!$O$7:$O$156,'PLUMBING EST'!$B$7:$B$156,"AC",'PLUMBING EST'!$C$7:$C$156,INPUTS!$B$68)+SUMIFS('HVAC EST'!$O$7:$O$156,'HVAC EST'!$B$7:$B$156,"AC",'HVAC EST'!$C$7:$C$156,INPUTS!$B$68) -> 0 | F74: =SUMIFS('PLUMBING EST'!$L$7:$L$156,'PLUMBING EST'!$B$7:$B$156,"AC",'PLUMBING EST'!$C$7:$C$156,INPUTS!$B$68)+SUMIFS('HVAC EST'!$L$7:$L$156,'HVAC EST'!$B$7:$B$156,"AC",'HVAC EST'!$C$7:$C$156,INPUTS!$B$68) -> 0 | G74: =SUMIFS('SUBS & GC'!$P$7:$P$28,'SUBS & GC'!$D$7:$D$28,INPUTS!$B$68) -> 0 | H74: =SUMIFS('SUBS & GC'!$P$33:$P$60,'SUBS & GC'!$D$33:$D$60,INPUTS!$B$68) -> 0 | J74: =SUM(D74:H74) -> 0 | K74: =IFERROR(J74/$J$84,0) -> 0
B75: =INPUTS!$B$69 -> 03 Rough-in (Labour) | C75: =SUMIFS('PLUMBING EST'!$M$7:$M$156,'PLUMBING EST'!$B$7:$B$156,"AC",'PLUMBING EST'!$C$7:$C$156,INPUTS!$B$69)+SUMIFS('HVAC EST'!$M$7:$M$156,'HVAC EST'!$B$7:$B$156,"AC",'HVAC EST'!$C$7:$C$156,INPUTS!$B$69) -> 0 | D75: =SUMIFS('PLUMBING EST'!$N$7:$N$156,'PLUMBING EST'!$B$7:$B$156,"AC",'PLUMBING EST'!$C$7:$C$156,INPUTS!$B$69)+SUMIFS('HVAC EST'!$N$7:$N$156,'HVAC EST'!$B$7:$B$156,"AC",'HVAC EST'!$C$7:$C$156,INPUTS!$B$69) -> 0 | E75: =SUMIFS('PLUMBING EST'!$O$7:$O$156,'PLUMBING EST'!$B$7:$B$156,"AC",'PLUMBING EST'!$C$7:$C$156,INPUTS!$B$69)+SUMIFS('HVAC EST'!$O$7:$O$156,'HVAC EST'!$B$7:$B$156,"AC",'HVAC EST'!$C$7:$C$156,INPUTS!$B$69) -> 0 | F75: =0 -> 0 | G75: =SUMIFS('SUBS & GC'!$P$7:$P$28,'SUBS & GC'!$D$7:$D$28,INPUTS!$B$69) -> 0 | H75: =SUMIFS('SUBS & GC'!$P$33:$P$60,'SUBS & GC'!$D$33:$D$60,INPUTS!$B$69) -> 0 | J75: =SUM(D75:H75) -> 0 | K75: =IFERROR(J75/$J$84,0) -> 0
B76: =INPUTS!$B$70 -> 04 Finishing (Labour) | C76: =SUMIFS('PLUMBING EST'!$M$7:$M$156,'PLUMBING EST'!$B$7:$B$156,"AC",'PLUMBING EST'!$C$7:$C$156,INPUTS!$B$70)+SUMIFS('HVAC EST'!$M$7:$M$156,'HVAC EST'!$B$7:$B$156,"AC",'HVAC EST'!$C$7:$C$156,INPUTS!$B$70) -> 0 | D76: =SUMIFS('PLUMBING EST'!$N$7:$N$156,'PLUMBING EST'!$B$7:$B$156,"AC",'PLUMBING EST'!$C$7:$C$156,INPUTS!$B$70)+SUMIFS('HVAC EST'!$N$7:$N$156,'HVAC EST'!$B$7:$B$156,"AC",'HVAC EST'!$C$7:$C$156,INPUTS!$B$70) -> 0 | E76: =SUMIFS('PLUMBING EST'!$O$7:$O$156,'PLUMBING EST'!$B$7:$B$156,"AC",'PLUMBING EST'!$C$7:$C$156,INPUTS!$B$70)+SUMIFS('HVAC EST'!$O$7:$O$156,'HVAC EST'!$B$7:$B$156,"AC",'HVAC EST'!$C$7:$C$156,INPUTS!$B$70) -> 0 | F76: =0 -> 0 | G76: =SUMIFS('SUBS & GC'!$P$7:$P$28,'SUBS & GC'!$D$7:$D$28,INPUTS!$B$70) -> 0 | H76: =SUMIFS('SUBS & GC'!$P$33:$P$60,'SUBS & GC'!$D$33:$D$60,INPUTS!$B$70) -> 0 | J76: =SUM(D76:H76) -> 0 | K76: =IFERROR(J76/$J$84,0) -> 0
B77: =INPUTS!$B$71 -> 05 Material Supply | C77: =SUMIFS('PLUMBING EST'!$M$7:$M$156,'PLUMBING EST'!$B$7:$B$156,"AC",'PLUMBING EST'!$C$7:$C$156,INPUTS!$B$71)+SUMIFS('HVAC EST'!$M$7:$M$156,'HVAC EST'!$B$7:$B$156,"AC",'HVAC EST'!$C$7:$C$156,INPUTS!$B$71) -> 0 | D77: =SUMIFS('PLUMBING EST'!$N$7:$N$156,'PLUMBING EST'!$B$7:$B$156,"AC",'PLUMBING EST'!$C$7:$C$156,INPUTS!$B$71)+SUMIFS('HVAC EST'!$N$7:$N$156,'HVAC EST'!$B$7:$B$156,"AC",'HVAC EST'!$C$7:$C$156,INPUTS!$B$71) -> 0 | E77: =SUMIFS('PLUMBING EST'!$O$7:$O$156,'PLUMBING EST'!$B$7:$B$156,"AC",'PLUMBING EST'!$C$7:$C$156,INPUTS!$B$71)+SUMIFS('HVAC EST'!$O$7:$O$156,'HVAC EST'!$B$7:$B$156,"AC",'HVAC EST'!$C$7:$C$156,INPUTS!$B$71) -> 0 | F77: =SUMIFS('PLUMBING EST'!$L$7:$L$156,'PLUMBING EST'!$B$7:$B$156,"AC",'PLUMBING EST'!$C$7:$C$156,INPUTS!$B$71)+SUMIFS('HVAC EST'!$L$7:$L$156,'HVAC EST'!$B$7:$B$156,"AC",'HVAC EST'!$C$7:$C$156,INPUTS!$B$71)+SUMIFS('PLUMBING EST'!$L$7:$L$156,'PLUMBING EST'!$B$7:$B$156,"AC",'PLUMBING EST'!$C$7:$C$156,INPUTS!$B$69)+SUMIFS('HVAC EST'!$L$7:$L$156,'HVAC EST'!$B$7:$B$156,"AC",'HVAC EST'!$C$7:$C$156,INPUTS!$B$69)+SUMIFS('PLUMBING EST'!$L$7:$L$156,'PLUMBING EST'!$B$7:$B$156,"AC",'PLUMBING EST'!$C$7:$C$156,INPUTS!$B$70)+SUMIFS('HVAC EST'!$L$7:$L$156,'HVAC EST'!$B$7:$B$156,"AC",'HVAC EST'!$C$7:$C$156,INPUTS!$B$70) -> 0 | G77: =SUMIFS('SUBS & GC'!$P$7:$P$28,'SUBS & GC'!$D$7:$D$28,INPUTS!$B$71) -> 0 | H77: =SUMIFS('SUBS & GC'!$P$33:$P$60,'SUBS & GC'!$D$33:$D$60,INPUTS!$B$71) -> 0 | J77: =SUM(D77:H77) -> 0 | K77: =IFERROR(J77/$J$84,0) -> 0
B78: =INPUTS!$B$72 -> 06 Fixtures & Equipment Supply | C78: =SUMIFS('PLUMBING EST'!$M$7:$M$156,'PLUMBING EST'!$B$7:$B$156,"AC",'PLUMBING EST'!$C$7:$C$156,INPUTS!$B$72)+SUMIFS('HVAC EST'!$M$7:$M$156,'HVAC EST'!$B$7:$B$156,"AC",'HVAC EST'!$C$7:$C$156,INPUTS!$B$72) -> 0 | D78: =SUMIFS('PLUMBING EST'!$N$7:$N$156,'PLUMBING EST'!$B$7:$B$156,"AC",'PLUMBING EST'!$C$7:$C$156,INPUTS!$B$72)+SUMIFS('HVAC EST'!$N$7:$N$156,'HVAC EST'!$B$7:$B$156,"AC",'HVAC EST'!$C$7:$C$156,INPUTS!$B$72) -> 0 | E78: =SUMIFS('PLUMBING EST'!$O$7:$O$156,'PLUMBING EST'!$B$7:$B$156,"AC",'PLUMBING EST'!$C$7:$C$156,INPUTS!$B$72)+SUMIFS('HVAC EST'!$O$7:$O$156,'HVAC EST'!$B$7:$B$156,"AC",'HVAC EST'!$C$7:$C$156,INPUTS!$B$72) -> 0 | F78: =SUMIFS('PLUMBING EST'!$L$7:$L$156,'PLUMBING EST'!$B$7:$B$156,"AC",'PLUMBING EST'!$C$7:$C$156,INPUTS!$B$72)+SUMIFS('HVAC EST'!$L$7:$L$156,'HVAC EST'!$B$7:$B$156,"AC",'HVAC EST'!$C$7:$C$156,INPUTS!$B$72) -> 0 | G78: =SUMIFS('SUBS & GC'!$P$7:$P$28,'SUBS & GC'!$D$7:$D$28,INPUTS!$B$72) -> 0 | H78: =SUMIFS('SUBS & GC'!$P$33:$P$60,'SUBS & GC'!$D$33:$D$60,INPUTS!$B$72) -> 0 | J78: =SUM(D78:H78) -> 0 | K78: =IFERROR(J78/$J$84,0) -> 0
B79: =INPUTS!$B$73 -> 07 Testing, TAB & Commissioning | C79: =SUMIFS('PLUMBING EST'!$M$7:$M$156,'PLUMBING EST'!$B$7:$B$156,"AC",'PLUMBING EST'!$C$7:$C$156,INPUTS!$B$73)+SUMIFS('HVAC EST'!$M$7:$M$156,'HVAC EST'!$B$7:$B$156,"AC",'HVAC EST'!$C$7:$C$156,INPUTS!$B$73) -> 0 | D79: =SUMIFS('PLUMBING EST'!$N$7:$N$156,'PLUMBING EST'!$B$7:$B$156,"AC",'PLUMBING EST'!$C$7:$C$156,INPUTS!$B$73)+SUMIFS('HVAC EST'!$N$7:$N$156,'HVAC EST'!$B$7:$B$156,"AC",'HVAC EST'!$C$7:$C$156,INPUTS!$B$73) -> 0 | E79: =SUMIFS('PLUMBING EST'!$O$7:$O$156,'PLUMBING EST'!$B$7:$B$156,"AC",'PLUMBING EST'!$C$7:$C$156,INPUTS!$B$73)+SUMIFS('HVAC EST'!$O$7:$O$156,'HVAC EST'!$B$7:$B$156,"AC",'HVAC EST'!$C$7:$C$156,INPUTS!$B$73) -> 0 | F79: =SUMIFS('PLUMBING EST'!$L$7:$L$156,'PLUMBING EST'!$B$7:$B$156,"AC",'PLUMBING EST'!$C$7:$C$156,INPUTS!$B$73)+SUMIFS('HVAC EST'!$L$7:$L$156,'HVAC EST'!$B$7:$B$156,"AC",'HVAC EST'!$C$7:$C$156,INPUTS!$B$73) -> 0 | G79: =SUMIFS('SUBS & GC'!$P$7:$P$28,'SUBS & GC'!$D$7:$D$28,INPUTS!$B$73) -> 0 | H79: =SUMIFS('SUBS & GC'!$P$33:$P$60,'SUBS & GC'!$D$33:$D$60,INPUTS!$B$73) -> 0 | J79: =SUM(D79:H79) -> 0 | K79: =IFERROR(J79/$J$84,0) -> 0
B80: =INPUTS!$B$74 -> 08 Completion & Final Documents | C80: =SUMIFS('PLUMBING EST'!$M$7:$M$156,'PLUMBING EST'!$B$7:$B$156,"AC",'PLUMBING EST'!$C$7:$C$156,INPUTS!$B$74)+SUMIFS('HVAC EST'!$M$7:$M$156,'HVAC EST'!$B$7:$B$156,"AC",'HVAC EST'!$C$7:$C$156,INPUTS!$B$74) -> 0 | D80: =SUMIFS('PLUMBING EST'!$N$7:$N$156,'PLUMBING EST'!$B$7:$B$156,"AC",'PLUMBING EST'!$C$7:$C$156,INPUTS!$B$74)+SUMIFS('HVAC EST'!$N$7:$N$156,'HVAC EST'!$B$7:$B$156,"AC",'HVAC EST'!$C$7:$C$156,INPUTS!$B$74) -> 0 | E80: =SUMIFS('PLUMBING EST'!$O$7:$O$156,'PLUMBING EST'!$B$7:$B$156,"AC",'PLUMBING EST'!$C$7:$C$156,INPUTS!$B$74)+SUMIFS('HVAC EST'!$O$7:$O$156,'HVAC EST'!$B$7:$B$156,"AC",'HVAC EST'!$C$7:$C$156,INPUTS!$B$74) -> 0 | F80: =SUMIFS('PLUMBING EST'!$L$7:$L$156,'PLUMBING EST'!$B$7:$B$156,"AC",'PLUMBING EST'!$C$7:$C$156,INPUTS!$B$74)+SUMIFS('HVAC EST'!$L$7:$L$156,'HVAC EST'!$B$7:$B$156,"AC",'HVAC EST'!$C$7:$C$156,INPUTS!$B$74) -> 0 | G80: =SUMIFS('SUBS & GC'!$P$7:$P$28,'SUBS & GC'!$D$7:$D$28,INPUTS!$B$74) -> 0 | H80: =SUMIFS('SUBS & GC'!$P$33:$P$60,'SUBS & GC'!$D$33:$D$60,INPUTS!$B$74) -> 0 | J80: =SUM(D80:H80) -> 0 | K80: =IFERROR(J80/$J$84,0) -> 0
B81: =INPUTS!$B$75 -> 09 Office, Supervision & General | C81: =SUMIFS('PLUMBING EST'!$M$7:$M$156,'PLUMBING EST'!$B$7:$B$156,"AC",'PLUMBING EST'!$C$7:$C$156,INPUTS!$B$75)+SUMIFS('HVAC EST'!$M$7:$M$156,'HVAC EST'!$B$7:$B$156,"AC",'HVAC EST'!$C$7:$C$156,INPUTS!$B$75) -> 0 | D81: =SUMIFS('PLUMBING EST'!$N$7:$N$156,'PLUMBING EST'!$B$7:$B$156,"AC",'PLUMBING EST'!$C$7:$C$156,INPUTS!$B$75)+SUMIFS('HVAC EST'!$N$7:$N$156,'HVAC EST'!$B$7:$B$156,"AC",'HVAC EST'!$C$7:$C$156,INPUTS!$B$75) -> 0 | E81: =SUMIFS('PLUMBING EST'!$O$7:$O$156,'PLUMBING EST'!$B$7:$B$156,"AC",'PLUMBING EST'!$C$7:$C$156,INPUTS!$B$75)+SUMIFS('HVAC EST'!$O$7:$O$156,'HVAC EST'!$B$7:$B$156,"AC",'HVAC EST'!$C$7:$C$156,INPUTS!$B$75) -> 0 | F81: =SUMIFS('PLUMBING EST'!$L$7:$L$156,'PLUMBING EST'!$B$7:$B$156,"AC",'PLUMBING EST'!$C$7:$C$156,INPUTS!$B$75)+SUMIFS('HVAC EST'!$L$7:$L$156,'HVAC EST'!$B$7:$B$156,"AC",'HVAC EST'!$C$7:$C$156,INPUTS!$B$75) -> 0 | G81: =SUMIFS('SUBS & GC'!$P$7:$P$28,'SUBS & GC'!$D$7:$D$28,INPUTS!$B$75) -> 0 | H81: =SUMIFS('SUBS & GC'!$P$33:$P$60,'SUBS & GC'!$D$33:$D$60,INPUTS!$B$75) -> 0 | J81: =SUM(D81:H81) -> 0 | K81: =IFERROR(J81/$J$84,0) -> 0
B82: Consumables allowance | F82: ='BID SUMMARY'!G9 -> 0 | J82: =F82 -> 0 | K82: =IFERROR(J82/$J$84,0) -> 0
B83: Contingency | J83: ='BID SUMMARY'!J9 -> 0 | K83: =IFERROR(J83/$J$84,0) -> 0
B84: TOTAL COST BUDGET | C84: =SUM(C73:C83) -> 0 | D84: =SUM(D73:D83) -> 0 | E84: =SUM(E73:E83) -> 0 | F84: =SUM(F73:F83) -> 0 | G84: =SUM(G73:G83) -> 0 | H84: =SUM(H73:H83) -> 0 | J84: =SUM(J73:J83) -> 0
B85: Margin (fee) | J85: ='BID SUMMARY'!O9 -> 0
B86: CONTRACT VALUE | J86: =J84+J85 -> 0

Sheet SCHEDULE OF VALUES
A1: SCHEDULE OF VALUES
A2: =IF(INPUTS!C4="","",INPUTS!C4)&" "&INPUTS!C11&", "&INPUTS!C12&" GC: "&INPUTS!C8 -> 2650 East 41st Ave, Vancouver GC:
B4: Contract value (from BID SUMMARY) | C4: ='BID SUMMARY'!N10 -> 488800
B5: Total of schedule below | C5: =C325 -> 488800 | D5: =IF(ABS(C5-C4)<1,"OK","CHECK") -> OK
B6: Line names follow your Knowify setup. Columns J:N are the cost budget for the same line, ready to load into Knowify.
J7: KNOWIFY COST BUDGET (no overhead, no margin)
A8: Item # | B8: Job Phase / Contract Item | C8: Scheduled Value $ | D8: % of Contract | E8: Completed to Date $ | F8: % Complete | G8: Balance to Finish $ | H8: Holdback $ | J8: Material $ | K8: Labour $ | L8: Subtrades $ | M8: Other $ | N8: Hours | P8: Div factor
A9: P | B9: =UPPER(INPUTS!B33) -> PLUMBING | C9: =SUM(C10:C86) -> 488800 | D9: =IFERROR(C9/$C$4,0) -> 1 | E9: =SUM(E10:E86) -> 0 | G9: =SUM(G10:G86) -> 488800 | H9: =SUM(H10:H86) -> 0 | J9: =SUM(J10:J86) -> 107393.76 | K9: =SUM(K10:K86) -> 95563.62 | L9: =SUM(L10:L86) -> 0 | M9: =SUM(M10:M86) -> 180000 | N9: =SUM(N10:N86) -> 1476 | P9: =IFERROR('BID SUMMARY'!N6/(BUDGET!$J$16+BUDGET!$J$17+BUDGET!$J$18+BUDGET!$J$19+BUDGET!$J$20+BUDGET!$J$21+BUDGET!$J$22+BUDGET!$J$23+BUDGET!$J$24),0) -> 1.1826084
A10: P-01 | B10: ="P - "&MID(INPUTS!$B$67,4,80) -> P - Shop Drawings, Permits & Mobilization | C10: =(BUDGET!$J$16-BUDGET!$G$16)*$P$9 -> 0 | D10: =IFERROR(C10/$C$4,0) -> 0 | F10: =IFERROR(E10/C10,0) -> 0 | G10: =C10-E10 -> 0 | H10: =E10*INPUTS!$C$29 -> 0 | J10: =BUDGET!$F$16 -> 0 | K10: =BUDGET!$D$16 -> 0 | M10: =BUDGET!$H$16 -> 0 | N10: =BUDGET!$C$16 -> 0
A11: P-02 | B11: ="P - "&MID(INPUTS!$B$68,4,80) -> P - Foundation & Underground | C11: =(BUDGET!$J$17-BUDGET!$G$17)*$P$9 -> 0 | D11: =IFERROR(C11/$C$4,0) -> 0 | F11: =IFERROR(E11/C11,0) -> 0 | G11: =C11-E11 -> 0 | H11: =E11*INPUTS!$C$29 -> 0 | J11: =BUDGET!$F$17 -> 0 | K11: =BUDGET!$D$17 -> 0 | M11: =BUDGET!$H$17 -> 0 | N11: =BUDGET!$C$17 -> 0
A12: P-03-01 | B12: =IF(INPUTS!$B$40="","","P - "&INPUTS!$B$40&" "&INPUTS!$B$33&" Rough-in (Labour)") -> P - U/G Plumbing Rough-in (Labour) | C12: =(BUDGET!$J$18-BUDGET!$G$18)*INPUTS!$E$40*$P$9 -> 0 | D12: =IFERROR(C12/$C$4,0) -> 0 | F12: =IFERROR(E12/C12,0) -> 0 | G12: =C12-E12 -> 0 | H12: =E12*INPUTS!$C$29 -> 0 | K12: =BUDGET!$D$18*INPUTS!$E$40 -> 0 | M12: =BUDGET!$H$18*INPUTS!$E$40 -> 0 | N12: =BUDGET!$C$18*INPUTS!$E$40 -> 0
A13: P-03-02 | B13: =IF(INPUTS!$B$41="","","P - "&INPUTS!$B$41&" "&INPUTS!$B$33&" Rough-in (Labour)") -> P - P-02 Plumbing Rough-in (Labour) | C13: =(BUDGET!$J$18-BUDGET!$G$18)*INPUTS!$E$41*$P$9 -> 0 | D13: =IFERROR(C13/$C$4,0) -> 0 | F13: =IFERROR(E13/C13,0) -> 0 | G13: =C13-E13 -> 0 | H13: =E13*INPUTS!$C$29 -> 0 | K13: =BUDGET!$D$18*INPUTS!$E$41 -> 0 | M13: =BUDGET!$H$18*INPUTS!$E$41 -> 0 | N13: =BUDGET!$C$18*INPUTS!$E$41 -> 0
A14: P-03-03 | B14: =IF(INPUTS!$B$42="","","P - "&INPUTS!$B$42&" "&INPUTS!$B$33&" Rough-in (Labour)") -> P - PRKG Plumbing Rough-in (Labour) | C14: =(BUDGET!$J$18-BUDGET!$G$18)*INPUTS!$E$42*$P$9 -> 0 | D14: =IFERROR(C14/$C$4,0) -> 0 | F14: =IFERROR(E14/C14,0) -> 0 | G14: =C14-E14 -> 0 | H14: =E14*INPUTS!$C$29 -> 0 | K14: =BUDGET!$D$18*INPUTS!$E$42 -> 0 | M14: =BUDGET!$H$18*INPUTS!$E$42 -> 0 | N14: =BUDGET!$C$18*INPUTS!$E$42 -> 0
A15: P-03-04 | B15: =IF(INPUTS!$B$43="","","P - "&INPUTS!$B$43&" "&INPUTS!$B$33&" Rough-in (Labour)") -> P - L-01 Plumbing Rough-in (Labour) | C15: =(BUDGET!$J$18-BUDGET!$G$18)*INPUTS!$E$43*$P$9 -> 29544.586 | D15: =IFERROR(C15/$C$4,0) -> 0.060443098 | F15: =IFERROR(E15/C15,0) -> 0 | G15: =C15-E15 -> 29544.586 | H15: =E15*INPUTS!$C$29 -> 0 | K15: =BUDGET!$D$18*INPUTS!$E$43 -> 18646.56 | M15: =BUDGET!$H$18*INPUTS!$E$43 -> 0 | N15: =BUDGET!$C$18*INPUTS!$E$43 -> 288
A16: P-03-05 | B16: =IF(INPUTS!$B$44="","","P - "&INPUTS!$B$44&" "&INPUTS!$B$33&" Rough-in (Labour)") -> P - L-02 Plumbing Rough-in (Labour) | C16: =(BUDGET!$J$18-BUDGET!$G$18)*INPUTS!$E$44*$P$9 -> 30775.611 | D16: =IFERROR(C16/$C$4,0) -> 0.06296156 | F16: =IFERROR(E16/C16,0) -> 0 | G16: =C16-E16 -> 30775.611 | H16: =E16*INPUTS!$C$29 -> 0 | K16: =BUDGET!$D$18*INPUTS!$E$44 -> 19423.5 | M16: =BUDGET!$H$18*INPUTS!$E$44 -> 0 | N16: =BUDGET!$C$18*INPUTS!$E$44 -> 300
A17: P-03-06 | B17: =IF(INPUTS!$B$45="","","P - "&INPUTS!$B$45&" "&INPUTS!$B$33&" Rough-in (Labour)") -> P - L-03 Plumbing Rough-in (Labour) | C17: =(BUDGET!$J$18-BUDGET!$G$18)*INPUTS!$E$45*$P$9 -> 30775.611 | D17: =IFERROR(C17/$C$4,0) -> 0.06296156 | F17: =IFERROR(E17/C17,0) -> 0 | G17: =C17-E17 -> 30775.611 | H17: =E17*INPUTS!$C$29 -> 0 | K17: =BUDGET!$D$18*INPUTS!$E$45 -> 19423.5 | M17: =BUDGET!$H$18*INPUTS!$E$45 -> 0 | N17: =BUDGET!$C$18*INPUTS!$E$45 -> 300
A18: P-03-07 | B18: =IF(INPUTS!$B$46="","","P - "&INPUTS!$B$46&" "&INPUTS!$B$33&" Rough-in (Labour)") -> P - L-04 Plumbing Rough-in (Labour) | C18: =(BUDGET!$J$18-BUDGET!$G$18)*INPUTS!$E$46*$P$9 -> 30775.611 | D18: =IFERROR(C18/$C$4,0) -> 0.06296156 | F18: =IFERROR(E18/C18,0) -> 0 | G18: =C18-E18 -> 30775.611 | H18: =E18*INPUTS!$C$29 -> 0 | K18: =BUDGET!$D$18*INPUTS!$E$46 -> 19423.5 | M18: =BUDGET!$H$18*INPUTS!$E$46 -> 0 | N18: =BUDGET!$C$18*INPUTS!$E$46 -> 300
A19: P-03-08 | B19: =IF(INPUTS!$B$47="","","P - "&INPUTS!$B$47&" "&INPUTS!$B$33&" Rough-in (Labour)") -> P - L-05 Plumbing Rough-in (Labour) | C19: =(BUDGET!$J$18-BUDGET!$G$18)*INPUTS!$E$47*$P$9 -> 29544.586 | D19: =IFERROR(C19/$C$4,0) -> 0.060443098 | F19: =IFERROR(E19/C19,0) -> 0 | G19: =C19-E19 -> 29544.586 | H19: =E19*INPUTS!$C$29 -> 0 | K19: =BUDGET!$D$18*INPUTS!$E$47 -> 18646.56 | M19: =BUDGET!$H$18*INPUTS!$E$47 -> 0 | N19: =BUDGET!$C$18*INPUTS!$E$47 -> 288
A20: P-03-09 | B20: =IF(INPUTS!$B$48="","","P - "&INPUTS!$B$48&" "&INPUTS!$B$33&" Rough-in (Labour)") -> P - L-06 Plumbing Rough-in (Labour) | C20: =(BUDGET!$J$18-BUDGET!$G$18)*INPUTS!$E$48*$P$9 -> 0 | D20: =IFERROR(C20/$C$4,0) -> 0 | F20: =IFERROR(E20/C20,0) -> 0 | G20: =C20-E20 -> 0 | H20: =E20*INPUTS!$C$29 -> 0 | K20: =BUDGET!$D$18*INPUTS!$E$48 -> 0 | M20: =BUDGET!$H$18*INPUTS!$E$48 -> 0 | N20: =BUDGET!$C$18*INPUTS!$E$48 -> 0
A21: P-03-10 | B21: =IF(INPUTS!$B$49="","","P - "&INPUTS!$B$49&" "&INPUTS!$B$33&" Rough-in (Labour)") -> P - L-07 Plumbing Rough-in (Labour) | C21: =(BUDGET!$J$18-BUDGET!$G$18)*INPUTS!$E$49*$P$9 -> 0 | D21: =IFERROR(C21/$C$4,0) -> 0 | F21: =IFERROR(E21/C21,0) -> 0 | G21: =C21-E21 -> 0 | H21: =E21*INPUTS!$C$29 -> 0 | K21: =BUDGET!$D$18*INPUTS!$E$49 -> 0 | M21: =BUDGET!$H$18*INPUTS!$E$49 -> 0 | N21: =BUDGET!$C$18*INPUTS!$E$49 -> 0
A22: P-03-11 | B22: =IF(INPUTS!$B$50="","","P - "&INPUTS!$B$50&" "&INPUTS!$B$33&" Rough-in (Labour)") -> P - L-08 Plumbing Rough-in (Labour) | C22: =(BUDGET!$J$18-BUDGET!$G$18)*INPUTS!$E$50*$P$9 -> 0 | D22: =IFERROR(C22/$C$4,0) -> 0 | F22: =IFERROR(E22/C22,0) -> 0 | G22: =C22-E22 -> 0 | H22: =E22*INPUTS!$C$29 -> 0 | K22: =BUDGET!$D$18*INPUTS!$E$50 -> 0 | M22: =BUDGET!$H$18*INPUTS!$E$50 -> 0 | N22: =BUDGET!$C$18*INPUTS!$E$50 -> 0
A23: P-03-12 | B23: =IF(INPUTS!$B$51="","","P - "&INPUTS!$B$51&" "&INPUTS!$B$33&" Rough-in (Labour)") -> P - L-09 Plumbing Rough-in (Labour) | C23: =(BUDGET!$J$18-BUDGET!$G$18)*INPUTS!$E$51*$P$9 -> 0 | D23: =IFERROR(C23/$C$4,0) -> 0 | F23: =IFERROR(E23/C23,0) -> 0 | G23: =C23-E23 -> 0 | H23: =E23*INPUTS!$C$29 -> 0 | K23: =BUDGET!$D$18*INPUTS!$E$51 -> 0 | M23: =BUDGET!$H$18*INPUTS!$E$51 -> 0 | N23: =BUDGET!$C$18*INPUTS!$E$51 -> 0
A24: P-03-13 | B24: =IF(INPUTS!$B$52="","","P - "&INPUTS!$B$52&" "&INPUTS!$B$33&" Rough-in (Labour)") -> P - L-10 Plumbing Rough-in (Labour) | C24: =(BUDGET!$J$18-BUDGET!$G$18)*INPUTS!$E$52*$P$9 -> 0 | D24: =IFERROR(C24/$C$4,0) -> 0 | F24: =IFERROR(E24/C24,0) -> 0 | G24: =C24-E24 -> 0 | H24: =E24*INPUTS!$C$29 -> 0 | K24: =BUDGET!$D$18*INPUTS!$E$52 -> 0 | M24: =BUDGET!$H$18*INPUTS!$E$52 -> 0 | N24: =BUDGET!$C$18*INPUTS!$E$52 -> 0
